Workbook

Sheet Distribution
A1: Exp Level | B1: (Multiple Items)
A3: Count of Job Title | B3: Column Labels
A4: Row Labels | B4: Data Analyst | C4: Data Engineer | D4: Data Scientist | E4: Director/VP | F4: DS Manager | G4: ML Engineer | H4: Research Scientist | I4: Grand Total
A5: $100–125K | B5: 3 | C5: 17 | D5: 33 | G5: 4 | H5: 3 | I5: 60
A6: $125–150K | B6: 2 | C6: 7 | D6: 46 | E6: 2 | G6: 2 | H6: 1 | I6: 60
A7: $50–75K | B7: 14 | C7: 2 | D7: 9 | G7: 2 | H7: 4 | I7: 31
A8: $75–100K | B8: 7 | C8: 7 | D8: 28 | G8: 3 | H8: 1 | I8: 46
A9: <$50K | B9: 9 | I9: 9
A10: >$150K | C10: 9 | D10: 31 | F10: 2 | G10: 1 | H10: 1 | I10: 44
A11: Grand Total | B11: 35 | C11: 42 | D11: 147 | E11: 2 | F11: 2 | G11: 12 | H11: 10 | I11: 250

Sheet data_cleaned_2021
A1: Job Title | B1: Exp Level | C1: Job Category | D1: Rating | E1: Location | F1: City | G1: Size | H1: Industry | I1: Lower Salary(in K) | J1: Upper Salary(in K ) | K1: Avg Salary(K) | L1: Salary Range | M1: Age
A2: Data Scientist | B2: =IF(OR(ISNUMBER(SEARCH("Senior",A2)),ISNUMBER(SEARCH("Sr",A2)),ISNUMBER(SEARCH("Lead",A2)),ISNUMBER(SEARCH("Principal",A2))),"Senior",IF(OR(ISNUMBER(SEARCH("Junior",A2)),ISNUMBER(SEARCH("Jr",A2)),ISNUMBER(SEARCH("Entry",A2)),ISNUMBER(SEARCH("Associate",A2))),"Junior",IF(OR(ISNUMBER(SEARCH("Manager",A2)),ISNUMBER(SEARCH("Director",A2)),ISNUMBER(SEARCH("Head",A2)),ISNUMBER(SEARCH("VP",A2))),"Management","Mid-Level"))) -> Mid-Level | C2: =IF(ISNUMBER(SEARCH("Machine Learn",A2)),"ML Engineer",IF(ISNUMBER(SEARCH("Data Engineer",A2)),"Data Engineer",IF(ISNUMBER(SEARCH("Data Analyst",A2)),"Data Analyst",IF(ISNUMBER(SEARCH("Business Analyst",A2)),"Business Analyst",IF(ISNUMBER(SEARCH("Research",A2)),"Research Scientist",IF(ISNUMBER(SEARCH("Manager",A2)),"DS Manager",IF(ISNUMBER(SEARCH("Director",A2)),"Director/VP","Data Scientist"))))))) -> Data Scientist | D2: 3.8 | E2: Albuquerque, NM | F2: =IFERROR(LEFT(E2, FIND(",", E2)-1), E2) -> Albuquerque | G2: 501 - 1000 | H2: Aerospace & Defense | I2: 53 | J2: 91 | K2: 72 | L2: =IF(K2<50,"<$50K",IF(K2<75,"$50–75K",IF(K2<100,"$75–100K",IF(K2<125,"$100–125K",IF(K2<150,"$125–150K",">$150K"))))) -> $50–75K | M2: 48
A3: Healthcare Data Scientist | B3: =IF(OR(ISNUMBER(SEARCH("Senior",A3)),ISNUMBER(SEARCH("Sr",A3)),ISNUMBER(SEARCH("Lead",A3)),ISNUMBER(SEARCH("Principal",A3))),"Senior",IF(OR(ISNUMBER(SEARCH("Junior",A3)),ISNUMBER(SEARCH("Jr",A3)),ISNUMBER(SEARCH("Entry",A3)),ISNUMBER(SEARCH("Associate",A3))),"Junior",IF(OR(ISNUMBER(SEARCH("Manager",A3)),ISNUMBER(SEARCH("Director",A3)),ISNUMBER(SEARCH("Head",A3)),ISNUMBER(SEARCH("VP",A3))),"Management","Mid-Level"))) -> Mid-Level | C3: =IF(ISNUMBER(SEARCH("Machine Learn",A3)),"ML Engineer",IF(ISNUMBER(SEARCH("Data Engineer",A3)),"Data Engineer",IF(ISNUMBER(SEARCH("Data Analyst",A3)),"Data Analyst",IF(ISNUMBER(SEARCH("Business Analyst",A3)),"Business Analyst",IF(ISNUMBER(SEARCH("Research",A3)),"Research Scientist",IF(ISNUMBER(SEARCH("Manager",A3)),"DS Manager",IF(ISNUMBER(SEARCH("Director",A3)),"Director/VP","Data Scientist"))))))) -> Data Scientist | D3: 3.4 | E3: Linthicum, MD | F3: =IFERROR(LEFT(E3, FIND(",", E3)-1), E3) -> Linthicum | G3: 10000+ | H3: Health Care Services & Hospitals | I3: 63 | J3: 112 | K3: 87.5 | L3: =IF(K3<50,"<$50K",IF(K3<75,"$50–75K",IF(K3<100,"$75–100K",IF(K3<125,"$100–125K",IF(K3<150,"$125–150K",">$150K"))))) -> $75–100K | M3: 37
A4: Data Scientist | B4: =IF(OR(ISNUMBER(SEARCH("Senior",A4)),ISNUMBER(SEARCH("Sr",A4)),ISNUMBER(SEARCH("Lead",A4)),ISNUMBER(SEARCH("Principal",A4))),"Senior",IF(OR(ISNUMBER(SEARCH("Junior",A4)),ISNUMBER(SEARCH("Jr",A4)),ISNUMBER(SEARCH("Entry",A4)),ISNUMBER(SEARCH("Associate",A4))),"Junior",IF(OR(ISNUMBER(SEARCH("Manager",A4)),ISNUMBER(SEARCH("Director",A4)),ISNUMBER(SEARCH("Head",A4)),ISNUMBER(SEARCH("VP",A4))),"Management","Mid-Level"))) -> Mid-Level | C4: =IF(ISNUMBER(SEARCH("Machine Learn",A4)),"ML Engineer",IF(ISNUMBER(SEARCH("Data Engineer",A4)),"Data Engineer",IF(ISNUMBER(SEARCH("Data Analyst",A4)),"Data Analyst",IF(ISNUMBER(SEARCH("Business Analyst",A4)),"Business Analyst",IF(ISNUMBER(SEARCH("Research",A4)),"Research Scientist",IF(ISNUMBER(SEARCH("Manager",A4)),"DS Manager",IF(ISNUMBER(SEARCH("Director",A4)),"Director/VP","Data Scientist"))))))) -> Data Scientist | D4: 4.8 | E4: Clearwater, FL | F4: =IFERROR(LEFT(E4, FIND(",", E4)-1), E4) -> Clearwater | G4: 501 - 1000 | H4: Security Services | I4: 80 | J4: 90 | K4: 85 | L4: =IF(K4<50,"<$50K",IF(K4<75,"$50–75K",IF(K4<100,"$75–100K",IF(K4<125,"$100–125K",IF(K4<150,"$125–150K",">$150K"))))) -> $75–100K | M4: 11
A5: Data Scientist | B5: =IF(OR(ISNUMBER(SEARCH("Senior",A5)),ISNUMBER(SEARCH("Sr",A5)),ISNUMBER(SEARCH("Lead",A5)),ISNUMBER(SEARCH("Principal",A5))),"Senior",IF(OR(ISNUMBER(SEARCH("Junior",A5)),ISNUMBER(SEARCH("Jr",A5)),ISNUMBER(SEARCH("Entry",A5)),ISNUMBER(SEARCH("Associate",A5))),"Junior",IF(OR(ISNUMBER(SEARCH("Manager",A5)),ISNUMBER(SEARCH("Director",A5)),ISNUMBER(SEARCH("Head",A5)),ISNUMBER(SEARCH("VP",A5))),"Management","Mid-Level"))) -> Mid-Level | C5: =IF(ISNUMBER(SEARCH("Machine Learn",A5)),"ML Engineer",IF(ISNUMBER(SEARCH("Data Engineer",A5)),"Data Engineer",IF(ISNUMBER(SEARCH("Data Analyst",A5)),"Data Analyst",IF(ISNUMBER(SEARCH("Business Analyst",A5)),"Business Analyst",IF(ISNUMBER(SEARCH("Research",A5)),"Research Scientist",IF(ISNUMBER(SEARCH("Manager",A5)),"DS Manager",IF(ISNUMBER(SEARCH("Director",A5)),"Director/VP","Data Scientist"))))))) -> Data Scientist | D5: 3.8 | E5: Richland, WA | F5: =IFERROR(LEFT(E5, FIND(",", E5)-1), E5) -> Richland | G5: 1001 - 5000 | H5: Energy | I5: 56 | J5: 97 | K5: 76.5 | L5: =IF(K5<50,"<$50K",IF(K5<75,"$50–75K",IF(K5<100,"$75–100K",IF(K5<125,"$100–125K",IF(K5<150,"$125–150K",">$150K"))))) -> $75–100K | M5: 56
A6: Data Scientist | B6: =IF(OR(ISNUMBER(SEARCH("Senior",A6)),ISNUMBER(SEARCH("Sr",A6)),ISNUMBER(SEARCH("Lead",A6)),ISNUMBER(SEARCH("Principal",A6))),"Senior",IF(OR(ISNUMBER(SEARCH("Junior",A6)),ISNUMBER(SEARCH("Jr",A6)),ISNUMBER(SEARCH("Entry",A6)),ISNUMBER(SEARCH("Associate",A6))),"Junior",IF(OR(ISNUMBER(SEARCH("Manager",A6)),ISNUMBER(SEARCH("Director",A6)),ISNUMBER(SEARCH("Head",A6)),ISNUMBER(SEARCH("VP",A6))),"Management","Mid-Level"))) -> Mid-Level | C6: =IF(ISNUMBER(SEARCH("Machine Learn",A6)),"ML Engineer",IF(ISNUMBER(SEARCH("Data Engineer",A6)),"Data Engineer",IF(ISNUMBER(SEARCH("Data Analyst",A6)),"Data Analyst",IF(ISNUMBER(SEARCH("Business Analyst",A6)),"Business Analyst",IF(ISNUMBER(SEARCH("Research",A6)),"Research Scientist",IF(ISNUMBER(SEARCH("Manager",A6)),"DS Manager",IF(ISNUMBER(SEARCH("Director",A6)),"Director/VP","Data Scientist"))))))) -> Data Scientist | D6: 2.9 | E6: New York, NY | F6: =IFERROR(LEFT(E6, FIND(",", E6)-1), E6) -> New York | G6: 51 - 200 | H6: Advertising & Marketing | I6: 86 | J6: 143 | K6: 114.5 | L6: =IF(K6<50,"<$50K",IF(K6<75,"$50–75K",IF(K6<100,"$75–100K",IF(K6<125,"$100–125K",IF(K6<150,"$125–150K",">$150K"))))) -> $100–125K | M6: 23
A7: Data Scientist | B7: =IF(OR(ISNUMBER(SEARCH("Senior",A7)),ISNUMBER(SEARCH("Sr",A7)),ISNUMBER(SEARCH("Lead",A7)),ISNUMBER(SEARCH("Principal",A7))),"Senior",IF(OR(ISNUMBER(SEARCH("Junior",A7)),ISNUMBER(SEARCH("Jr",A7)),ISNUMBER(SEARCH("Entry",A7)),ISNUMBER(SEARCH("Associate",A7))),"Junior",IF(OR(ISNUMBER(SEARCH("Manager",A7)),ISNUMBER(SEARCH("Director",A7)),ISNUMBER(SEARCH("Head",A7)),ISNUMBER(SEARCH("VP",A7))),"Management","Mid-Level"))) -> Mid-Level | C7: =IF(ISNUMBER(SEARCH("Machine Learn",A7)),"ML Engineer",IF(ISNUMBER(SEARCH("Data Engineer",A7)),"Data Engineer",IF(ISNUMBER(SEARCH("Data Analyst",A7)),"Data Analyst",IF(ISNUMBER(SEARCH("Business Analyst",A7)),"Business Analyst",IF(ISNUMBER(SEARCH("Research",A7)),"Research Scientist",IF(ISNUMBER(SEARCH("Manager",A7)),"DS Manager",IF(ISNUMBER(SEARCH("Director",A7)),"Director/VP","Data Scientist"))))))) -> Data Scientist | D7: 3.4 | E7: Dallas, TX | F7: =IFERROR(LEFT(E7, FIND(",", E7)-1), E7) -> Dallas | G7: 201 - 500 | H7: Real Estate | I7: 71 | J7: 119 | K7: 95 | L7: =IF(K7<50,"<$50K",IF(K7<75,"$50–75K",IF(K7<100,"$75–100K",IF(K7<125,"$100–125K",IF(K7<150,"$125–150K",">$150K"))))) -> $75–100K | M7: 21
A8: Data Scientist | B8: =IF(OR(ISNUMBER(SEARCH("Senior",A8)),ISNUMBER(SEARCH("Sr",A8)),ISNUMBER(SEARCH("Lead",A8)),ISNUMBER(SEARCH("Principal",A8))),"Senior",IF(OR(ISNUMBER(SEARCH("Junior",A8)),ISNUMBER(SEARCH("Jr",A8)),ISNUMBER(SEARCH("Entry",A8)),ISNUMBER(SEARCH("Associate",A8))),"Junior",IF(OR(ISNUMBER(SEARCH("Manager",A8)),ISNUMBER(SEARCH("Director",A8)),ISNUMBER(SEARCH("Head",A8)),ISNUMBER(SEARCH("VP",A8))),"Management","Mid-Level"))) -> Mid-Level | C8: =IF(ISNUMBER(SEARCH("Machine Learn",A8)),"ML Engineer",IF(ISNUMBER(SEARCH("Data Engineer",A8)),"Data Engineer",IF(ISNUMBER(SEARCH("Data Analyst",A8)),"Data Analyst",IF(ISNUMBER(SEARCH("Business Analyst",A8)),"Business Analyst",IF(ISNUMBER(SEARCH("Research",A8)),"Research Scientist",IF(ISNUMBER(SEARCH("Manager",A8)),"DS Manager",IF(ISNUMBER(SEARCH("Director",A8)),"Director/VP","Data Scientist"))))))) -> Data Scientist | D8: 4.1 | E8: Baltimore, MD | F8: =IFERROR(LEFT(E8, FIND(",", E8)-1), E8) -> Baltimore | G8: 501 - 1000 | H8: Banks & Credit Unions | I8: 54 | J8: 93 | K8: 73.5 | L8: =IF(K8<50,"<$50K",IF(K8<75,"$50–75K",IF(K8<100,"$75–100K",IF(K8<125,"$100–125K",IF(K8<150,"$125–150K",">$150K"))))) -> $50–75K | M8: 13
A9: Data Scientist | B9: =IF(OR(ISNUMBER(SEARCH("Senior",A9)),ISNUMBER(SEARCH("Sr",A9)),ISNUMBER(SEARCH("Lead",A9)),ISNUMBER(SEARCH("Principal",A9))),"Senior",IF(OR(ISNUMBER(SEARCH("Junior",A9)),ISNUMBER(SEARCH("Jr",A9)),ISNUMBER(SEARCH("Entry",A9)),ISNUMBER(SEARCH("Associate",A9))),"Junior",IF(OR(ISNUMBER(SEARCH("Manager",A9)),ISNUMBER(SEARCH("Director",A9)),ISNUMBER(SEARCH("Head",A9)),ISNUMBER(SEARCH("VP",A9))),"Management","Mid-Level"))) -> Mid-Level | C9: =IF(ISNUMBER(SEARCH("Machine Learn",A9)),"ML Engineer",IF(ISNUMBER(SEARCH("Data Engineer",A9)),"Data Engineer",IF(ISNUMBER(SEARCH("Data Analyst",A9)),"Data Analyst",IF(ISNUMBER(SEARCH("Business Analyst",A9)),"Business Analyst",IF(ISNUMBER(SEARCH("Research",A9)),"Research Scientist",IF(ISNUMBER(SEARCH("Manager",A9)),"DS Manager",IF(ISNUMBER(SEARCH("Director",A9)),"Director/VP","Data Scientist"))))))) -> Data Scientist | D9: 3.8 | E9: San Jose, CA | F9: =IFERROR(LEFT(E9, FIND(",", E9)-1), E9) -> San Jose | G9: 201 - 500 | H9: Consulting | I9: 86 | J9: 142 | K9: 114 | L9: =IF(K9<50,"<$50K",IF(K9<75,"$50–75K",IF(K9<100,"$75–100K",IF(K9<125,"$100–125K",IF(K9<150,"$125–150K",">$150K"))))) -> $100–125K | M9: 16
A10: Research Scientist | B10: =IF(OR(ISNUMBER(SEARCH("Senior",A10)),ISNUMBER(SEARCH("Sr",A10)),ISNUMBER(SEARCH("Lead",A10)),ISNUMBER(SEARCH("Principal",A10))),"Senior",IF(OR(ISNUMBER(SEARCH("Junior",A10)),ISNUMBER(SEARCH("Jr",A10)),ISNUMBER(SEARCH("Entry",A10)),ISNUMBER(SEARCH("Associate",A10))),"Junior",IF(OR(ISNUMBER(SEARCH("Manager",A10)),ISNUMBER(SEARCH("Director",A10)),ISNUMBER(SEARCH("Head",A10)),ISNUMBER(SEARCH("VP",A10))),"Management","Mid-Level"))) -> Mid-Level | C10: =IF(ISNUMBER(SEARCH("Machine Learn",A10)),"ML Engineer",IF(ISNUMBER(SEARCH("Data Engineer",A10)),"Data Engineer",IF(ISNUMBER(SEARCH("Data Analyst",A10)),"Data Analyst",IF(ISNUMBER(SEARCH("Business Analyst",A10)),"Business Analyst",IF(ISNUMBER(SEARCH("Research",A10)),"Research Scientist",IF(ISNUMBER(SEARCH("Manager",A10)),"DS Manager",IF(ISNUMBER(SEARCH("Director",A10)),"Director/VP","Data Scientist"))))))) -> Research Scientist | D10: 3.3 | E10: Rochester, NY | F10: =IFERROR(LEFT(E10, FIND(",", E10)-1), E10) -> Rochester | G10: 10000+ | H10: Health Care Services & Hospitals | I10: 38 | J10: 84 | K10: 61 | L10: =IF(K10<50,"<$50K",IF(K10<75,"$50–75K",IF(K10<100,"$75–100K",IF(K10<125,"$100–125K",IF(K10<150,"$125–150K",">$150K"))))) -> $50–75K | M10: 7
A11: Data Scientist | B11: =IF(OR(ISNUMBER(SEARCH("Senior",A11)),ISNUMBER(SEARCH("Sr",A11)),ISNUMBER(SEARCH("Lead",A11)),ISNUMBER(SEARCH("Principal",A11))),"Senior",IF(OR(ISNUMBER(SEARCH("Junior",A11)),ISNUMBER(SEARCH("Jr",A11)),ISNUMBER(SEARCH("Entry",A11)),ISNUMBER(SEARCH("Associate",A11))),"Junior",IF(OR(ISNUMBER(SEARCH("Manager",A11)),ISNUMBER(SEARCH("Director",A11)),ISNUMBER(SEARCH("Head",A11)),ISNUMBER(SEARCH("VP",A11))),"Management","Mid-Level"))) -> Mid-Level | C11: =IF(ISNUMBER(SEARCH("Machine Learn",A11)),"ML Engineer",IF(ISNUMBER(SEARCH("Data Engineer",A11)),"Data Engineer",IF(ISNUMBER(SEARCH("Data Analyst",A11)),"Data Analyst",IF(ISNUMBER(SEARCH("Business Analyst",A11)),"Business Analyst",IF(ISNUMBER(SEARCH("Research",A11)),"Research Scientist",IF(ISNUMBER(SEARCH("Manager",A11)),"DS Manager",IF(ISNUMBER(SEARCH("Director",A11)),"Director/VP","Data Scientist"))))))) -> Data Scientist | D11: 4.6 | E11: New York, NY | F11: =IFERROR(LEFT(E11, FIND(",", E11)-1), E11) -> New York | G11: 51 - 200 | H11: Internet | I11: 120 | J11: 160 | K11: 140 | L11: =IF(K11<50,"<$50K",IF(K11<75,"$50–75K",IF(K11<100,"$75–100K",IF(K11<125,"$100–125K",IF(K11<150,"$125–150K",">$150K"))))) -> $125–150K | M11: 12
A12: Data Scientist | B12: =IF(OR(ISNUMBER(SEARCH("Senior",A12)),ISNUMBER(SEARCH("Sr",A12)),ISNUMBER(SEARCH("Lead",A12)),ISNUMBER(SEARCH("Principal",A12))),"Senior",IF(OR(ISNUMBER(SEARCH("Junior",A12)),ISNUMBER(SEARCH("Jr",A12)),ISNUMBER(SEARCH("Entry",A12)),ISNUMBER(SEARCH("Associate",A12))),"Junior",IF(OR(ISNUMBER(SEARCH("Manager",A12)),ISNUMBER(SEARCH("Director",A12)),ISNUMBER(SEARCH("Head",A12)),ISNUMBER(SEARCH("VP",A12))),"Management","Mid-Level"))) -> Mid-Level | C12: =IF(ISNUMBER(SEARCH("Machine Learn",A12)),"ML Engineer",IF(ISNUMBER(SEARCH("Data Engineer",A12)),"Data Engineer",IF(ISNUMBER(SEARCH("Data Analyst",A12)),"Data Analyst",IF(ISNUMBER(SEARCH("Business Analyst",A12)),"Business Analyst",IF(ISNUMBER(SEARCH("Research",A12)),"Research Scientist",IF(ISNUMBER(SEARCH("Manager",A12)),"DS Manager",IF(ISNUMBER(SEARCH("Director",A12)),"Director/VP","Data Scientist"))))))) -> Data Scientist | D12: 3.5 | E12: San Jose, CA | F12: =IFERROR(LEFT(E12, FIND(",", E12)-1), E12) -> San Jose | G12: 501 - 1000 | H12: Other Retail Stores | I12: 126 | J12: 201 | K12: 163.5 | L12: =IF(K12<50,"<$50K",IF(K12<75,"$50–75K",IF(K12<100,"$75–100K",IF(K12<125,"$100–125K",IF(K12<150,"$125–150K",">$150K"))))) -> >$150K | M12: 10
A13: Data Scientist | B13: =IF(OR(ISNUMBER(SEARCH("Senior",A13)),ISNUMBER(SEARCH("Sr",A13)),ISNUMBER(SEARCH("Lead",A13)),ISNUMBER(SEARCH("Principal",A13))),"Senior",IF(OR(ISNUMBER(SEARCH("Junior",A13)),ISNUMBER(SEARCH("Jr",A13)),ISNUMBER(SEARCH("Entry",A13)),ISNUMBER(SEARCH("Associate",A13))),"Junior",IF(OR(ISNUMBER(SEARCH("Manager",A13)),ISNUMBER(SEARCH("Director",A13)),ISNUMBER(SEARCH("Head",A13)),ISNUMBER(SEARCH("VP",A13))),"Management","Mid-Level"))) -> Mid-Level | C13: =IF(ISNUMBER(SEARCH("Machine Learn",A13)),"ML Engineer",IF(ISNUMBER(SEARCH("Data Engineer",A13)),"Data Engineer",IF(ISNUMBER(SEARCH("Data Analyst",A13)),"Data Analyst",IF(ISNUMBER(SEARCH("Business Analyst",A13)),"Business Analyst",IF(ISNUMBER(SEARCH("Research",A13)),"Research Scientist",IF(ISNUMBER(SEARCH("Manager",A13)),"DS Manager",IF(ISNUMBER(SEARCH("Director",A13)),"Director/VP","Data Scientist"))))))) -> Data Scientist | D13: 4.1 | E13: Chantilly, VA | F13: =IFERROR(LEFT(E13, FIND(",", E13)-1), E13) -> Chantilly | G13: 5001 - 10000 | H13: Research & Development | I13: 64 | J13: 106 | K13: 85 | L13: =IF(K13<50,"<$50K",IF(K13<75,"$50–75K",IF(K13<100,"$75–100K",IF(K13<125,"$100–125K",IF(K13<150,"$125–150K",">$150K"))))) -> $75–100K | M13: 53
... A42: Data Analyst | B42: =IF(OR(ISNUMBER(SEARCH("Senior",A42)),ISNUMBER(SEARCH("Sr",A42)),ISNUMBER(SEARCH("Lead",A42)),ISNUMBER(SEARCH("Principal",A42))),"Senior",IF(OR(ISNUMBER(SEARCH("Junior",A42)),ISNUMBER(SEARCH("Jr",A42)),ISNUMBER(SEARCH("Entry",A42)),ISNUMBER(SEARCH("Associate",A42))),"Junior",IF(OR(ISNUMBER(SEARCH("Manager",A42)),ISNUMBER(SEARCH("Director",A42)),ISNUMBER(SEARCH("Head",A42)),ISNUMBER(SEARCH("VP",A42))),"Management","Mid-Level"))) -> Mid-Level | C42: =IF(ISNUMBER(SEARCH("Machine Learn",A42)),"ML Engineer",IF(ISNUMBER(SEARCH("Data Engineer",A42)),"Data Engineer",IF(ISNUMBER(SEARCH("Data Analyst",A42)),"Data Analyst",IF(ISNUMBER(SEARCH("Business Analyst",A42)),"Business Analyst",IF(ISNUMBER(SEARCH("Research",A42)),"Research Scientist",IF(ISNUMBER(SEARCH("Manager",A42)),"DS Manager",IF(ISNUMBER(SEARCH("Director",A42)),"Director/VP","Data Scientist"))))))) -> Data Analyst | D42: 4.2 | E42: San Francisco, CA | F42: =IFERROR(LEFT(E42, FIND(",", E42)-1), E42) -> San Francisco | G42: 201 - 500 | H42: IT Services | I42: 64 | J42: 112 | K42: 88 | L42: =IF(K42<50,"<$50K",IF(K42<75,"$50–75K",IF(K42<100,"$75–100K",IF(K42<125,"$100–125K",IF(K42<150,"$125–150K",">$150K"))))) -> $75–100K | M42: 13
A43: Data Engineer | B43: =IF(OR(ISNUMBER(SEARCH("Senior",A43)),ISNUMBER(SEARCH("Sr",A43)),ISNUMBER(SEARCH("Lead",A43)),ISNUMBER(SEARCH("Principal",A43))),"Senior",IF(OR(ISNUMBER(SEARCH("Junior",A43)),ISNUMBER(SEARCH("Jr",A43)),ISNUMBER(SEARCH("Entry",A43)),ISNUMBER(SEARCH("Associate",A43))),"Junior",IF(OR(ISNUMBER(SEARCH("Manager",A43)),ISNUMBER(SEARCH("Director",A43)),ISNUMBER(SEARCH("Head",A43)),ISNUMBER(SEARCH("VP",A43))),"Management","Mid-Level"))) -> Mid-Level | C43: =IF(ISNUMBER(SEARCH("Machine Learn",A43)),"ML Engineer",IF(ISNUMBER(SEARCH("Data Engineer",A43)),"Data Engineer",IF(ISNUMBER(SEARCH("Data Analyst",A43)),"Data Analyst",IF(ISNUMBER(SEARCH("Business Analyst",A43)),"Business Analyst",IF(ISNUMBER(SEARCH("Research",A43)),"Research Scientist",IF(ISNUMBER(SEARCH("Manager",A43)),"DS Manager",IF(ISNUMBER(SEARCH("Director",A43)),"Director/VP","Data Scientist"))))))) -> Data Engineer | D43: 3.6 | E43: Marlborough, MA | F43: =IFERROR(LEFT(E43, FIND(",", E43)-1), E43) -> Marlborough | G43: 18264 | H43: -1 | I43: 68 | J43: 129 | K43: 98.5 | L43: =IF(K43<50,"<$50K",IF(K43<75,"$50–75K",IF(K43<100,"$75–100K",IF(K43<125,"$100–125K",IF(K43<150,"$125–150K",">$150K"))))) -> $75–100K | M43: -1
A44: Data Scientist - Algorithms & Inference | B44: =IF(OR(ISNUMBER(SEARCH("Senior",A44)),ISNUMBER(SEARCH("Sr",A44)),ISNUMBER(SEARCH("Lead",A44)),ISNUMBER(SEARCH("Principal",A44))),"Senior",IF(OR(ISNUMBER(SEARCH("Junior",A44)),ISNUMBER(SEARCH("Jr",A44)),ISNUMBER(SEARCH("Entry",A44)),ISNUMBER(SEARCH("Associate",A44))),"Junior",IF(OR(ISNUMBER(SEARCH("Manager",A44)),ISNUMBER(SEARCH("Director",A44)),ISNUMBER(SEARCH("Head",A44)),ISNUMBER(SEARCH("VP",A44))),"Management","Mid-Level"))) -> Mid-Level | C44: =IF(ISNUMBER(SEARCH("Machine Learn",A44)),"ML Engineer",IF(ISNUMBER(SEARCH("Data Engineer",A44)),"Data Engineer",IF(ISNUMBER(SEARCH("Data Analyst",A44)),"Data Analyst",IF(ISNUMBER(SEARCH("Business Analyst",A44)),"Business Analyst",IF(ISNUMBER(SEARCH("Research",A44)),"Research Scientist",IF(ISNUMBER(SEARCH("Manager",A44)),"DS Manager",IF(ISNUMBER(SEARCH("Director",A44)),"Director/VP","Data Scientist"))))))) -> Data Scientist | D44: 4.2 | E44: San Francisco, CA | F44: =IFERROR(LEFT(E44, FIND(",", E44)-1), E44) -> San Francisco | G44: 51 - 200 | H44: Enterprise Software & Network Solutions | I44: 110 | J44: 175 | K44: 142.5 | L44: =IF(K44<50,"<$50K",IF(K44<75,"$50–75K",IF(K44<100,"$75–100K",IF(K44<125,"$100–125K",IF(K44<150,"$125–150K",">$150K"))))) -> $125–150K | M44: 11
A45: Scientist | B45: =IF(OR(ISNUMBER(SEARCH("Senior",A45)),ISNUMBER(SEARCH("Sr",A45)),ISNUMBER(SEARCH("Lead",A45)),ISNUMBER(SEARCH("Principal",A45))),"Senior",IF(OR(ISNUMBER(SEARCH("Junior",A45)),ISNUMBER(SEARCH("Jr",A45)),ISNUMBER(SEARCH("Entry",A45)),ISNUMBER(SEARCH("Associate",A45))),"Junior",IF(OR(ISNUMBER(SEARCH("Manager",A45)),ISNUMBER(SEARCH("Director",A45)),ISNUMBER(SEARCH("Head",A45)),ISNUMBER(SEARCH("VP",A45))),"Management","Mid-Level"))) -> Mid-Level | C45: =IF(ISNUMBER(SEARCH("Machine Learn",A45)),"ML Engineer",IF(ISNUMBER(SEARCH("Data Engineer",A45)),"Data Engineer",IF(ISNUMBER(SEARCH("Data Analyst",A45)),"Data Analyst",IF(ISNUMBER(SEARCH("Business Analyst",A45)),"Business Analyst",IF(ISNUMBER(SEARCH("Research",A45)),"Research Scientist",IF(ISNUMBER(SEARCH("Manager",A45)),"DS Manager",IF(ISNUMBER(SEARCH("Director",A45)),"Director/VP","Data Scientist"))))))) -> Data Scientist | D45: 3.4 | E45: Allendale, NJ | F45: =IFERROR(LEFT(E45, FIND(",", E45)-1), E45) -> Allendale | G45: 5001 - 10000 | H45: Consumer Products Manufacturing | I45: 52 | J45: 113 | K45: 82.5 | L45: =IF(K45<50,"<$50K",IF(K45<75,"$50–75K",IF(K45<100,"$75–100K",IF(K45<125,"$100–125K",IF(K45<150,"$125–150K",">$150K"))))) -> $75–100K | M45: 6
A46: Senior Data Scientist | B46: =IF(OR(ISNUMBER(SEARCH("Senior",A46)),ISNUMBER(SEARCH("Sr",A46)),ISNUMBER(SEARCH("Lead",A46)),ISNUMBER(SEARCH("Principal",A46))),"Senior",IF(OR(ISNUMBER(SEARCH("Junior",A46)),ISNUMBER(SEARCH("Jr",A46)),ISNUMBER(SEARCH("Entry",A46)),ISNUMBER(SEARCH("Associate",A46))),"Junior",IF(OR(ISNUMBER(SEARCH("Manager",A46)),ISNUMBER(SEARCH("Director",A46)),ISNUMBER(SEARCH("Head",A46)),ISNUMBER(SEARCH("VP",A46))),"Management","Mid-Level"))) -> Senior | C46: =IF(ISNUMBER(SEARCH("Machine Learn",A46)),"ML Engineer",IF(ISNUMBER(SEARCH("Data Engineer",A46)),"Data Engineer",IF(ISNUMBER(SEARCH("Data Analyst",A46)),"Data Analyst",IF(ISNUMBER(SEARCH("Business Analyst",A46)),"Business Analyst",IF(ISNUMBER(SEARCH("Research",A46)),"Research Scientist",IF(ISNUMBER(SEARCH("Manager",A46)),"DS Manager",IF(ISNUMBER(SEARCH("Director",A46)),"Director/VP","Data Scientist"))))))) -> Data Scientist | D46: 4.3 | E46: Chicago, IL | F46: =IFERROR(LEFT(E46, FIND(",", E46)-1), E46) -> Chicago | G46: 1001 - 5000 | H46: Real Estate | I46: 110 | J46: 150 | K46: 130 | L46: =IF(K46<50,"<$50K",IF(K46<75,"$50–75K",IF(K46<100,"$75–100K",IF(K46<125,"$100–125K",IF(K46<150,"$125–150K",">$150K"))))) -> $125–150K | M46: 28
A47: Data Scientist | B47: =IF(OR(ISNUMBER(SEARCH("Senior",A47)),ISNUMBER(SEARCH("Sr",A47)),ISNUMBER(SEARCH("Lead",A47)),ISNUMBER(SEARCH("Principal",A47))),"Senior",IF(OR(ISNUMBER(SEARCH("Junior",A47)),ISNUMBER(SEARCH("Jr",A47)),ISNUMBER(SEARCH("Entry",A47)),ISNUMBER(SEARCH("Associate",A47))),"Junior",IF(OR(ISNUMBER(SEARCH("Manager",A47)),ISNUMBER(SEARCH("Director",A47)),ISNUMBER(SEARCH("Head",A47)),ISNUMBER(SEARCH("VP",A47))),"Management","Mid-Level"))) -> Mid-Level | C47: =IF(ISNUMBER(SEARCH("Machine Learn",A47)),"ML Engineer",IF(ISNUMBER(SEARCH("Data Engineer",A47)),"Data Engineer",IF(ISNUMBER(SEARCH("Data Analyst",A47)),"Data Analyst",IF(ISNUMBER(SEARCH("Business Analyst",A47)),"Business Analyst",IF(ISNUMBER(SEARCH("Research",A47)),"Research Scientist",IF(ISNUMBER(SEARCH("Manager",A47)),"DS Manager",IF(ISNUMBER(SEARCH("Director",A47)),"Director/VP","Data Scientist"))))))) -> Data Scientist | D47: 5 | E47: Washington, DC | F47: =IFERROR(LEFT(E47, FIND(",", E47)-1), E47) -> Washington | G47: unknown | H47: Enterprise Software & Network Solutions | I47: 150 | J47: 160 | K47: 155 | L47: =IF(K47<50,"<$50K",IF(K47<75,"$50–75K",IF(K47<100,"$75–100K",IF(K47<125,"$100–125K",IF(K47<150,"$125–150K",">$150K"))))) -> >$150K | M47: -1
A48: Lead Data Scientist | B48: =IF(OR(ISNUMBER(SEARCH("Senior",A48)),ISNUMBER(SEARCH("Sr",A48)),ISNUMBER(SEARCH("Lead",A48)),ISNUMBER(SEARCH("Principal",A48))),"Senior",IF(OR(ISNUMBER(SEARCH("Junior",A48)),ISNUMBER(SEARCH("Jr",A48)),ISNUMBER(SEARCH("Entry",A48)),ISNUMBER(SEARCH("Associate",A48))),"Junior",IF(OR(ISNUMBER(SEARCH("Manager",A48)),ISNUMBER(SEARCH("Director",A48)),ISNUMBER(SEARCH("Head",A48)),ISNUMBER(SEARCH("VP",A48))),"Management","Mid-Level"))) -> Senior | C48: =IF(ISNUMBER(SEARCH("Machine Learn",A48)),"ML Engineer",IF(ISNUMBER(SEARCH("Data Engineer",A48)),"Data Engineer",IF(ISNUMBER(SEARCH("Data Analyst",A48)),"Data Analyst",IF(ISNUMBER(SEARCH("Business Analyst",A48)),"Business Analyst",IF(ISNUMBER(SEARCH("Research",A48)),"Research Scientist",IF(ISNUMBER(SEARCH("Manager",A48)),"DS Manager",IF(ISNUMBER(SEARCH("Director",A48)),"Director/VP","Data Scientist"))))))) -> Data Scientist | D48: 3.7 | E48: Bellevue, WA | F48: =IFERROR(LEFT(E48, FIND(",", E48)-1), E48) -> Bellevue | G48: 10000+ | H48: IT Services | I48: 158 | J48: 211 | K48: 184.5 | L48: =IF(K48<50,"<$50K",IF(K48<75,"$50–75K",IF(K48<100,"$75–100K",IF(K48<125,"$100–125K",IF(K48<150,"$125–150K",">$150K"))))) -> >$150K | M48: 63
A49: Associate Data Analyst | B49: =IF(OR(ISNUMBER(SEARCH("Senior",A49)),ISNUMBER(SEARCH("Sr",A49)),ISNUMBER(SEARCH("Lead",A49)),ISNUMBER(SEARCH("Principal",A49))),"Senior",IF(OR(ISNUMBER(SEARCH("Junior",A49)),ISNUMBER(SEARCH("Jr",A49)),ISNUMBER(SEARCH("Entry",A49)),ISNUMBER(SEARCH("Associate",A49))),"Junior",IF(OR(ISNUMBER(SEARCH("Manager",A49)),ISNUMBER(SEARCH("Director",A49)),ISNUMBER(SEARCH("Head",A49)),ISNUMBER(SEARCH("VP",A49))),"Management","Mid-Level"))) -> Junior | C49: =IF(ISNUMBER(SEARCH("Machine Learn",A49)),"ML Engineer",IF(ISNUMBER(SEARCH("Data Engineer",A49)),"Data Engineer",IF(ISNUMBER(SEARCH("Data Analyst",A49)),"Data Analyst",IF(ISNUMBER(SEARCH("Business Analyst",A49)),"Business Analyst",IF(ISNUMBER(SEARCH("Research",A49)),"Research Scientist",IF(ISNUMBER(SEARCH("Manager",A49)),"DS Manager",IF(ISNUMBER(SEARCH("Director",A49)),"Director/VP","Data Scientist"))))))) -> Data Analyst | D49: 3.1 | E49: Longmont, CO | F49: =IFERROR(LEFT(E49, FIND(",", E49)-1), E49) -> Longmont | G49: 5001 - 10000 | H49: Enterprise Software & Network Solutions | I49: 20 | J49: 39 | K49: 29.5 | L49: =IF(K49<50,"<$50K",IF(K49<75,"$50–75K",IF(K49<100,"$75–100K",IF(K49<125,"$100–125K",IF(K49<150,"$125–150K",">$150K"))))) -> <$50K | M49: 35
A50: Spectral Scientist/Engineer | B50: =IF(OR(ISNUMBER(SEARCH("Senior",A50)),ISNUMBER(SEARCH("Sr",A50)),ISNUMBER(SEARCH("Lead",A50)),ISNUMBER(SEARCH("Principal",A50))),"Senior",IF(OR(ISNUMBER(SEARCH("Junior",A50)),ISNUMBER(SEARCH("Jr",A50)),ISNUMBER(SEARCH("Entry",A50)),ISNUMBER(SEARCH("Associate",A50))),"Junior",IF(OR(ISNUMBER(SEARCH("Manager",A50)),ISNUMBER(SEARCH("Director",A50)),ISNUMBER(SEARCH("Head",A50)),ISNUMBER(SEARCH("VP",A50))),"Management","Mid-Level"))) -> Mid-Level | C50: =IF(ISNUMBER(SEARCH("Machine Learn",A50)),"ML Engineer",IF(ISNUMBER(SEARCH("Data Engineer",A50)),"Data Engineer",IF(ISNUMBER(SEARCH("Data Analyst",A50)),"Data Analyst",IF(ISNUMBER(SEARCH("Business Analyst",A50)),"Business Analyst",IF(ISNUMBER(SEARCH("Research",A50)),"Research Scientist",IF(ISNUMBER(SEARCH("Manager",A50)),"DS Manager",IF(ISNUMBER(SEARCH("Director",A50)),"Director/VP","Data Scientist"))))))) -> Data Scientist | D50: 4.7 | E50: Beavercreek, OH | F50: =IFERROR(LEFT(E50, FIND(",", E50)-1), E50) -> Beavercreek | G50: 501 - 1000 | H50: Aerospace & Defense | I50: 56 | J50: 117 | K50: 86.5 | L50: =IF(K50<50,"<$50K",IF(K50<75,"$50–75K",IF(K50<100,"$75–100K",IF(K50<125,"$100–125K",IF(K50<150,"$125–150K",">$150K"))))) -> $75–100K | M50: 22
A51: College Hire - Data Scientist - Open to December 2019 Graduates | B51: =IF(OR(ISNUMBER(SEARCH("Senior",A51)),ISNUMBER(SEARCH("Sr",A51)),ISNUMBER(SEARCH("Lead",A51)),ISNUMBER(SEARCH("Principal",A51))),"Senior",IF(OR(ISNUMBER(SEARCH("Junior",A51)),ISNUMBER(SEARCH("Jr",A51)),ISNUMBER(SEARCH("Entry",A51)),ISNUMBER(SEARCH("Associate",A51))),"Junior",IF(OR(ISNUMBER(SEARCH("Manager",A51)),ISNUMBER(SEARCH("Director",A51)),ISNUMBER(SEARCH("Head",A51)),ISNUMBER(SEARCH("VP",A51))),"Management","Mid-Level"))) -> Mid-Level | C51: =IF(ISNUMBER(SEARCH("Machine Learn",A51)),"ML Engineer",IF(ISNUMBER(SEARCH("Data Engineer",A51)),"Data Engineer",IF(ISNUMBER(SEARCH("Data Analyst",A51)),"Data Analyst",IF(ISNUMBER(SEARCH("Business Analyst",A51)),"Business Analyst",IF(ISNUMBER(SEARCH("Research",A51)),"Research Scientist",IF(ISNUMBER(SEARCH("Manager",A51)),"DS Manager",IF(ISNUMBER(SEARCH("Director",A51)),"Director/VP","Data Scientist"))))))) -> Data Scientist | D51: 3.7 | E51: Peoria, IL | F51: =IFERROR(LEFT(E51, FIND(",", E51)-1), E51) -> Peoria | G51: 10000+ | H51: Industrial Manufacturing | I51: 63 | J51: 99 | K51: 81 | L51: =IF(K51<50,"<$50K",IF(K51<75,"$50–75K",IF(K51<100,"$75–100K",IF(K51<125,"$100–125K",IF(K51<150,"$125–150K",">$150K"))))) -> $75–100K | M51: 96
A52: Data Scientist | B52: =IF(OR(ISNUMBER(SEARCH("Senior",A52)),ISNUMBER(SEARCH("Sr",A52)),ISNUMBER(SEARCH("Lead",A52)),ISNUMBER(SEARCH("Principal",A52))),"Senior",IF(OR(ISNUMBER(SEARCH("Junior",A52)),ISNUMBER(SEARCH("Jr",A52)),ISNUMBER(SEARCH("Entry",A52)),ISNUMBER(SEARCH("Associate",A52))),"Junior",IF(OR(ISNUMBER(SEARCH("Manager",A52)),ISNUMBER(SEARCH("Director",A52)),ISNUMBER(SEARCH("Head",A52)),ISNUMBER(SEARCH("VP",A52))),"Management","Mid-Level"))) -> Mid-Level | C52: =IF(ISNUMBER(SEARCH("Machine Learn",A52)),"ML Engineer",IF(ISNUMBER(SEARCH("Data Engineer",A52)),"Data Engineer",IF(ISNUMBER(SEARCH("Data Analyst",A52)),"Data Analyst",IF(ISNUMBER(SEARCH("Business Analyst",A52)),"Business Analyst",IF(ISNUMBER(SEARCH("Research",A52)),"Research Scientist",IF(ISNUMBER(SEARCH("Manager",A52)),"DS Manager",IF(ISNUMBER(SEARCH("Director",A52)),"Director/VP","Data Scientist"))))))) -> Data Scientist | D52: 3.8 | E52: Fort Lauderdale, FL | F52: =IFERROR(LEFT(E52, FIND(",", E52)-1), E52) -> Fort Lauderdale | G52: 501 - 1000 | H52: Advertising & Marketing | I52: 68 | J52: 114 | K52: 91 | L52: =IF(K52<50,"<$50K",IF(K52<75,"$50–75K",IF(K52<100,"$75–100K",IF(K52<125,"$100–125K",IF(K52<150,"$125–150K",">$150K"))))) -> $75–100K | M52: 37
A53: Data Scientist, Office of Data Science | B53: =IF(OR(ISNUMBER(SEARCH("Senior",A53)),ISNUMBER(SEARCH("Sr",A53)),ISNUMBER(SEARCH("Lead",A53)),ISNUMBER(SEARCH("Principal",A53))),"Senior",IF(OR(ISNUMBER(SEARCH("Junior",A53)),ISNUMBER(SEARCH("Jr",A53)),ISNUMBER(SEARCH("Entry",A53)),ISNUMBER(SEARCH("Associate",A53))),"Junior",IF(OR(ISNUMBER(SEARCH("Manager",A53)),ISNUMBER(SEARCH("Director",A53)),ISNUMBER(SEARCH("Head",A53)),ISNUMBER(SEARCH("VP",A53))),"Management","Mid-Level"))) -> Mid-Level | C53: =IF(ISNUMBER(SEARCH("Machine Learn",A53)),"ML Engineer",IF(ISNUMBER(SEARCH("Data Engineer",A53)),"Data Engineer",IF(ISNUMBER(SEARCH("Data Analyst",A53)),"Data Analyst",IF(ISNUMBER(SEARCH("Business Analyst",A53)),"Business Analyst",IF(ISNUMBER(SEARCH("Research",A53)),"Research Scientist",IF(ISNUMBER(SEARCH("Manager",A53)),"DS Manager",IF(ISNUMBER(SEARCH("Director",A53)),"Director/VP","Data Scientist"))))))) -> Data Scientist | D53: 3.3 | E53: Boston, MA | F53: =IFERROR(LEFT(E53, FIND(",", E53)-1), E53) -> Boston | G53: 10000+ | H53: Insurance Carriers | I53: 86 | J53: 143 | K53: 114.5 | L53: =IF(K53<50,"<$50K",IF(K53<75,"$50–75K",IF(K53<100,"$75–100K",IF(K53<125,"$100–125K",IF(K53<150,"$125–150K",">$150K"))))) -> $100–125K | M53: 109
A54: Data Science Analyst | B54: =IF(OR(ISNUMBER(SEARCH("Senior",A54)),ISNUMBER(SEARCH("Sr",A54)),ISNUMBER(SEARCH("Lead",A54)),ISNUMBER(SEARCH("Principal",A54))),"Senior",IF(OR(ISNUMBER(SEARCH("Junior",A54)),ISNUMBER(SEARCH("Jr",A54)),ISNUMBER(SEARCH("Entry",A54)),ISNUMBER(SEARCH("Associate",A54))),"Junior",IF(OR(ISNUMBER(SEARCH("Manager",A54)),ISNUMBER(SEARCH("Director",A54)),ISNUMBER(SEARCH("Head",A54)),ISNUMBER(SEARCH("VP",A54))),"Management","Mid-Level"))) -> Mid-Level | C54: =IF(ISNUMBER(SEARCH("Machine Learn",A54)),"ML Engineer",IF(ISNUMBER(SEARCH("Data Engineer",A54)),"Data Engineer",IF(ISNUMBER(SEARCH("Data Analyst",A54)),"Data Analyst",IF(ISNUMBER(SEARCH("Business Analyst",A54)),"Business Analyst",IF(ISNUMBER(SEARCH("Research",A54)),"Research Scientist",IF(ISNUMBER(SEARCH("Manager",A54)),"DS Manager",IF(ISNUMBER(SEARCH("Director",A54)),"Director/VP","Data Scientist"))))))) -> Data Scientist | D54: 4.6 | E54: Huntsville, AL | F54: =IFERROR(LEFT(E54, FIND(",", E54)-1), E54) -> Huntsville | G54: 1001 - 5000 | H54: Aerospace & Defense | I54: 41 | J54: 95 | K54: 68 | L54: =IF(K54<50,"<$50K",IF(K54<75,"$50–75K",IF(K54<100,"$75–100K",IF(K54<125,"$100–125K",IF(K54<150,"$125–150K",">$150K"))))) -> $50–75K | M54: 19
A55: Data Scientist | B55: =IF(OR(ISNUMBER(SEARCH("Senior",A55)),ISNUMBER(SEARCH("Sr",A55)),ISNUMBER(SEARCH("Lead",A55)),ISNUMBER(SEARCH("Principal",A55))),"Senior",IF(OR(ISNUMBER(SEARCH("Junior",A55)),ISNUMBER(SEARCH("Jr",A55)),ISNUMBER(SEARCH("Entry",A55)),ISNUMBER(SEARCH("Associate",A55))),"Junior",IF(OR(ISNUMBER(SEARCH("Manager",A55)),ISNUMBER(SEARCH("Director",A55)),ISNUMBER(SEARCH("Head",A55)),ISNUMBER(SEARCH("VP",A55))),"Management","Mid-Level"))) -> Mid-Level | C55: =IF(ISNUMBER(SEARCH("Machine Learn",A55)),"ML Engineer",IF(ISNUMBER(SEARCH("Data Engineer",A55)),"Data Engineer",IF(ISNUMBER(SEARCH("Data Analyst",A55)),"Data Analyst",IF(ISNUMBER(SEARCH("Business Analyst",A55)),"Business Analyst",IF(ISNUMBER(SEARCH("Research",A55)),"Research Scientist",IF(ISNUMBER(SEARCH("Manager",A55)),"DS Manager",IF(ISNUMBER(SEARCH("Director",A55)),"Director/VP","Data Scientist"))))))) -> Data Scientist | D55: 3.7 | E55: Armonk, NY | F55: =IFERROR(LEFT(E55, FIND(",", E55)-1), E55) -> Armonk | G55: 10000+ | H55: Insurance Agencies & Brokerages | I55: 86 | J55: 144 | K55: 115 | L55: =IF(K55<50,"<$50K",IF(K55<75,"$50–75K",IF(K55<100,"$75–100K",IF(K55<125,"$100–125K",IF(K55<150,"$125–150K",">$150K"))))) -> $100–125K | M55: 158
... A69: Data Scientist - Research | B69: =IF(OR(ISNUMBER(SEARCH("Senior",A69)),ISNUMBER(SEARCH("Sr",A69)),ISNUMBER(SEARCH("Lead",A69)),ISNUMBER(SEARCH("Principal",A69))),"Senior",IF(OR(ISNUMBER(SEARCH("Junior",A69)),ISNUMBER(SEARCH("Jr",A69)),ISNUMBER(SEARCH("Entry",A69)),ISNUMBER(SEARCH("Associate",A69))),"Junior",IF(OR(ISNUMBER(SEARCH("Manager",A69)),ISNUMBER(SEARCH("Director",A69)),ISNUMBER(SEARCH("Head",A69)),ISNUMBER(SEARCH("VP",A69))),"Management","Mid-Level"))) -> Mid-Level | C69: =IF(ISNUMBER(SEARCH("Machine Learn",A69)),"ML Engineer",IF(ISNUMBER(SEARCH("Data Engineer",A69)),"Data Engineer",IF(ISNUMBER(SEARCH("Data Analyst",A69)),"Data Analyst",IF(ISNUMBER(SEARCH("Business Analyst",A69)),"Business Analyst",IF(ISNUMBER(SEARCH("Research",A69)),"Research Scientist",IF(ISNUMBER(SEARCH("Manager",A69)),"DS Manager",IF(ISNUMBER(SEARCH("Director",A69)),"Director/VP","Data Scientist"))))))) -> Research Scientist | D69: 3.1 | E69: Boston, MA | F69: =IFERROR(LEFT(E69, FIND(",", E69)-1), E69) -> Boston | G69: 201 - 500 | H69: Advertising & Marketing | I69: 41 | J69: 72 | K69: 56.5 | L69: =IF(K69<50,"<$50K",IF(K69<75,"$50–75K",IF(K69<100,"$75–100K",IF(K69<125,"$100–125K",IF(K69<150,"$125–150K",">$150K"))))) -> $50–75K | M69: 22
A70: Data Scientist | B70: =IF(OR(ISNUMBER(SEARCH("Senior",A70)),ISNUMBER(SEARCH("Sr",A70)),ISNUMBER(SEARCH("Lead",A70)),ISNUMBER(SEARCH("Principal",A70))),"Senior",IF(OR(ISNUMBER(SEARCH("Junior",A70)),ISNUMBER(SEARCH("Jr",A70)),ISNUMBER(SEARCH("Entry",A70)),ISNUMBER(SEARCH("Associate",A70))),"Junior",IF(OR(ISNUMBER(SEARCH("Manager",A70)),ISNUMBER(SEARCH("Director",A70)),ISNUMBER(SEARCH("Head",A70)),ISNUMBER(SEARCH("VP",A70))),"Management","Mid-Level"))) -> Mid-Level | C70: =IF(ISNUMBER(SEARCH("Machine Learn",A70)),"ML Engineer",IF(ISNUMBER(SEARCH("Data Engineer",A70)),"Data Engineer",IF(ISNUMBER(SEARCH("Data Analyst",A70)),"Data Analyst",IF(ISNUMBER(SEARCH("Business Analyst",A70)),"Business Analyst",IF(ISNUMBER(SEARCH("Research",A70)),"Research Scientist",IF(ISNUMBER(SEARCH("Manager",A70)),"DS Manager",IF(ISNUMBER(SEARCH("Director",A70)),"Director/VP","Data Scientist"))))))) -> Data Scientist | D70: 3.2 | E70: Philadelphia, PA | F70: =IFERROR(LEFT(E70, FIND(",", E70)-1), E70) -> Philadelphia | G70: 18264 | H70: Staffing & Outsourcing | I70: 96 | J70: 161 | K70: 128.5 | L70: =IF(K70<50,"<$50K",IF(K70<75,"$50–75K",IF(K70<100,"$75–100K",IF(K70<125,"$100–125K",IF(K70<150,"$125–150K",">$150K"))))) -> $125–150K | M70: -1
A71: R&D Data Analysis Scientist | B71: =IF(OR(ISNUMBER(SEARCH("Senior",A71)),ISNUMBER(SEARCH("Sr",A71)),ISNUMBER(SEARCH("Lead",A71)),ISNUMBER(SEARCH("Principal",A71))),"Senior",IF(OR(ISNUMBER(SEARCH("Junior",A71)),ISNUMBER(SEARCH("Jr",A71)),ISNUMBER(SEARCH("Entry",A71)),ISNUMBER(SEARCH("Associate",A71))),"Junior",IF(OR(ISNUMBER(SEARCH("Manager",A71)),ISNUMBER(SEARCH("Director",A71)),ISNUMBER(SEARCH("Head",A71)),ISNUMBER(SEARCH("VP",A71))),"Management","Mid-Level"))) -> Mid-Level | C71: =IF(ISNUMBER(SEARCH("Machine Learn",A71)),"ML Engineer",IF(ISNUMBER(SEARCH("Data Engineer",A71)),"Data Engineer",IF(ISNUMBER(SEARCH("Data Analyst",A71)),"Data Analyst",IF(ISNUMBER(SEARCH("Business Analyst",A71)),"Business Analyst",IF(ISNUMBER(SEARCH("Research",A71)),"Research Scientist",IF(ISNUMBER(SEARCH("Manager",A71)),"DS Manager",IF(ISNUMBER(SEARCH("Director",A71)),"Director/VP","Data Scientist"))))))) -> Data Scientist | D71: 4 | E71: Vancouver, WA | F71: =IFERROR(LEFT(E71, FIND(",", E71)-1), E71) -> Vancouver | G71: 10000+ | H71: Computer Hardware & Software | I71: 65 | J71: 130 | K71: 97.5 | L71: =IF(K71<50,"<$50K",IF(K71<75,"$50–75K",IF(K71<100,"$75–100K",IF(K71<125,"$100–125K",IF(K71<150,"$125–150K",">$150K"))))) -> $75–100K | M71: 82
A72: Analytics Consultant | B72: =IF(OR(ISNUMBER(SEARCH("Senior",A72)),ISNUMBER(SEARCH("Sr",A72)),ISNUMBER(SEARCH("Lead",A72)),ISNUMBER(SEARCH("Principal",A72))),"Senior",IF(OR(ISNUMBER(SEARCH("Junior",A72)),ISNUMBER(SEARCH("Jr",A72)),ISNUMBER(SEARCH("Entry",A72)),ISNUMBER(SEARCH("Associate",A72))),"Junior",IF(OR(ISNUMBER(SEARCH("Manager",A72)),ISNUMBER(SEARCH("Director",A72)),ISNUMBER(SEARCH("Head",A72)),ISNUMBER(SEARCH("VP",A72))),"Management","Mid-Level"))) -> Mid-Level | C72: =IF(ISNUMBER(SEARCH("Machine Learn",A72)),"ML Engineer",IF(ISNUMBER(SEARCH("Data Engineer",A72)),"Data Engineer",IF(ISNUMBER(SEARCH("Data Analyst",A72)),"Data Analyst",IF(ISNUMBER(SEARCH("Business Analyst",A72)),"Business Analyst",IF(ISNUMBER(SEARCH("Research",A72)),"Research Scientist",IF(ISNUMBER(SEARCH("Manager",A72)),"DS Manager",IF(ISNUMBER(SEARCH("Director",A72)),"Director/VP","Data Scientist"))))))) -> Data Scientist | D72: 4.4 | E72: Indianapolis, IN | F72: =IFERROR(LEFT(E72, FIND(",", E72)-1), E72) -> Indianapolis | G72: 18264 | H72: Enterprise Software & Network Solutions | I72: 52 | J72: 81 | K72: 66.5 | L72: =IF(K72<50,"<$50K",IF(K72<75,"$50–75K",IF(K72<100,"$75–100K",IF(K72<125,"$100–125K",IF(K72<150,"$125–150K",">$150K"))))) -> $50–75K | M72: 6
A73: Director, Data Science | B73: =IF(OR(ISNUMBER(SEARCH("Senior",A73)),ISNUMBER(SEARCH("Sr",A73)),ISNUMBER(SEARCH("Lead",A73)),ISNUMBER(SEARCH("Principal",A73))),"Senior",IF(OR(ISNUMBER(SEARCH("Junior",A73)),ISNUMBER(SEARCH("Jr",A73)),ISNUMBER(SEARCH("Entry",A73)),ISNUMBER(SEARCH("Associate",A73))),"Junior",IF(OR(ISNUMBER(SEARCH("Manager",A73)),ISNUMBER(SEARCH("Director",A73)),ISNUMBER(SEARCH("Head",A73)),ISNUMBER(SEARCH("VP",A73))),"Management","Mid-Level"))) -> Management | C73: =IF(ISNUMBER(SEARCH("Machine Learn",A73)),"ML Engineer",IF(ISNUMBER(SEARCH("Data Engineer",A73)),"Data Engineer",IF(ISNUMBER(SEARCH("Data Analyst",A73)),"Data Analyst",IF(ISNUMBER(SEARCH("Business Analyst",A73)),"Business Analyst",IF(ISNUMBER(SEARCH("Research",A73)),"Research Scientist",IF(ISNUMBER(SEARCH("Manager",A73)),"DS Manager",IF(ISNUMBER(SEARCH("Director",A73)),"Director/VP","Data Scientist"))))))) -> Director/VP | D73: 3.6 | E73: Lake Forest, IL | F73: =IFERROR(LEFT(E73, FIND(",", E73)-1), E73) -> Lake Forest | G73: 10000+ | H73: Wholesale | I73: 139 | J73: 220 | K73: 179.5 | L73: =IF(K73<50,"<$50K",IF(K73<75,"$50–75K",IF(K73<100,"$75–100K",IF(K73<125,"$100–125K",IF(K73<150,"$125–150K",">$150K"))))) -> >$150K | M73: 94
A74: Scientist | B74: =IF(OR(ISNUMBER(SEARCH("Senior",A74)),ISNUMBER(SEARCH("Sr",A74)),ISNUMBER(SEARCH("Lead",A74)),ISNUMBER(SEARCH("Principal",A74))),"Senior",IF(OR(ISNUMBER(SEARCH("Junior",A74)),ISNUMBER(SEARCH("Jr",A74)),ISNUMBER(SEARCH("Entry",A74)),ISNUMBER(SEARCH("Associate",A74))),"Junior",IF(OR(ISNUMBER(SEARCH("Manager",A74)),ISNUMBER(SEARCH("Director",A74)),ISNUMBER(SEARCH("Head",A74)),ISNUMBER(SEARCH("VP",A74))),"Management","Mid-Level"))) -> Mid-Level | C74: =IF(ISNUMBER(SEARCH("Machine Learn",A74)),"ML Engineer",IF(ISNUMBER(SEARCH("Data Engineer",A74)),"Data Engineer",IF(ISNUMBER(SEARCH("Data Analyst",A74)),"Data Analyst",IF(ISNUMBER(SEARCH("Business Analyst",A74)),"Business Analyst",IF(ISNUMBER(SEARCH("Research",A74)),"Research Scientist",IF(ISNUMBER(SEARCH("Manager",A74)),"DS Manager",IF(ISNUMBER(SEARCH("Director",A74)),"Director/VP","Data Scientist"))))))) -> Data Scientist | D74: 2.7 | E74: Maryland Heights, MO | F74: =IFERROR(LEFT(E74, FIND(",", E74)-1), E74) -> Maryland Heights | G74: 501 - 1000 | H74: Research & Development | I74: 50 | J74: 102 | K74: 76 | L74: =IF(K74<50,"<$50K",IF(K74<75,"$50–75K",IF(K74<100,"$75–100K",IF(K74<125,"$100–125K",IF(K74<150,"$125–150K",">$150K"))))) -> $75–100K | M74: 43
A75: Data Scientist SR | B75: =IF(OR(ISNUMBER(SEARCH("Senior",A75)),ISNUMBER(SEARCH("Sr",A75)),ISNUMBER(SEARCH("Lead",A75)),ISNUMBER(SEARCH("Principal",A75))),"Senior",IF(OR(ISNUMBER(SEARCH("Junior",A75)),ISNUMBER(SEARCH("Jr",A75)),ISNUMBER(SEARCH("Entry",A75)),ISNUMBER(SEARCH("Associate",A75))),"Junior",IF(OR(ISNUMBER(SEARCH("Manager",A75)),ISNUMBER(SEARCH("Director",A75)),ISNUMBER(SEARCH("Head",A75)),ISNUMBER(SEARCH("VP",A75))),"Management","Mid-Level"))) -> Senior | C75: =IF(ISNUMBER(SEARCH("Machine Learn",A75)),"ML Engineer",IF(ISNUMBER(SEARCH("Data Engineer",A75)),"Data Engineer",IF(ISNUMBER(SEARCH("Data Analyst",A75)),"Data Analyst",IF(ISNUMBER(SEARCH("Business Analyst",A75)),"Business Analyst",IF(ISNUMBER(SEARCH("Research",A75)),"Research Scientist",IF(ISNUMBER(SEARCH("Manager",A75)),"DS Manager",IF(ISNUMBER(SEARCH("Director",A75)),"Director/VP","Data Scientist"))))))) -> Data Scientist | D75: 3.9 | E75: Charlottesville, VA | F75: =IFERROR(LEFT(E75, FIND(",", E75)-1), E75) -> Charlottesville | G75: 501 - 1000 | H75: IT Services | I75: 85 | J75: 139 | K75: 112 | L75: =IF(K75<50,"<$50K",IF(K75<75,"$50–75K",IF(K75<100,"$75–100K",IF(K75<125,"$100–125K",IF(K75<150,"$125–150K",">$150K"))))) -> $100–125K | M75: 11
A76: Data Scientist | B76: =IF(OR(ISNUMBER(SEARCH("Senior",A76)),ISNUMBER(SEARCH("Sr",A76)),ISNUMBER(SEARCH("Lead",A76)),ISNUMBER(SEARCH("Principal",A76))),"Senior",IF(OR(ISNUMBER(SEARCH("Junior",A76)),ISNUMBER(SEARCH("Jr",A76)),ISNUMBER(SEARCH("Entry",A76)),ISNUMBER(SEARCH("Associate",A76))),"Junior",IF(OR(ISNUMBER(SEARCH("Manager",A76)),ISNUMBER(SEARCH("Director",A76)),ISNUMBER(SEARCH("Head",A76)),ISNUMBER(SEARCH("VP",A76))),"Management","Mid-Level"))) -> Mid-Level | C76: =IF(ISNUMBER(SEARCH("Machine Learn",A76)),"ML Engineer",IF(ISNUMBER(SEARCH("Data Engineer",A76)),"Data Engineer",IF(ISNUMBER(SEARCH("Data Analyst",A76)),"Data Analyst",IF(ISNUMBER(SEARCH("Business Analyst",A76)),"Business Analyst",IF(ISNUMBER(SEARCH("Research",A76)),"Research Scientist",IF(ISNUMBER(SEARCH("Manager",A76)),"DS Manager",IF(ISNUMBER(SEARCH("Director",A76)),"Director/VP","Data Scientist"))))))) -> Data Scientist | D76: 3.1 | E76: Pittsburgh, PA | F76: =IFERROR(LEFT(E76, FIND(",", E76)-1), E76) -> Pittsburgh | G76: 1001 - 5000 | H76: Mining | I76: 74 | J76: 122 | K76: 98 | L76: =IF(K76<50,"<$50K",IF(K76<75,"$50–75K",IF(K76<100,"$75–100K",IF(K76<125,"$100–125K",IF(K76<150,"$125–150K",">$150K"))))) -> $75–100K | M76: 161
A77: R&D Sr Data Scientist | B77: =IF(OR(ISNUMBER(SEARCH("Senior",A77)),ISNUMBER(SEARCH("Sr",A77)),ISNUMBER(SEARCH("Lead",A77)),ISNUMBER(SEARCH("Principal",A77))),"Senior",IF(OR(ISNUMBER(SEARCH("Junior",A77)),ISNUMBER(SEARCH("Jr",A77)),ISNUMBER(SEARCH("Entry",A77)),ISNUMBER(SEARCH("Associate",A77))),"Junior",IF(OR(ISNUMBER(SEARCH("Manager",A77)),ISNUMBER(SEARCH("Director",A77)),ISNUMBER(SEARCH("Head",A77)),ISNUMBER(SEARCH("VP",A77))),"Management","Mid-Level"))) -> Senior | C77: =IF(ISNUMBER(SEARCH("Machine Learn",A77)),"ML Engineer",IF(ISNUMBER(SEARCH("Data Engineer",A77)),"Data Engineer",IF(ISNUMBER(SEARCH("Data Analyst",A77)),"Data Analyst",IF(ISNUMBER(SEARCH("Business Analyst",A77)),"Business Analyst",IF(ISNUMBER(SEARCH("Research",A77)),"Research Scientist",IF(ISNUMBER(SEARCH("Manager",A77)),"DS Manager",IF(ISNUMBER(SEARCH("Director",A77)),"Director/VP","Data Scientist"))))))) -> Data Scientist | D77: 4 | E77: Vancouver, WA | F77: =IFERROR(LEFT(E77, FIND(",", E77)-1), E77) -> Vancouver | G77: 10000+ | H77: Computer Hardware & Software | I77: 99 | J77: 157 | K77: 128 | L77: =IF(K77<50,"<$50K",IF(K77<75,"$50–75K",IF(K77<100,"$75–100K",IF(K77<125,"$100–125K",IF(K77<150,"$125–150K",">$150K"))))) -> $125–150K | M77: 82
A78: Customer Data Scientist/Sales Engineer (Bay | B78: =IF(OR(ISNUMBER(SEARCH("Senior",A78)),ISNUMBER(SEARCH("Sr",A78)),ISNUMBER(SEARCH("Lead",A78)),ISNUMBER(SEARCH("Principal",A78))),"Senior",IF(OR(ISNUMBER(SEARCH("Junior",A78)),ISNUMBER(SEARCH("Jr",A78)),ISNUMBER(SEARCH("Entry",A78)),ISNUMBER(SEARCH("Associate",A78))),"Junior",IF(OR(ISNUMBER(SEARCH("Manager",A78)),ISNUMBER(SEARCH("Director",A78)),ISNUMBER(SEARCH("Head",A78)),ISNUMBER(SEARCH("VP",A78))),"Management","Mid-Level"))) -> Mid-Level | C78: =IF(ISNUMBER(SEARCH("Machine Learn",A78)),"ML Engineer",IF(ISNUMBER(SEARCH("Data Engineer",A78)),"Data Engineer",IF(ISNUMBER(SEARCH("Data Analyst",A78)),"Data Analyst",IF(ISNUMBER(SEARCH("Business Analyst",A78)),"Business Analyst",IF(ISNUMBER(SEARCH("Research",A78)),"Research Scientist",IF(ISNUMBER(SEARCH("Manager",A78)),"DS Manager",IF(ISNUMBER(SEARCH("Director",A78)),"Director/VP","Data Scientist"))))))) -> Data Scientist | D78: 4.3 | E78: Mountain View, CA | F78: =IFERROR(LEFT(E78, FIND(",", E78)-1), E78) -> Mountain View | G78: 201 - 500 | H78: Enterprise Software & Network Solutions | I78: 79 | J78: 222 | K78: 150.5 | L78: =IF(K78<50,"<$50K",IF(K78<75,"$50–75K",IF(K78<100,"$75–100K",IF(K78<125,"$100–125K",IF(K78<150,"$125–150K",">$150K"))))) -> >$150K | M78: 10
A79: Research Scientist | B79: =IF(OR(ISNUMBER(SEARCH("Senior",A79)),ISNUMBER(SEARCH("Sr",A79)),ISNUMBER(SEARCH("Lead",A79)),ISNUMBER(SEARCH("Principal",A79))),"Senior",IF(OR(ISNUMBER(SEARCH("Junior",A79)),ISNUMBER(SEARCH("Jr",A79)),ISNUMBER(SEARCH("Entry",A79)),ISNUMBER(SEARCH("Associate",A79))),"Junior",IF(OR(ISNUMBER(SEARCH("Manager",A79)),ISNUMBER(SEARCH("Director",A79)),ISNUMBER(SEARCH("Head",A79)),ISNUMBER(SEARCH("VP",A79))),"Management","Mid-Level"))) -> Mid-Level | C79: =IF(ISNUMBER(SEARCH("Machine Learn",A79)),"ML Engineer",IF(ISNUMBER(SEARCH("Data Engineer",A79)),"Data Engineer",IF(ISNUMBER(SEARCH("Data Analyst",A79)),"Data Analyst",IF(ISNUMBER(SEARCH("Business Analyst",A79)),"Business Analyst",IF(ISNUMBER(SEARCH("Research",A79)),"Research Scientist",IF(ISNUMBER(SEARCH("Manager",A79)),"DS Manager",IF(ISNUMBER(SEARCH("Director",A79)),"Director/VP","Data Scientist"))))))) -> Research Scientist | D79: 1.9 | E79: Cambridge, MA | F79: =IFERROR(LEFT(E79, FIND(",", E79)-1), E79) -> Cambridge | G79: 51 - 200 | H79: Biotech & Pharmaceuticals | I79: 57 | J79: 118 | K79: 87.5 | L79: =IF(K79<50,"<$50K",IF(K79<75,"$50–75K",IF(K79<100,"$75–100K",IF(K79<125,"$100–125K",IF(K79<150,"$125–150K",">$150K"))))) -> $75–100K | M79: 21
A80: Data Scientist | B80: =IF(OR(ISNUMBER(SEARCH("Senior",A80)),ISNUMBER(SEARCH("Sr",A80)),ISNUMBER(SEARCH("Lead",A80)),ISNUMBER(SEARCH("Principal",A80))),"Senior",IF(OR(ISNUMBER(SEARCH("Junior",A80)),ISNUMBER(SEARCH("Jr",A80)),ISNUMBER(SEARCH("Entry",A80)),ISNUMBER(SEARCH("Associate",A80))),"Junior",IF(OR(ISNUMBER(SEARCH("Manager",A80)),ISNUMBER(SEARCH("Director",A80)),ISNUMBER(SEARCH("Head",A80)),ISNUMBER(SEARCH("VP",A80))),"Management","Mid-Level"))) -> Mid-Level | C80: =IF(ISNUMBER(SEARCH("Machine Learn",A80)),"ML Engineer",IF(ISNUMBER(SEARCH("Data Engineer",A80)),"Data Engineer",IF(ISNUMBER(SEARCH("Data Analyst",A80)),"Data Analyst",IF(ISNUMBER(SEARCH("Business Analyst",A80)),"Business Analyst",IF(ISNUMBER(SEARCH("Research",A80)),"Research Scientist",IF(ISNUMBER(SEARCH("Manager",A80)),"DS Manager",IF(ISNUMBER(SEARCH("Director",A80)),"Director/VP","Data Scientist"))))))) -> Data Scientist | D80: 3.3 | E80: Chantilly, VA | F80: =IFERROR(LEFT(E80, FIND(",", E80)-1), E80) -> Chantilly | G80: 1001 - 5000 | H80: Aerospace & Defense | I80: 83 | J80: 137 | K80: 110 | L80: =IF(K80<50,"<$50K",IF(K80<75,"$50–75K",IF(K80<100,"$75–100K",IF(K80<125,"$100–125K",IF(K80<150,"$125–150K",">$150K"))))) -> $100–125K | M80: 4
A81: Data Scientist | B81: =IF(OR(ISNUMBER(SEARCH("Senior",A81)),ISNUMBER(SEARCH("Sr",A81)),ISNUMBER(SEARCH("Lead",A81)),ISNUMBER(SEARCH("Principal",A81))),"Senior",IF(OR(ISNUMBER(SEARCH("Junior",A81)),ISNUMBER(SEARCH("Jr",A81)),ISNUMBER(SEARCH("Entry",A81)),ISNUMBER(SEARCH("Associate",A81))),"Junior",IF(OR(ISNUMBER(SEARCH("Manager",A81)),ISNUMBER(SEARCH("Director",A81)),ISNUMBER(SEARCH("Head",A81)),ISNUMBER(SEARCH("VP",A81))),"Management","Mid-Level"))) -> Mid-Level | C81: =IF(ISNUMBER(SEARCH("Machine Learn",A81)),"ML Engineer",IF(ISNUMBER(SEARCH("Data Engineer",A81)),"Data Engineer",IF(ISNUMBER(SEARCH("Data Analyst",A81)),"Data Analyst",IF(ISNUMBER(SEARCH("Business Analyst",A81)),"Business Analyst",IF(ISNUMBER(SEARCH("Research",A81)),"Research Scientist",IF(ISNUMBER(SEARCH("Manager",A81)),"DS Manager",IF(ISNUMBER(SEARCH("Director",A81)),"Director/VP","Data Scientist"))))))) -> Data Scientist | D81: 4.4 | E81: San Jose, CA | F81: =IFERROR(LEFT(E81, FIND(",", E81)-1), E81) -> San Jose | G81: 10000+ | H81: IT Services | I81: 86 | J81: 141 | K81: 113.5 | L81: =IF(K81<50,"<$50K",IF(K81<75,"$50–75K",IF(K81<100,"$75–100K",IF(K81<125,"$100–125K",IF(K81<150,"$125–150K",">$150K"))))) -> $100–125K | M81: 26
A82: Data Scientist | B82: =IF(OR(ISNUMBER(SEARCH("Senior",A82)),ISNUMBER(SEARCH("Sr",A82)),ISNUMBER(SEARCH("Lead",A82)),ISNUMBER(SEARCH("Principal",A82))),"Senior",IF(OR(ISNUMBER(SEARCH("Junior",A82)),ISNUMBER(SEARCH("Jr",A82)),ISNUMBER(SEARCH("Entry",A82)),ISNUMBER(SEARCH("Associate",A82))),"Junior",IF(OR(ISNUMBER(SEARCH("Manager",A82)),ISNUMBER(SEARCH("Director",A82)),ISNUMBER(SEARCH("Head",A82)),ISNUMBER(SEARCH("VP",A82))),"Management","Mid-Level"))) -> Mid-Level | C82: =IF(ISNUMBER(SEARCH("Machine Learn",A82)),"ML Engineer",IF(ISNUMBER(SEARCH("Data Engineer",A82)),"Data Engineer",IF(ISNUMBER(SEARCH("Data Analyst",A82)),"Data Analyst",IF(ISNUMBER(SEARCH("Business Analyst",A82)),"Business Analyst",IF(ISNUMBER(SEARCH("Research",A82)),"Research Scientist",IF(ISNUMBER(SEARCH("Manager",A82)),"DS Manager",IF(ISNUMBER(SEARCH("Director",A82)),"Director/VP","Data Scientist"))))))) -> Data Scientist | D82: 3.9 | E82: San Francisco, CA | F82: =IFERROR(LEFT(E82, FIND(",", E82)-1), E82) -> San Francisco | G82: 51 - 200 | H82: Health Care Services & Hospitals | I82: 94 | J82: 154 | K82: 124 | L82: =IF(K82<50,"<$50K",IF(K82<75,"$50–75K",IF(K82<100,"$75–100K",IF(K82<125,"$100–125K",IF(K82<150,"$125–150K",">$150K"))))) -> $100–125K | M82: 5
A83: Jr. Business Data Analyst | B83: =IF(OR(ISNUMBER(SEARCH("Senior",A83)),ISNUMBER(SEARCH("Sr",A83)),ISNUMBER(SEARCH("Lead",A83)),ISNUMBER(SEARCH("Principal",A83))),"Senior",IF(OR(ISNUMBER(SEARCH("Junior",A83)),ISNUMBER(SEARCH("Jr",A83)),ISNUMBER(SEARCH("Entry",A83)),ISNUMBER(SEARCH("Associate",A83))),"Junior",IF(OR(ISNUMBER(SEARCH("Manager",A83)),ISNUMBER(SEARCH("Director",A83)),ISNUMBER(SEARCH("Head",A83)),ISNUMBER(SEARCH("VP",A83))),"Management","Mid-Level"))) -> Junior | C83: =IF(ISNUMBER(SEARCH("Machine Learn",A83)),"ML Engineer",IF(ISNUMBER(SEARCH("Data Engineer",A83)),"Data Engineer",IF(ISNUMBER(SEARCH("Data Analyst",A83)),"Data Analyst",IF(ISNUMBER(SEARCH("Business Analyst",A83)),"Business Analyst",IF(ISNUMBER(SEARCH("Research",A83)),"Research Scientist",IF(ISNUMBER(SEARCH("Manager",A83)),"DS Manager",IF(ISNUMBER(SEARCH("Director",A83)),"Director/VP","Data Scientist"))))))) -> Data Analyst | D83: 4.7 | E83: Harrisburg, PA | F83: =IFERROR(LEFT(E83, FIND(",", E83)-1), E83) -> Harrisburg | G83: 201 - 500 | H83: Advertising & Marketing | I83: 37 | J83: 76 | K83: 56.5 | L83: =IF(K83<50,"<$50K",IF(K83<75,"$50–75K",IF(K83<100,"$75–100K",IF(K83<125,"$100–125K",IF(K83<150,"$125–150K",">$150K"))))) -> $50–75K | M83: 24
A84: Data Scientist | B84: =IF(OR(ISNUMBER(SEARCH("Senior",A84)),ISNUMBER(SEARCH("Sr",A84)),ISNUMBER(SEARCH("Lead",A84)),ISNUMBER(SEARCH("Principal",A84))),"Senior",IF(OR(ISNUMBER(SEARCH("Junior",A84)),ISNUMBER(SEARCH("Jr",A84)),ISNUMBER(SEARCH("Entry",A84)),ISNUMBER(SEARCH("Associate",A84))),"Junior",IF(OR(ISNUMBER(SEARCH("Manager",A84)),ISNUMBER(SEARCH("Director",A84)),ISNUMBER(SEARCH("Head",A84)),ISNUMBER(SEARCH("VP",A84))),"Management","Mid-Level"))) -> Mid-Level | C84: =IF(ISNUMBER(SEARCH("Machine Learn",A84)),"ML Engineer",IF(ISNUMBER(SEARCH("Data Engineer",A84)),"Data Engineer",IF(ISNUMBER(SEARCH("Data Analyst",A84)),"Data Analyst",IF(ISNUMBER(SEARCH("Business Analyst",A84)),"Business Analyst",IF(ISNUMBER(SEARCH("Research",A84)),"Research Scientist",IF(ISNUMBER(SEARCH("Manager",A84)),"DS Manager",IF(ISNUMBER(SEARCH("Director",A84)),"Director/VP","Data Scientist"))))))) -> Data Scientist | D84: 4.5 | E84: Laurel, MD | F84: =IFERROR(LEFT(E84, FIND(",", E84)-1), E84) -> Laurel | G84: 5001 - 10000 | H84: Aerospace & Defense | I84: 100 | J84: 160 | K84: 130 | L84: =IF(K84<50,"<$50K",IF(K84<75,"$50–75K",IF(K84<100,"$75–100K",IF(K84<125,"$100–125K",IF(K84<150,"$125–150K",">$150K"))))) -> $125–150K | M84: 79
... A100: Data Analyst | B100: =IF(OR(ISNUMBER(SEARCH("Senior",A100)),ISNUMBER(SEARCH("Sr",A100)),ISNUMBER(SEARCH("Lead",A100)),ISNUMBER(SEARCH("Principal",A100))),"Senior",IF(OR(ISNUMBER(SEARCH("Junior",A100)),ISNUMBER(SEARCH("Jr",A100)),ISNUMBER(SEARCH("Entry",A100)),ISNUMBER(SEARCH("Associate",A100))),"Junior",IF(OR(ISNUMBER(SEARCH("Manager",A100)),ISNUMBER(SEARCH("Director",A100)),ISNUMBER(SEARCH("Head",A100)),ISNUMBER(SEARCH("VP",A100))),"Management","Mid-Level"))) -> Mid-Level | C100: =IF(ISNUMBER(SEARCH("Machine Learn",A100)),"ML Engineer",IF(ISNUMBER(SEARCH("Data Engineer",A100)),"Data Engineer",IF(ISNUMBER(SEARCH("Data Analyst",A100)),"Data Analyst",IF(ISNUMBER(SEARCH("Business Analyst",A100)),"Business Analyst",IF(ISNUMBER(SEARCH("Research",A100)),"Research Scientist",IF(ISNUMBER(SEARCH("Manager",A100)),"DS Manager",IF(ISNUMBER(SEARCH("Director",A100)),"Director/VP","Data Scientist"))))))) -> Data Analyst | D100: 3.1 | E100: Milwaukee, WI | F100: =IFERROR(LEFT(E100, FIND(",", E100)-1), E100) -> Milwaukee | G100: 1001 - 5000 | H100: Insurance Carriers | I100: 40 | J100: 73 | K100: 56.5 | L100: =IF(K100<50,"<$50K",IF(K100<75,"$50–75K",IF(K100<100,"$75–100K",IF(K100<125,"$100–125K",IF(K100<150,"$125–150K",">$150K"))))) -> $50–75K | M100: 20
A101: Lead Data Scientist | B101: =IF(OR(ISNUMBER(SEARCH("Senior",A101)),ISNUMBER(SEARCH("Sr",A101)),ISNUMBER(SEARCH("Lead",A101)),ISNUMBER(SEARCH("Principal",A101))),"Senior",IF(OR(ISNUMBER(SEARCH("Junior",A101)),ISNUMBER(SEARCH("Jr",A101)),ISNUMBER(SEARCH("Entry",A101)),ISNUMBER(SEARCH("Associate",A101))),"Junior",IF(OR(ISNUMBER(SEARCH("Manager",A101)),ISNUMBER(SEARCH("Director",A101)),ISNUMBER(SEARCH("Head",A101)),ISNUMBER(SEARCH("VP",A101))),"Management","Mid-Level"))) -> Senior | C101: =IF(ISNUMBER(SEARCH("Machine Learn",A101)),"ML Engineer",IF(ISNUMBER(SEARCH("Data Engineer",A101)),"Data Engineer",IF(ISNUMBER(SEARCH("Data Analyst",A101)),"Data Analyst",IF(ISNUMBER(SEARCH("Business Analyst",A101)),"Business Analyst",IF(ISNUMBER(SEARCH("Research",A101)),"Research Scientist",IF(ISNUMBER(SEARCH("Manager",A101)),"DS Manager",IF(ISNUMBER(SEARCH("Director",A101)),"Director/VP","Data Scientist"))))))) -> Data Scientist | D101: 4.1 | E101: Silver Spring, MD | F101: =IFERROR(LEFT(E101, FIND(",", E101)-1), E101) -> Silver Spring | G101: 18264 | H101: IT Services | I101: 102 | J101: 164 | K101: 133 | L101: =IF(K101<50,"<$50K",IF(K101<75,"$50–75K",IF(K101<100,"$75–100K",IF(K101<125,"$100–125K",IF(K101<150,"$125–150K",">$150K"))))) -> $125–150K | M101: 14
A102: Data Scientist | B102: =IF(OR(ISNUMBER(SEARCH("Senior",A102)),ISNUMBER(SEARCH("Sr",A102)),ISNUMBER(SEARCH("Lead",A102)),ISNUMBER(SEARCH("Principal",A102))),"Senior",IF(OR(ISNUMBER(SEARCH("Junior",A102)),ISNUMBER(SEARCH("Jr",A102)),ISNUMBER(SEARCH("Entry",A102)),ISNUMBER(SEARCH("Associate",A102))),"Junior",IF(OR(ISNUMBER(SEARCH("Manager",A102)),ISNUMBER(SEARCH("Director",A102)),ISNUMBER(SEARCH("Head",A102)),ISNUMBER(SEARCH("VP",A102))),"Management","Mid-Level"))) -> Mid-Level | C102: =IF(ISNUMBER(SEARCH("Machine Learn",A102)),"ML Engineer",IF(ISNUMBER(SEARCH("Data Engineer",A102)),"Data Engineer",IF(ISNUMBER(SEARCH("Data Analyst",A102)),"Data Analyst",IF(ISNUMBER(SEARCH("Business Analyst",A102)),"Business Analyst",IF(ISNUMBER(SEARCH("Research",A102)),"Research Scientist",IF(ISNUMBER(SEARCH("Manager",A102)),"DS Manager",IF(ISNUMBER(SEARCH("Director",A102)),"Director/VP","Data Scientist"))))))) -> Data Scientist | D102: 3.8 | E102: New York, NY | F102: =IFERROR(LEFT(E102, FIND(",", E102)-1), E102) -> New York | G102: 51 - 200 | H102: Research & Development | I102: 89 | J102: 153 | K102: 121 | L102: =IF(K102<50,"<$50K",IF(K102<75,"$50–75K",IF(K102<100,"$75–100K",IF(K102<125,"$100–125K",IF(K102<150,"$125–150K",">$150K"))))) -> $100–125K | M102: 9
A103: Data Scientist | B103: =IF(OR(ISNUMBER(SEARCH("Senior",A103)),ISNUMBER(SEARCH("Sr",A103)),ISNUMBER(SEARCH("Lead",A103)),ISNUMBER(SEARCH("Principal",A103))),"Senior",IF(OR(ISNUMBER(SEARCH("Junior",A103)),ISNUMBER(SEARCH("Jr",A103)),ISNUMBER(SEARCH("Entry",A103)),ISNUMBER(SEARCH("Associate",A103))),"Junior",IF(OR(ISNUMBER(SEARCH("Manager",A103)),ISNUMBER(SEARCH("Director",A103)),ISNUMBER(SEARCH("Head",A103)),ISNUMBER(SEARCH("VP",A103))),"Management","Mid-Level"))) -> Mid-Level | C103: =IF(ISNUMBER(SEARCH("Machine Learn",A103)),"ML Engineer",IF(ISNUMBER(SEARCH("Data Engineer",A103)),"Data Engineer",IF(ISNUMBER(SEARCH("Data Analyst",A103)),"Data Analyst",IF(ISNUMBER(SEARCH("Business Analyst",A103)),"Business Analyst",IF(ISNUMBER(SEARCH("Research",A103)),"Research Scientist",IF(ISNUMBER(SEARCH("Manager",A103)),"DS Manager",IF(ISNUMBER(SEARCH("Director",A103)),"Director/VP","Data Scientist"))))))) -> Data Scientist | D103: 4.7 | E103: Syracuse, NY | F103: =IFERROR(LEFT(E103, FIND(",", E103)-1), E103) -> Syracuse | G103: 501 - 1000 | H103: Security Services | I103: 61 | J103: 110 | K103: 85.5 | L103: =IF(K103<50,"<$50K",IF(K103<75,"$50–75K",IF(K103<100,"$75–100K",IF(K103<125,"$100–125K",IF(K103<150,"$125–150K",">$150K"))))) -> $75–100K | M103: 29
A104: Data Scientist, Rice University | B104: =IF(OR(ISNUMBER(SEARCH("Senior",A104)),ISNUMBER(SEARCH("Sr",A104)),ISNUMBER(SEARCH("Lead",A104)),ISNUMBER(SEARCH("Principal",A104))),"Senior",IF(OR(ISNUMBER(SEARCH("Junior",A104)),ISNUMBER(SEARCH("Jr",A104)),ISNUMBER(SEARCH("Entry",A104)),ISNUMBER(SEARCH("Associate",A104))),"Junior",IF(OR(ISNUMBER(SEARCH("Manager",A104)),ISNUMBER(SEARCH("Director",A104)),ISNUMBER(SEARCH("Head",A104)),ISNUMBER(SEARCH("VP",A104))),"Management","Mid-Level"))) -> Mid-Level | C104: =IF(ISNUMBER(SEARCH("Machine Learn",A104)),"ML Engineer",IF(ISNUMBER(SEARCH("Data Engineer",A104)),"Data Engineer",IF(ISNUMBER(SEARCH("Data Analyst",A104)),"Data Analyst",IF(ISNUMBER(SEARCH("Business Analyst",A104)),"Business Analyst",IF(ISNUMBER(SEARCH("Research",A104)),"Research Scientist",IF(ISNUMBER(SEARCH("Manager",A104)),"DS Manager",IF(ISNUMBER(SEARCH("Director",A104)),"Director/VP","Data Scientist"))))))) -> Data Scientist | D104: 4.3 | E104: Houston, TX | F104: =IFERROR(LEFT(E104, FIND(",", E104)-1), E104) -> Houston | G104: 1001 - 5000 | H104: Education Training Services | I104: 65 | J104: 110 | K104: 87.5 | L104: =IF(K104<50,"<$50K",IF(K104<75,"$50–75K",IF(K104<100,"$75–100K",IF(K104<125,"$100–125K",IF(K104<150,"$125–150K",">$150K"))))) -> $75–100K | M104: 6
A105: Senior Data Scientist | B105: =IF(OR(ISNUMBER(SEARCH("Senior",A105)),ISNUMBER(SEARCH("Sr",A105)),ISNUMBER(SEARCH("Lead",A105)),ISNUMBER(SEARCH("Principal",A105))),"Senior",IF(OR(ISNUMBER(SEARCH("Junior",A105)),ISNUMBER(SEARCH("Jr",A105)),ISNUMBER(SEARCH("Entry",A105)),ISNUMBER(SEARCH("Associate",A105))),"Junior",IF(OR(ISNUMBER(SEARCH("Manager",A105)),ISNUMBER(SEARCH("Director",A105)),ISNUMBER(SEARCH("Head",A105)),ISNUMBER(SEARCH("VP",A105))),"Management","Mid-Level"))) -> Senior | C105: =IF(ISNUMBER(SEARCH("Machine Learn",A105)),"ML Engineer",IF(ISNUMBER(SEARCH("Data Engineer",A105)),"Data Engineer",IF(ISNUMBER(SEARCH("Data Analyst",A105)),"Data Analyst",IF(ISNUMBER(SEARCH("Business Analyst",A105)),"Business Analyst",IF(ISNUMBER(SEARCH("Research",A105)),"Research Scientist",IF(ISNUMBER(SEARCH("Manager",A105)),"DS Manager",IF(ISNUMBER(SEARCH("Director",A105)),"Director/VP","Data Scientist"))))))) -> Data Scientist | D105: 4.2 | E105: Washington, DC | F105: =IFERROR(LEFT(E105, FIND(",", E105)-1), E105) -> Washington | G105: 1001 - 5000 | H105: Consulting | I105: 200 | J105: 275 | K105: 237.5 | L105: =IF(K105<50,"<$50K",IF(K105<75,"$50–75K",IF(K105<100,"$75–100K",IF(K105<125,"$100–125K",IF(K105<150,"$125–150K",">$150K"))))) -> >$150K | M105: 86
A106: Data Engineer | B106: =IF(OR(ISNUMBER(SEARCH("Senior",A106)),ISNUMBER(SEARCH("Sr",A106)),ISNUMBER(SEARCH("Lead",A106)),ISNUMBER(SEARCH("Principal",A106))),"Senior",IF(OR(ISNUMBER(SEARCH("Junior",A106)),ISNUMBER(SEARCH("Jr",A106)),ISNUMBER(SEARCH("Entry",A106)),ISNUMBER(SEARCH("Associate",A106))),"Junior",IF(OR(ISNUMBER(SEARCH("Manager",A106)),ISNUMBER(SEARCH("Director",A106)),ISNUMBER(SEARCH("Head",A106)),ISNUMBER(SEARCH("VP",A106))),"Management","Mid-Level"))) -> Mid-Level | C106: =IF(ISNUMBER(SEARCH("Machine Learn",A106)),"ML Engineer",IF(ISNUMBER(SEARCH("Data Engineer",A106)),"Data Engineer",IF(ISNUMBER(SEARCH("Data Analyst",A106)),"Data Analyst",IF(ISNUMBER(SEARCH("Business Analyst",A106)),"Business Analyst",IF(ISNUMBER(SEARCH("Research",A106)),"Research Scientist",IF(ISNUMBER(SEARCH("Manager",A106)),"DS Manager",IF(ISNUMBER(SEARCH("Director",A106)),"Director/VP","Data Scientist"))))))) -> Data Engineer | D106: 3.9 | E106: Charlotte, NC | F106: =IFERROR(LEFT(E106, FIND(",", E106)-1), E106) -> Charlotte | G106: 1001 - 5000 | H106: IT Services | I106: 68 | J106: 123 | K106: 95.5 | L106: =IF(K106<50,"<$50K",IF(K106<75,"$50–75K",IF(K106<100,"$75–100K",IF(K106<125,"$100–125K",IF(K106<150,"$125–150K",">$150K"))))) -> $75–100K | M106: 24
A107: Senior Data Scientist | B107: =IF(OR(ISNUMBER(SEARCH("Senior",A107)),ISNUMBER(SEARCH("Sr",A107)),ISNUMBER(SEARCH("Lead",A107)),ISNUMBER(SEARCH("Principal",A107))),"Senior",IF(OR(ISNUMBER(SEARCH("Junior",A107)),ISNUMBER(SEARCH("Jr",A107)),ISNUMBER(SEARCH("Entry",A107)),ISNUMBER(SEARCH("Associate",A107))),"Junior",IF(OR(ISNUMBER(SEARCH("Manager",A107)),ISNUMBER(SEARCH("Director",A107)),ISNUMBER(SEARCH("Head",A107)),ISNUMBER(SEARCH("VP",A107))),"Management","Mid-Level"))) -> Senior | C107: =IF(ISNUMBER(SEARCH("Machine Learn",A107)),"ML Engineer",IF(ISNUMBER(SEARCH("Data Engineer",A107)),"Data Engineer",IF(ISNUMBER(SEARCH("Data Analyst",A107)),"Data Analyst",IF(ISNUMBER(SEARCH("Business Analyst",A107)),"Business Analyst",IF(ISNUMBER(SEARCH("Research",A107)),"Research Scientist",IF(ISNUMBER(SEARCH("Manager",A107)),"DS Manager",IF(ISNUMBER(SEARCH("Director",A107)),"Director/VP","Data Scientist"))))))) -> Data Scientist | D107: 3.3 | E107: Southfield, MI | F107: =IFERROR(LEFT(E107, FIND(",", E107)-1), E107) -> Southfield | G107: 10000+ | H107: Transportation Equipment Manufacturing | I107: 80 | J107: 129 | K107: 104.5 | L107: =IF(K107<50,"<$50K",IF(K107<75,"$50–75K",IF(K107<100,"$75–100K",IF(K107<125,"$100–125K",IF(K107<150,"$125–150K",">$150K"))))) -> $100–125K | M107: 27
A108: Financial Data Analyst | B108: =IF(OR(ISNUMBER(SEARCH("Senior",A108)),ISNUMBER(SEARCH("Sr",A108)),ISNUMBER(SEARCH("Lead",A108)),ISNUMBER(SEARCH("Principal",A108))),"Senior",IF(OR(ISNUMBER(SEARCH("Junior",A108)),ISNUMBER(SEARCH("Jr",A108)),ISNUMBER(SEARCH("Entry",A108)),ISNUMBER(SEARCH("Associate",A108))),"Junior",IF(OR(ISNUMBER(SEARCH("Manager",A108)),ISNUMBER(SEARCH("Director",A108)),ISNUMBER(SEARCH("Head",A108)),ISNUMBER(SEARCH("VP",A108))),"Management","Mid-Level"))) -> Mid-Level | C108: =IF(ISNUMBER(SEARCH("Machine Learn",A108)),"ML Engineer",IF(ISNUMBER(SEARCH("Data Engineer",A108)),"Data Engineer",IF(ISNUMBER(SEARCH("Data Analyst",A108)),"Data Analyst",IF(ISNUMBER(SEARCH("Business Analyst",A108)),"Business Analyst",IF(ISNUMBER(SEARCH("Research",A108)),"Research Scientist",IF(ISNUMBER(SEARCH("Manager",A108)),"DS Manager",IF(ISNUMBER(SEARCH("Director",A108)),"Director/VP","Data Scientist"))))))) -> Data Analyst | D108: 4.7 | E108: Matawan, NJ | F108: =IFERROR(LEFT(E108, FIND(",", E108)-1), E108) -> Matawan | G108: 201 - 500 | H108: Computer Hardware & Software | I108: 41 | J108: 72 | K108: 56.5 | L108: =IF(K108<50,"<$50K",IF(K108<75,"$50–75K",IF(K108<100,"$75–100K",IF(K108<125,"$100–125K",IF(K108<150,"$125–150K",">$150K"))))) -> $50–75K | M108: 9
A109: Senior Data Analyst | B109: =IF(OR(ISNUMBER(SEARCH("Senior",A109)),ISNUMBER(SEARCH("Sr",A109)),ISNUMBER(SEARCH("Lead",A109)),ISNUMBER(SEARCH("Principal",A109))),"Senior",IF(OR(ISNUMBER(SEARCH("Junior",A109)),ISNUMBER(SEARCH("Jr",A109)),ISNUMBER(SEARCH("Entry",A109)),ISNUMBER(SEARCH("Associate",A109))),"Junior",IF(OR(ISNUMBER(SEARCH("Manager",A109)),ISNUMBER(SEARCH("Director",A109)),ISNUMBER(SEARCH("Head",A109)),ISNUMBER(SEARCH("VP",A109))),"Management","Mid-Level"))) -> Senior | C109: =IF(ISNUMBER(SEARCH("Machine Learn",A109)),"ML Engineer",IF(ISNUMBER(SEARCH("Data Engineer",A109)),"Data Engineer",IF(ISNUMBER(SEARCH("Data Analyst",A109)),"Data Analyst",IF(ISNUMBER(SEARCH("Business Analyst",A109)),"Business Analyst",IF(ISNUMBER(SEARCH("Research",A109)),"Research Scientist",IF(ISNUMBER(SEARCH("Manager",A109)),"DS Manager",IF(ISNUMBER(SEARCH("Director",A109)),"Director/VP","Data Scientist"))))))) -> Data Analyst | D109: 4.3 | E109: Phoenix, AZ | F109: =IFERROR(LEFT(E109, FIND(",", E109)-1), E109) -> Phoenix | G109: 201 - 500 | H109: Enterprise Software & Network Solutions | I109: 39 | J109: 71 | K109: 55 | L109: =IF(K109<50,"<$50K",IF(K109<75,"$50–75K",IF(K109<100,"$75–100K",IF(K109<125,"$100–125K",IF(K109<150,"$125–150K",">$150K"))))) -> $50–75K | M109: 11
A110: Research Scientist | B110: =IF(OR(ISNUMBER(SEARCH("Senior",A110)),ISNUMBER(SEARCH("Sr",A110)),ISNUMBER(SEARCH("Lead",A110)),ISNUMBER(SEARCH("Principal",A110))),"Senior",IF(OR(ISNUMBER(SEARCH("Junior",A110)),ISNUMBER(SEARCH("Jr",A110)),ISNUMBER(SEARCH("Entry",A110)),ISNUMBER(SEARCH("Associate",A110))),"Junior",IF(OR(ISNUMBER(SEARCH("Manager",A110)),ISNUMBER(SEARCH("Director",A110)),ISNUMBER(SEARCH("Head",A110)),ISNUMBER(SEARCH("VP",A110))),"Management","Mid-Level"))) -> Mid-Level | C110: =IF(ISNUMBER(SEARCH("Machine Learn",A110)),"ML Engineer",IF(ISNUMBER(SEARCH("Data Engineer",A110)),"Data Engineer",IF(ISNUMBER(SEARCH("Data Analyst",A110)),"Data Analyst",IF(ISNUMBER(SEARCH("Business Analyst",A110)),"Business Analyst",IF(ISNUMBER(SEARCH("Research",A110)),"Research Scientist",IF(ISNUMBER(SEARCH("Manager",A110)),"DS Manager",IF(ISNUMBER(SEARCH("Director",A110)),"Director/VP","Data Scientist"))))))) -> Research Scientist | D110: 2.9 | E110: Omaha, NE | F110: =IFERROR(LEFT(E110, FIND(",", E110)-1), E110) -> Omaha | G110: 1001 - 5000 | H110: Health Care Services & Hospitals | I110: 38 | J110: 85 | K110: 61.5 | L110: =IF(K110<50,"<$50K",IF(K110<75,"$50–75K",IF(K110<100,"$75–100K",IF(K110<125,"$100–125K",IF(K110<150,"$125–150K",">$150K"))))) -> $50–75K | M110: 44
A111: Data Scientist | B111: =IF(OR(ISNUMBER(SEARCH("Senior",A111)),ISNUMBER(SEARCH("Sr",A111)),ISNUMBER(SEARCH("Lead",A111)),ISNUMBER(SEARCH("Principal",A111))),"Senior",IF(OR(ISNUMBER(SEARCH("Junior",A111)),ISNUMBER(SEARCH("Jr",A111)),ISNUMBER(SEARCH("Entry",A111)),ISNUMBER(SEARCH("Associate",A111))),"Junior",IF(OR(ISNUMBER(SEARCH("Manager",A111)),ISNUMBER(SEARCH("Director",A111)),ISNUMBER(SEARCH("Head",A111)),ISNUMBER(SEARCH("VP",A111))),"Management","Mid-Level"))) -> Mid-Level | C111: =IF(ISNUMBER(SEARCH("Machine Learn",A111)),"ML Engineer",IF(ISNUMBER(SEARCH("Data Engineer",A111)),"Data Engineer",IF(ISNUMBER(SEARCH("Data Analyst",A111)),"Data Analyst",IF(ISNUMBER(SEARCH("Business Analyst",A111)),"Business Analyst",IF(ISNUMBER(SEARCH("Research",A111)),"Research Scientist",IF(ISNUMBER(SEARCH("Manager",A111)),"DS Manager",IF(ISNUMBER(SEARCH("Director",A111)),"Director/VP","Data Scientist"))))))) -> Data Scientist | D111: 4.5 | E111: San Francisco, CA | F111: =IFERROR(LEFT(E111, FIND(",", E111)-1), E111) -> San Francisco | G111: 201 - 500 | H111: Computer Hardware & Software | I111: 121 | J111: 193 | K111: 157 | L111: =IF(K111<50,"<$50K",IF(K111<75,"$50–75K",IF(K111<100,"$75–100K",IF(K111<125,"$100–125K",IF(K111<150,"$125–150K",">$150K"))))) -> >$150K | M111: 15
A112: Data Engineer | B112: =IF(OR(ISNUMBER(SEARCH("Senior",A112)),ISNUMBER(SEARCH("Sr",A112)),ISNUMBER(SEARCH("Lead",A112)),ISNUMBER(SEARCH("Principal",A112))),"Senior",IF(OR(ISNUMBER(SEARCH("Junior",A112)),ISNUMBER(SEARCH("Jr",A112)),ISNUMBER(SEARCH("Entry",A112)),ISNUMBER(SEARCH("Associate",A112))),"Junior",IF(OR(ISNUMBER(SEARCH("Manager",A112)),ISNUMBER(SEARCH("Director",A112)),ISNUMBER(SEARCH("Head",A112)),ISNUMBER(SEARCH("VP",A112))),"Management","Mid-Level"))) -> Mid-Level | C112: =IF(ISNUMBER(SEARCH("Machine Learn",A112)),"ML Engineer",IF(ISNUMBER(SEARCH("Data Engineer",A112)),"Data Engineer",IF(ISNUMBER(SEARCH("Data Analyst",A112)),"Data Analyst",IF(ISNUMBER(SEARCH("Business Analyst",A112)),"Business Analyst",IF(ISNUMBER(SEARCH("Research",A112)),"Research Scientist",IF(ISNUMBER(SEARCH("Manager",A112)),"DS Manager",IF(ISNUMBER(SEARCH("Director",A112)),"Director/VP","Data Scientist"))))))) -> Data Engineer | D112: 3.4 | E112: Lyndhurst, NJ | F112: =IFERROR(LEFT(E112, FIND(",", E112)-1), E112) -> Lyndhurst | G112: 201 - 500 | H112: Internet | I112: 54 | J112: 102 | K112: 78 | L112: =IF(K112<50,"<$50K",IF(K112<75,"$50–75K",IF(K112<100,"$75–100K",IF(K112<125,"$100–125K",IF(K112<150,"$125–150K",">$150K"))))) -> $75–100K | M112: 2
A113: Data Scientist | B113: =IF(OR(ISNUMBER(SEARCH("Senior",A113)),ISNUMBER(SEARCH("Sr",A113)),ISNUMBER(SEARCH("Lead",A113)),ISNUMBER(SEARCH("Principal",A113))),"Senior",IF(OR(ISNUMBER(SEARCH("Junior",A113)),ISNUMBER(SEARCH("Jr",A113)),ISNUMBER(SEARCH("Entry",A113)),ISNUMBER(SEARCH("Associate",A113))),"Junior",IF(OR(ISNUMBER(SEARCH("Manager",A113)),ISNUMBER(SEARCH("Director",A113)),ISNUMBER(SEARCH("Head",A113)),ISNUMBER(SEARCH("VP",A113))),"Management","Mid-Level"))) -> Mid-Level | C113: =IF(ISNUMBER(SEARCH("Machine Learn",A113)),"ML Engineer",IF(ISNUMBER(SEARCH("Data Engineer",A113)),"Data Engineer",IF(ISNUMBER(SEARCH("Data Analyst",A113)),"Data Analyst",IF(ISNUMBER(SEARCH("Business Analyst",A113)),"Business Analyst",IF(ISNUMBER(SEARCH("Research",A113)),"Research Scientist",IF(ISNUMBER(SEARCH("Manager",A113)),"DS Manager",IF(ISNUMBER(SEARCH("Director",A113)),"Director/VP","Data Scientist"))))))) -> Data Scientist | D113: 3.7 | E113: Cambridge, MA | F113: =IFERROR(LEFT(E113, FIND(",", E113)-1), E113) -> Cambridge | G113: 10000+ | H113: Biotech & Pharmaceuticals | I113: 83 | J113: 144 | K113: 113.5 | L113: =IF(K113<50,"<$50K",IF(K113<75,"$50–75K",IF(K113<100,"$75–100K",IF(K113<125,"$100–125K",IF(K113<150,"$125–150K",">$150K"))))) -> $100–125K | M113: 240
... A135: Scientist 2, QC Viral Vector | B135: =IF(OR(ISNUMBER(SEARCH("Senior",A135)),ISNUMBER(SEARCH("Sr",A135)),ISNUMBER(SEARCH("Lead",A135)),ISNUMBER(SEARCH("Principal",A135))),"Senior",IF(OR(ISNUMBER(SEARCH("Junior",A135)),ISNUMBER(SEARCH("Jr",A135)),ISNUMBER(SEARCH("Entry",A135)),ISNUMBER(SEARCH("Associate",A135))),"Junior",IF(OR(ISNUMBER(SEARCH("Manager",A135)),ISNUMBER(SEARCH("Director",A135)),ISNUMBER(SEARCH("Head",A135)),ISNUMBER(SEARCH("VP",A135))),"Management","Mid-Level"))) -> Mid-Level | C135: =IF(ISNUMBER(SEARCH("Machine Learn",A135)),"ML Engineer",IF(ISNUMBER(SEARCH("Data Engineer",A135)),"Data Engineer",IF(ISNUMBER(SEARCH("Data Analyst",A135)),"Data Analyst",IF(ISNUMBER(SEARCH("Business Analyst",A135)),"Business Analyst",IF(ISNUMBER(SEARCH("Research",A135)),"Research Scientist",IF(ISNUMBER(SEARCH("Manager",A135)),"DS Manager",IF(ISNUMBER(SEARCH("Director",A135)),"Director/VP","Data Scientist"))))))) -> Data Scientist | D135: 3.8 | E135: Novato, CA | F135: =IFERROR(LEFT(E135, FIND(",", E135)-1), E135) -> Novato | G135: 1001 - 5000 | H135: Biotech & Pharmaceuticals | I135: 113 | J135: 223 | K135: 168 | L135: =IF(K135<50,"<$50K",IF(K135<75,"$50–75K",IF(K135<100,"$75–100K",IF(K135<125,"$100–125K",IF(K135<150,"$125–150K",">$150K"))))) -> >$150K | M135: 24
A136: Machine Learning Engineer | B136: =IF(OR(ISNUMBER(SEARCH("Senior",A136)),ISNUMBER(SEARCH("Sr",A136)),ISNUMBER(SEARCH("Lead",A136)),ISNUMBER(SEARCH("Principal",A136))),"Senior",IF(OR(ISNUMBER(SEARCH("Junior",A136)),ISNUMBER(SEARCH("Jr",A136)),ISNUMBER(SEARCH("Entry",A136)),ISNUMBER(SEARCH("Associate",A136))),"Junior",IF(OR(ISNUMBER(SEARCH("Manager",A136)),ISNUMBER(SEARCH("Director",A136)),ISNUMBER(SEARCH("Head",A136)),ISNUMBER(SEARCH("VP",A136))),"Management","Mid-Level"))) -> Mid-Level | C136: =IF(ISNUMBER(SEARCH("Machine Learn",A136)),"ML Engineer",IF(ISNUMBER(SEARCH("Data Engineer",A136)),"Data Engineer",IF(ISNUMBER(SEARCH("Data Analyst",A136)),"Data Analyst",IF(ISNUMBER(SEARCH("Business Analyst",A136)),"Business Analyst",IF(ISNUMBER(SEARCH("Research",A136)),"Research Scientist",IF(ISNUMBER(SEARCH("Manager",A136)),"DS Manager",IF(ISNUMBER(SEARCH("Director",A136)),"Director/VP","Data Scientist"))))))) -> ML Engineer | D136: 4.3 | E136: Aurora, CO | F136: =IFERROR(LEFT(E136, FIND(",", E136)-1), E136) -> Aurora | G136: 18264 | H136: Aerospace & Defense | I136: 72 | J136: 129 | K136: 100.5 | L136: =IF(K136<50,"<$50K",IF(K136<75,"$50–75K",IF(K136<100,"$75–100K",IF(K136<125,"$100–125K",IF(K136<150,"$125–150K",">$150K"))))) -> $100–125K | M136: 14
A137: Data Scientist/ML Engineer | B137: =IF(OR(ISNUMBER(SEARCH("Senior",A137)),ISNUMBER(SEARCH("Sr",A137)),ISNUMBER(SEARCH("Lead",A137)),ISNUMBER(SEARCH("Principal",A137))),"Senior",IF(OR(ISNUMBER(SEARCH("Junior",A137)),ISNUMBER(SEARCH("Jr",A137)),ISNUMBER(SEARCH("Entry",A137)),ISNUMBER(SEARCH("Associate",A137))),"Junior",IF(OR(ISNUMBER(SEARCH("Manager",A137)),ISNUMBER(SEARCH("Director",A137)),ISNUMBER(SEARCH("Head",A137)),ISNUMBER(SEARCH("VP",A137))),"Management","Mid-Level"))) -> Mid-Level | C137: =IF(ISNUMBER(SEARCH("Machine Learn",A137)),"ML Engineer",IF(ISNUMBER(SEARCH("Data Engineer",A137)),"Data Engineer",IF(ISNUMBER(SEARCH("Data Analyst",A137)),"Data Analyst",IF(ISNUMBER(SEARCH("Business Analyst",A137)),"Business Analyst",IF(ISNUMBER(SEARCH("Research",A137)),"Research Scientist",IF(ISNUMBER(SEARCH("Manager",A137)),"DS Manager",IF(ISNUMBER(SEARCH("Director",A137)),"Director/VP","Data Scientist"))))))) -> Data Scientist | D137: 3.4 | E137: New York, NY | F137: =IFERROR(LEFT(E137, FIND(",", E137)-1), E137) -> New York | G137: 1001 - 5000 | H137: Consulting | I137: 71 | J137: 123 | K137: 97 | L137: =IF(K137<50,"<$50K",IF(K137<75,"$50–75K",IF(K137<100,"$75–100K",IF(K137<125,"$100–125K",IF(K137<150,"$125–150K",">$150K"))))) -> $75–100K | M137: 78
A138: Data Scientist | B138: =IF(OR(ISNUMBER(SEARCH("Senior",A138)),ISNUMBER(SEARCH("Sr",A138)),ISNUMBER(SEARCH("Lead",A138)),ISNUMBER(SEARCH("Principal",A138))),"Senior",IF(OR(ISNUMBER(SEARCH("Junior",A138)),ISNUMBER(SEARCH("Jr",A138)),ISNUMBER(SEARCH("Entry",A138)),ISNUMBER(SEARCH("Associate",A138))),"Junior",IF(OR(ISNUMBER(SEARCH("Manager",A138)),ISNUMBER(SEARCH("Director",A138)),ISNUMBER(SEARCH("Head",A138)),ISNUMBER(SEARCH("VP",A138))),"Management","Mid-Level"))) -> Mid-Level | C138: =IF(ISNUMBER(SEARCH("Machine Learn",A138)),"ML Engineer",IF(ISNUMBER(SEARCH("Data Engineer",A138)),"Data Engineer",IF(ISNUMBER(SEARCH("Data Analyst",A138)),"Data Analyst",IF(ISNUMBER(SEARCH("Business Analyst",A138)),"Business Analyst",IF(ISNUMBER(SEARCH("Research",A138)),"Research Scientist",IF(ISNUMBER(SEARCH("Manager",A138)),"DS Manager",IF(ISNUMBER(SEARCH("Director",A138)),"Director/VP","Data Scientist"))))))) -> Data Scientist | D138: 4.1 | E138: Chantilly, VA | F138: =IFERROR(LEFT(E138, FIND(",", E138)-1), E138) -> Chantilly | G138: 5001 - 10000 | H138: Research & Development | I138: 64 | J138: 106 | K138: 85 | L138: =IF(K138<50,"<$50K",IF(K138<75,"$50–75K",IF(K138<100,"$75–100K",IF(K138<125,"$100–125K",IF(K138<150,"$125–150K",">$150K"))))) -> $75–100K | M138: 53
A139: Customer Data Scientist | B139: =IF(OR(ISNUMBER(SEARCH("Senior",A139)),ISNUMBER(SEARCH("Sr",A139)),ISNUMBER(SEARCH("Lead",A139)),ISNUMBER(SEARCH("Principal",A139))),"Senior",IF(OR(ISNUMBER(SEARCH("Junior",A139)),ISNUMBER(SEARCH("Jr",A139)),ISNUMBER(SEARCH("Entry",A139)),ISNUMBER(SEARCH("Associate",A139))),"Junior",IF(OR(ISNUMBER(SEARCH("Manager",A139)),ISNUMBER(SEARCH("Director",A139)),ISNUMBER(SEARCH("Head",A139)),ISNUMBER(SEARCH("VP",A139))),"Management","Mid-Level"))) -> Mid-Level | C139: =IF(ISNUMBER(SEARCH("Machine Learn",A139)),"ML Engineer",IF(ISNUMBER(SEARCH("Data Engineer",A139)),"Data Engineer",IF(ISNUMBER(SEARCH("Data Analyst",A139)),"Data Analyst",IF(ISNUMBER(SEARCH("Business Analyst",A139)),"Business Analyst",IF(ISNUMBER(SEARCH("Research",A139)),"Research Scientist",IF(ISNUMBER(SEARCH("Manager",A139)),"DS Manager",IF(ISNUMBER(SEARCH("Director",A139)),"Director/VP","Data Scientist"))))))) -> Data Scientist | D139: 4.3 | E139: Mountain View, CA | F139: =IFERROR(LEFT(E139, FIND(",", E139)-1), E139) -> Mountain View | G139: 201 - 500 | H139: Enterprise Software & Network Solutions | I139: 118 | J139: 189 | K139: 153.5 | L139: =IF(K139<50,"<$50K",IF(K139<75,"$50–75K",IF(K139<100,"$75–100K",IF(K139<125,"$100–125K",IF(K139<150,"$125–150K",">$150K"))))) -> >$150K | M139: 10
A140: Data Engineer | B140: =IF(OR(ISNUMBER(SEARCH("Senior",A140)),ISNUMBER(SEARCH("Sr",A140)),ISNUMBER(SEARCH("Lead",A140)),ISNUMBER(SEARCH("Principal",A140))),"Senior",IF(OR(ISNUMBER(SEARCH("Junior",A140)),ISNUMBER(SEARCH("Jr",A140)),ISNUMBER(SEARCH("Entry",A140)),ISNUMBER(SEARCH("Associate",A140))),"Junior",IF(OR(ISNUMBER(SEARCH("Manager",A140)),ISNUMBER(SEARCH("Director",A140)),ISNUMBER(SEARCH("Head",A140)),ISNUMBER(SEARCH("VP",A140))),"Management","Mid-Level"))) -> Mid-Level | C140: =IF(ISNUMBER(SEARCH("Machine Learn",A140)),"ML Engineer",IF(ISNUMBER(SEARCH("Data Engineer",A140)),"Data Engineer",IF(ISNUMBER(SEARCH("Data Analyst",A140)),"Data Analyst",IF(ISNUMBER(SEARCH("Business Analyst",A140)),"Business Analyst",IF(ISNUMBER(SEARCH("Research",A140)),"Research Scientist",IF(ISNUMBER(SEARCH("Manager",A140)),"DS Manager",IF(ISNUMBER(SEARCH("Director",A140)),"Director/VP","Data Scientist"))))))) -> Data Engineer | D140: 5 | E140: Tampa, FL | F140: =IFERROR(LEFT(E140, FIND(",", E140)-1), E140) -> Tampa | G140: 51 - 200 | H140: IT Services | I140: 120 | J140: 145 | K140: 132.5 | L140: =IF(K140<50,"<$50K",IF(K140<75,"$50–75K",IF(K140<100,"$75–100K",IF(K140<125,"$100–125K",IF(K140<150,"$125–150K",">$150K"))))) -> $125–150K | M140: 4
A141: Data Engineer | B141: =IF(OR(ISNUMBER(SEARCH("Senior",A141)),ISNUMBER(SEARCH("Sr",A141)),ISNUMBER(SEARCH("Lead",A141)),ISNUMBER(SEARCH("Principal",A141))),"Senior",IF(OR(ISNUMBER(SEARCH("Junior",A141)),ISNUMBER(SEARCH("Jr",A141)),ISNUMBER(SEARCH("Entry",A141)),ISNUMBER(SEARCH("Associate",A141))),"Junior",IF(OR(ISNUMBER(SEARCH("Manager",A141)),ISNUMBER(SEARCH("Director",A141)),ISNUMBER(SEARCH("Head",A141)),ISNUMBER(SEARCH("VP",A141))),"Management","Mid-Level"))) -> Mid-Level | C141: =IF(ISNUMBER(SEARCH("Machine Learn",A141)),"ML Engineer",IF(ISNUMBER(SEARCH("Data Engineer",A141)),"Data Engineer",IF(ISNUMBER(SEARCH("Data Analyst",A141)),"Data Analyst",IF(ISNUMBER(SEARCH("Business Analyst",A141)),"Business Analyst",IF(ISNUMBER(SEARCH("Research",A141)),"Research Scientist",IF(ISNUMBER(SEARCH("Manager",A141)),"DS Manager",IF(ISNUMBER(SEARCH("Director",A141)),"Director/VP","Data Scientist"))))))) -> Data Engineer | D141: 4.3 | E141: Chicago, IL | F141: =IFERROR(LEFT(E141, FIND(",", E141)-1), E141) -> Chicago | G141: 51 - 200 | H141: Computer Hardware & Software | I141: 80 | J141: 120 | K141: 100 | L141: =IF(K141<50,"<$50K",IF(K141<75,"$50–75K",IF(K141<100,"$75–100K",IF(K141<125,"$100–125K",IF(K141<150,"$125–150K",">$150K"))))) -> $100–125K | M141: 13
A142: Sr. Data Scientist | B142: =IF(OR(ISNUMBER(SEARCH("Senior",A142)),ISNUMBER(SEARCH("Sr",A142)),ISNUMBER(SEARCH("Lead",A142)),ISNUMBER(SEARCH("Principal",A142))),"Senior",IF(OR(ISNUMBER(SEARCH("Junior",A142)),ISNUMBER(SEARCH("Jr",A142)),ISNUMBER(SEARCH("Entry",A142)),ISNUMBER(SEARCH("Associate",A142))),"Junior",IF(OR(ISNUMBER(SEARCH("Manager",A142)),ISNUMBER(SEARCH("Director",A142)),ISNUMBER(SEARCH("Head",A142)),ISNUMBER(SEARCH("VP",A142))),"Management","Mid-Level"))) -> Senior | C142: =IF(ISNUMBER(SEARCH("Machine Learn",A142)),"ML Engineer",IF(ISNUMBER(SEARCH("Data Engineer",A142)),"Data Engineer",IF(ISNUMBER(SEARCH("Data Analyst",A142)),"Data Analyst",IF(ISNUMBER(SEARCH("Business Analyst",A142)),"Business Analyst",IF(ISNUMBER(SEARCH("Research",A142)),"Research Scientist",IF(ISNUMBER(SEARCH("Manager",A142)),"DS Manager",IF(ISNUMBER(SEARCH("Director",A142)),"Director/VP","Data Scientist"))))))) -> Data Scientist | D142: 3.7 | E142: Denver, CO | F142: =IFERROR(LEFT(E142, FIND(",", E142)-1), E142) -> Denver | G142: 201 - 500 | H142: Travel Agencies | I142: 80 | J142: 130 | K142: 105 | L142: =IF(K142<50,"<$50K",IF(K142<75,"$50–75K",IF(K142<100,"$75–100K",IF(K142<125,"$100–125K",IF(K142<150,"$125–150K",">$150K"))))) -> $100–125K | M142: 10
A143: Data Engineer 4 - Contract | B143: =IF(OR(ISNUMBER(SEARCH("Senior",A143)),ISNUMBER(SEARCH("Sr",A143)),ISNUMBER(SEARCH("Lead",A143)),ISNUMBER(SEARCH("Principal",A143))),"Senior",IF(OR(ISNUMBER(SEARCH("Junior",A143)),ISNUMBER(SEARCH("Jr",A143)),ISNUMBER(SEARCH("Entry",A143)),ISNUMBER(SEARCH("Associate",A143))),"Junior",IF(OR(ISNUMBER(SEARCH("Manager",A143)),ISNUMBER(SEARCH("Director",A143)),ISNUMBER(SEARCH("Head",A143)),ISNUMBER(SEARCH("VP",A143))),"Management","Mid-Level"))) -> Mid-Level | C143: =IF(ISNUMBER(SEARCH("Machine Learn",A143)),"ML Engineer",IF(ISNUMBER(SEARCH("Data Engineer",A143)),"Data Engineer",IF(ISNUMBER(SEARCH("Data Analyst",A143)),"Data Analyst",IF(ISNUMBER(SEARCH("Business Analyst",A143)),"Business Analyst",IF(ISNUMBER(SEARCH("Research",A143)),"Research Scientist",IF(ISNUMBER(SEARCH("Manager",A143)),"DS Manager",IF(ISNUMBER(SEARCH("Director",A143)),"Director/VP","Data Scientist"))))))) -> Data Engineer | D143: 4.2 | E143: Riverton, UT | F143: =IFERROR(LEFT(E143, FIND(",", E143)-1), E143) -> Riverton | G143: 10000+ | H143: Religious Organizations | I143: 59 | J143: 115 | K143: 87 | L143: =IF(K143<50,"<$50K",IF(K143<75,"$50–75K",IF(K143<100,"$75–100K",IF(K143<125,"$100–125K",IF(K143<150,"$125–150K",">$150K"))))) -> $75–100K | M143: -1
A144: Data Analyst - Asset Management | B144: =IF(OR(ISNUMBER(SEARCH("Senior",A144)),ISNUMBER(SEARCH("Sr",A144)),ISNUMBER(SEARCH("Lead",A144)),ISNUMBER(SEARCH("Principal",A144))),"Senior",IF(OR(ISNUMBER(SEARCH("Junior",A144)),ISNUMBER(SEARCH("Jr",A144)),ISNUMBER(SEARCH("Entry",A144)),ISNUMBER(SEARCH("Associate",A144))),"Junior",IF(OR(ISNUMBER(SEARCH("Manager",A144)),ISNUMBER(SEARCH("Director",A144)),ISNUMBER(SEARCH("Head",A144)),ISNUMBER(SEARCH("VP",A144))),"Management","Mid-Level"))) -> Mid-Level | C144: =IF(ISNUMBER(SEARCH("Machine Learn",A144)),"ML Engineer",IF(ISNUMBER(SEARCH("Data Engineer",A144)),"Data Engineer",IF(ISNUMBER(SEARCH("Data Analyst",A144)),"Data Analyst",IF(ISNUMBER(SEARCH("Business Analyst",A144)),"Business Analyst",IF(ISNUMBER(SEARCH("Research",A144)),"Research Scientist",IF(ISNUMBER(SEARCH("Manager",A144)),"DS Manager",IF(ISNUMBER(SEARCH("Director",A144)),"Director/VP","Data Scientist"))))))) -> Data Analyst | D144: 4.3 | E144: San Francisco, CA | F144: =IFERROR(LEFT(E144, FIND(",", E144)-1), E144) -> San Francisco | G144: 51 - 200 | H144: Real Estate | I144: 71 | J144: 136 | K144: 103.5 | L144: =IF(K144<50,"<$50K",IF(K144<75,"$50–75K",IF(K144<100,"$75–100K",IF(K144<125,"$100–125K",IF(K144<150,"$125–150K",">$150K"))))) -> $100–125K | M144: 8
A145: Senior Research Scientist - Embedded System Development for DevOps | B145: =IF(OR(ISNUMBER(SEARCH("Senior",A145)),ISNUMBER(SEARCH("Sr",A145)),ISNUMBER(SEARCH("Lead",A145)),ISNUMBER(SEARCH("Principal",A145))),"Senior",IF(OR(ISNUMBER(SEARCH("Junior",A145)),ISNUMBER(SEARCH("Jr",A145)),ISNUMBER(SEARCH("Entry",A145)),ISNUMBER(SEARCH("Associate",A145))),"Junior",IF(OR(ISNUMBER(SEARCH("Manager",A145)),ISNUMBER(SEARCH("Director",A145)),ISNUMBER(SEARCH("Head",A145)),ISNUMBER(SEARCH("VP",A145))),"Management","Mid-Level"))) -> Senior | C145: =IF(ISNUMBER(SEARCH("Machine Learn",A145)),"ML Engineer",IF(ISNUMBER(SEARCH("Data Engineer",A145)),"Data Engineer",IF(ISNUMBER(SEARCH("Data Analyst",A145)),"Data Analyst",IF(ISNUMBER(SEARCH("Business Analyst",A145)),"Business Analyst",IF(ISNUMBER(SEARCH("Research",A145)),"Research Scientist",IF(ISNUMBER(SEARCH("Manager",A145)),"DS Manager",IF(ISNUMBER(SEARCH("Director",A145)),"Director/VP","Data Scientist"))))))) -> Research Scientist | D145: 2.6 | E145: Pittsburgh, PA | F145: =IFERROR(LEFT(E145, FIND(",", E145)-1), E145) -> Pittsburgh | G145: 501 - 1000 | H145: Colleges & Universities | I145: 81 | J145: 167 | K145: 124 | L145: =IF(K145<50,"<$50K",IF(K145<75,"$50–75K",IF(K145<100,"$75–100K",IF(K145<125,"$100–125K",IF(K145<150,"$125–150K",">$150K"))))) -> $100–125K | M145: 37
A146: Data Scientist - Bioinformatics | B146: =IF(OR(ISNUMBER(SEARCH("Senior",A146)),ISNUMBER(SEARCH("Sr",A146)),ISNUMBER(SEARCH("Lead",A146)),ISNUMBER(SEARCH("Principal",A146))),"Senior",IF(OR(ISNUMBER(SEARCH("Junior",A146)),ISNUMBER(SEARCH("Jr",A146)),ISNUMBER(SEARCH("Entry",A146)),ISNUMBER(SEARCH("Associate",A146))),"Junior",IF(OR(ISNUMBER(SEARCH("Manager",A146)),ISNUMBER(SEARCH("Director",A146)),ISNUMBER(SEARCH("Head",A146)),ISNUMBER(SEARCH("VP",A146))),"Management","Mid-Level"))) -> Mid-Level | C146: =IF(ISNUMBER(SEARCH("Machine Learn",A146)),"ML Engineer",IF(ISNUMBER(SEARCH("Data Engineer",A146)),"Data Engineer",IF(ISNUMBER(SEARCH("Data Analyst",A146)),"Data Analyst",IF(ISNUMBER(SEARCH("Business Analyst",A146)),"Business Analyst",IF(ISNUMBER(SEARCH("Research",A146)),"Research Scientist",IF(ISNUMBER(SEARCH("Manager",A146)),"DS Manager",IF(ISNUMBER(SEARCH("Director",A146)),"Director/VP","Data Scientist"))))))) -> Data Scientist | D146: 3.8 | E146: Richland, WA | F146: =IFERROR(LEFT(E146, FIND(",", E146)-1), E146) -> Richland | G146: 1001 - 5000 | H146: Energy | I146: 49 | J146: 85 | K146: 67 | L146: =IF(K146<50,"<$50K",IF(K146<75,"$50–75K",IF(K146<100,"$75–100K",IF(K146<125,"$100–125K",IF(K146<150,"$125–150K",">$150K"))))) -> $50–75K | M146: 56
A147: Data Engineer | B147: =IF(OR(ISNUMBER(SEARCH("Senior",A147)),ISNUMBER(SEARCH("Sr",A147)),ISNUMBER(SEARCH("Lead",A147)),ISNUMBER(SEARCH("Principal",A147))),"Senior",IF(OR(ISNUMBER(SEARCH("Junior",A147)),ISNUMBER(SEARCH("Jr",A147)),ISNUMBER(SEARCH("Entry",A147)),ISNUMBER(SEARCH("Associate",A147))),"Junior",IF(OR(ISNUMBER(SEARCH("Manager",A147)),ISNUMBER(SEARCH("Director",A147)),ISNUMBER(SEARCH("Head",A147)),ISNUMBER(SEARCH("VP",A147))),"Management","Mid-Level"))) -> Mid-Level | C147: =IF(ISNUMBER(SEARCH("Machine Learn",A147)),"ML Engineer",IF(ISNUMBER(SEARCH("Data Engineer",A147)),"Data Engineer",IF(ISNUMBER(SEARCH("Data Analyst",A147)),"Data Analyst",IF(ISNUMBER(SEARCH("Business Analyst",A147)),"Business Analyst",IF(ISNUMBER(SEARCH("Research",A147)),"Research Scientist",IF(ISNUMBER(SEARCH("Manager",A147)),"DS Manager",IF(ISNUMBER(SEARCH("Director",A147)),"Director/VP","Data Scientist"))))))) -> Data Engineer | D147: 3.9 | E147: Washington, DC | F147: =IFERROR(LEFT(E147, FIND(",", E147)-1), E147) -> Washington | G147: 10000+ | H147: IT Services | I147: 60 | J147: 114 | K147: 87 | L147: =IF(K147<50,"<$50K",IF(K147<75,"$50–75K",IF(K147<100,"$75–100K",IF(K147<125,"$100–125K",IF(K147<150,"$125–150K",">$150K"))))) -> $75–100K | M147: 21
A148: Customer Data Scientist/Sales Engineer | B148: =IF(OR(ISNUMBER(SEARCH("Senior",A148)),ISNUMBER(SEARCH("Sr",A148)),ISNUMBER(SEARCH("Lead",A148)),ISNUMBER(SEARCH("Principal",A148))),"Senior",IF(OR(ISNUMBER(SEARCH("Junior",A148)),ISNUMBER(SEARCH("Jr",A148)),ISNUMBER(SEARCH("Entry",A148)),ISNUMBER(SEARCH("Associate",A148))),"Junior",IF(OR(ISNUMBER(SEARCH("Manager",A148)),ISNUMBER(SEARCH("Director",A148)),ISNUMBER(SEARCH("Head",A148)),ISNUMBER(SEARCH("VP",A148))),"Management","Mid-Level"))) -> Mid-Level | C148: =IF(ISNUMBER(SEARCH("Machine Learn",A148)),"ML Engineer",IF(ISNUMBER(SEARCH("Data Engineer",A148)),"Data Engineer",IF(ISNUMBER(SEARCH("Data Analyst",A148)),"Data Analyst",IF(ISNUMBER(SEARCH("Business Analyst",A148)),"Business Analyst",IF(ISNUMBER(SEARCH("Research",A148)),"Research Scientist",IF(ISNUMBER(SEARCH("Manager",A148)),"DS Manager",IF(ISNUMBER(SEARCH("Director",A148)),"Director/VP","Data Scientist"))))))) -> Data Scientist | D148: 4.3 | E148: Chicago, IL | F148: =IFERROR(LEFT(E148, FIND(",", E148)-1), E148) -> Chicago | G148: 201 - 500 | H148: Enterprise Software & Network Solutions | I148: 71 | J148: 204 | K148: 137.5 | L148: =IF(K148<50,"<$50K",IF(K148<75,"$50–75K",IF(K148<100,"$75–100K",IF(K148<125,"$100–125K",IF(K148<150,"$125–150K",">$150K"))))) -> $125–150K | M148: 10
... A242: Data Scientist | B242: =IF(OR(ISNUMBER(SEARCH("Senior",A242)),ISNUMBER(SEARCH("Sr",A242)),ISNUMBER(SEARCH("Lead",A242)),ISNUMBER(SEARCH("Principal",A242))),"Senior",IF(OR(ISNUMBER(SEARCH("Junior",A242)),ISNUMBER(SEARCH("Jr",A242)),ISNUMBER(SEARCH("Entry",A242)),ISNUMBER(SEARCH("Associate",A242))),"Junior",IF(OR(ISNUMBER(SEARCH("Manager",A242)),ISNUMBER(SEARCH("Director",A242)),ISNUMBER(SEARCH("Head",A242)),ISNUMBER(SEARCH("VP",A242))),"Management","Mid-Level"))) -> Mid-Level | C242: =IF(ISNUMBER(SEARCH("Machine Learn",A242)),"ML Engineer",IF(ISNUMBER(SEARCH("Data Engineer",A242)),"Data Engineer",IF(ISNUMBER(SEARCH("Data Analyst",A242)),"Data Analyst",IF(ISNUMBER(SEARCH("Business Analyst",A242)),"Business Analyst",IF(ISNUMBER(SEARCH("Research",A242)),"Research Scientist",IF(ISNUMBER(SEARCH("Manager",A242)),"DS Manager",IF(ISNUMBER(SEARCH("Director",A242)),"Director/VP","Data Scientist"))))))) -> Data Scientist | D242: 3.9 | E242: Port Washington, NY | F242: =IFERROR(LEFT(E242, FIND(",", E242)-1), E242) -> Port Washington | G242: 1001 - 5000 | H242: Research & Development | I242: 15 | J242: 16 | K242: 15.5 | L242: =IF(K242<50,"<$50K",IF(K242<75,"$50–75K",IF(K242<100,"$75–100K",IF(K242<125,"$100–125K",IF(K242<150,"$125–150K",">$150K"))))) -> <$50K | M242: 55
A243: Data Scientist | B243: =IF(OR(ISNUMBER(SEARCH("Senior",A243)),ISNUMBER(SEARCH("Sr",A243)),ISNUMBER(SEARCH("Lead",A243)),ISNUMBER(SEARCH("Principal",A243))),"Senior",IF(OR(ISNUMBER(SEARCH("Junior",A243)),ISNUMBER(SEARCH("Jr",A243)),ISNUMBER(SEARCH("Entry",A243)),ISNUMBER(SEARCH("Associate",A243))),"Junior",IF(OR(ISNUMBER(SEARCH("Manager",A243)),ISNUMBER(SEARCH("Director",A243)),ISNUMBER(SEARCH("Head",A243)),ISNUMBER(SEARCH("VP",A243))),"Management","Mid-Level"))) -> Mid-Level | C243: =IF(ISNUMBER(SEARCH("Machine Learn",A243)),"ML Engineer",IF(ISNUMBER(SEARCH("Data Engineer",A243)),"Data Engineer",IF(ISNUMBER(SEARCH("Data Analyst",A243)),"Data Analyst",IF(ISNUMBER(SEARCH("Business Analyst",A243)),"Business Analyst",IF(ISNUMBER(SEARCH("Research",A243)),"Research Scientist",IF(ISNUMBER(SEARCH("Manager",A243)),"DS Manager",IF(ISNUMBER(SEARCH("Director",A243)),"Director/VP","Data Scientist"))))))) -> Data Scientist | D243: 4.3 | E243: Austin, TX | F243: =IFERROR(LEFT(E243, FIND(",", E243)-1), E243) -> Austin | G243: 18264 | H243: Advertising & Marketing | I243: 61 | J243: 106 | K243: 83.5 | L243: =IF(K243<50,"<$50K",IF(K243<75,"$50–75K",IF(K243<100,"$75–100K",IF(K243<125,"$100–125K",IF(K243<150,"$125–150K",">$150K"))))) -> $75–100K | M243: 11
A244: Risk and Analytics IT, Data Scientist | B244: =IF(OR(ISNUMBER(SEARCH("Senior",A244)),ISNUMBER(SEARCH("Sr",A244)),ISNUMBER(SEARCH("Lead",A244)),ISNUMBER(SEARCH("Principal",A244))),"Senior",IF(OR(ISNUMBER(SEARCH("Junior",A244)),ISNUMBER(SEARCH("Jr",A244)),ISNUMBER(SEARCH("Entry",A244)),ISNUMBER(SEARCH("Associate",A244))),"Junior",IF(OR(ISNUMBER(SEARCH("Manager",A244)),ISNUMBER(SEARCH("Director",A244)),ISNUMBER(SEARCH("Head",A244)),ISNUMBER(SEARCH("VP",A244))),"Management","Mid-Level"))) -> Mid-Level | C244: =IF(ISNUMBER(SEARCH("Machine Learn",A244)),"ML Engineer",IF(ISNUMBER(SEARCH("Data Engineer",A244)),"Data Engineer",IF(ISNUMBER(SEARCH("Data Analyst",A244)),"Data Analyst",IF(ISNUMBER(SEARCH("Business Analyst",A244)),"Business Analyst",IF(ISNUMBER(SEARCH("Research",A244)),"Research Scientist",IF(ISNUMBER(SEARCH("Manager",A244)),"DS Manager",IF(ISNUMBER(SEARCH("Director",A244)),"Director/VP","Data Scientist"))))))) -> Data Scientist | D244: 2.7 | E244: Madison, WI | F244: =IFERROR(LEFT(E244, FIND(",", E244)-1), E244) -> Madison | G244: 51 - 200 | H244: Investment Banking & Asset Management | I244: 91 | J244: 149 | K244: 120 | L244: =IF(K244<50,"<$50K",IF(K244<75,"$50–75K",IF(K244<100,"$75–100K",IF(K244<125,"$100–125K",IF(K244<150,"$125–150K",">$150K"))))) -> $100–125K | M244: 70
A245: Data Scientist | B245: =IF(OR(ISNUMBER(SEARCH("Senior",A245)),ISNUMBER(SEARCH("Sr",A245)),ISNUMBER(SEARCH("Lead",A245)),ISNUMBER(SEARCH("Principal",A245))),"Senior",IF(OR(ISNUMBER(SEARCH("Junior",A245)),ISNUMBER(SEARCH("Jr",A245)),ISNUMBER(SEARCH("Entry",A245)),ISNUMBER(SEARCH("Associate",A245))),"Junior",IF(OR(ISNUMBER(SEARCH("Manager",A245)),ISNUMBER(SEARCH("Director",A245)),ISNUMBER(SEARCH("Head",A245)),ISNUMBER(SEARCH("VP",A245))),"Management","Mid-Level"))) -> Mid-Level | C245: =IF(ISNUMBER(SEARCH("Machine Learn",A245)),"ML Engineer",IF(ISNUMBER(SEARCH("Data Engineer",A245)),"Data Engineer",IF(ISNUMBER(SEARCH("Data Analyst",A245)),"Data Analyst",IF(ISNUMBER(SEARCH("Business Analyst",A245)),"Business Analyst",IF(ISNUMBER(SEARCH("Research",A245)),"Research Scientist",IF(ISNUMBER(SEARCH("Manager",A245)),"DS Manager",IF(ISNUMBER(SEARCH("Director",A245)),"Director/VP","Data Scientist"))))))) -> Data Scientist | D245: 3.9 | E245: South San Francisco, CA | F245: =IFERROR(LEFT(E245, FIND(",", E245)-1), E245) -> South San Francisco | G245: 10000+ | H245: Biotech & Pharmaceuticals | I245: 127 | J245: 199 | K245: 163 | L245: =IF(K245<50,"<$50K",IF(K245<75,"$50–75K",IF(K245<100,"$75–100K",IF(K245<125,"$100–125K",IF(K245<150,"$125–150K",">$150K"))))) -> >$150K | M245: 45
A246: Lead Health Data Analyst - Front End | B246: =IF(OR(ISNUMBER(SEARCH("Senior",A246)),ISNUMBER(SEARCH("Sr",A246)),ISNUMBER(SEARCH("Lead",A246)),ISNUMBER(SEARCH("Principal",A246))),"Senior",IF(OR(ISNUMBER(SEARCH("Junior",A246)),ISNUMBER(SEARCH("Jr",A246)),ISNUMBER(SEARCH("Entry",A246)),ISNUMBER(SEARCH("Associate",A246))),"Junior",IF(OR(ISNUMBER(SEARCH("Manager",A246)),ISNUMBER(SEARCH("Director",A246)),ISNUMBER(SEARCH("Head",A246)),ISNUMBER(SEARCH("VP",A246))),"Management","Mid-Level"))) -> Senior | C246: =IF(ISNUMBER(SEARCH("Machine Learn",A246)),"ML Engineer",IF(ISNUMBER(SEARCH("Data Engineer",A246)),"Data Engineer",IF(ISNUMBER(SEARCH("Data Analyst",A246)),"Data Analyst",IF(ISNUMBER(SEARCH("Business Analyst",A246)),"Business Analyst",IF(ISNUMBER(SEARCH("Research",A246)),"Research Scientist",IF(ISNUMBER(SEARCH("Manager",A246)),"DS Manager",IF(ISNUMBER(SEARCH("Director",A246)),"Director/VP","Data Scientist"))))))) -> Data Analyst | D246: 3.4 | E246: Providence, RI | F246: =IFERROR(LEFT(E246, FIND(",", E246)-1), E246) -> Providence | G246: 501 - 1000 | H246: Insurance Carriers | I246: 74 | J246: 126 | K246: 100 | L246: =IF(K246<50,"<$50K",IF(K246<75,"$50–75K",IF(K246<100,"$75–100K",IF(K246<125,"$100–125K",IF(K246<150,"$125–150K",">$150K"))))) -> $100–125K | M246: 82
A247: Research Scientist | B247: =IF(OR(ISNUMBER(SEARCH("Senior",A247)),ISNUMBER(SEARCH("Sr",A247)),ISNUMBER(SEARCH("Lead",A247)),ISNUMBER(SEARCH("Principal",A247))),"Senior",IF(OR(ISNUMBER(SEARCH("Junior",A247)),ISNUMBER(SEARCH("Jr",A247)),ISNUMBER(SEARCH("Entry",A247)),ISNUMBER(SEARCH("Associate",A247))),"Junior",IF(OR(ISNUMBER(SEARCH("Manager",A247)),ISNUMBER(SEARCH("Director",A247)),ISNUMBER(SEARCH("Head",A247)),ISNUMBER(SEARCH("VP",A247))),"Management","Mid-Level"))) -> Mid-Level | C247: =IF(ISNUMBER(SEARCH("Machine Learn",A247)),"ML Engineer",IF(ISNUMBER(SEARCH("Data Engineer",A247)),"Data Engineer",IF(ISNUMBER(SEARCH("Data Analyst",A247)),"Data Analyst",IF(ISNUMBER(SEARCH("Business Analyst",A247)),"Business Analyst",IF(ISNUMBER(SEARCH("Research",A247)),"Research Scientist",IF(ISNUMBER(SEARCH("Manager",A247)),"DS Manager",IF(ISNUMBER(SEARCH("Director",A247)),"Director/VP","Data Scientist"))))))) -> Research Scientist | D247: 3.8 | E247: Omaha, NE | F247: =IFERROR(LEFT(E247, FIND(",", E247)-1), E247) -> Omaha | G247: 1001 - 5000 | H247: Social Assistance | I247: 33 | J247: 72 | K247: 52.5 | L247: =IF(K247<50,"<$50K",IF(K247<75,"$50–75K",IF(K247<100,"$75–100K",IF(K247<125,"$100–125K",IF(K247<150,"$125–150K",">$150K"))))) -> $50–75K | M247: 104
A248: Medical Lab Scientist | B248: =IF(OR(ISNUMBER(SEARCH("Senior",A248)),ISNUMBER(SEARCH("Sr",A248)),ISNUMBER(SEARCH("Lead",A248)),ISNUMBER(SEARCH("Principal",A248))),"Senior",IF(OR(ISNUMBER(SEARCH("Junior",A248)),ISNUMBER(SEARCH("Jr",A248)),ISNUMBER(SEARCH("Entry",A248)),ISNUMBER(SEARCH("Associate",A248))),"Junior",IF(OR(ISNUMBER(SEARCH("Manager",A248)),ISNUMBER(SEARCH("Director",A248)),ISNUMBER(SEARCH("Head",A248)),ISNUMBER(SEARCH("VP",A248))),"Management","Mid-Level"))) -> Mid-Level | C248: =IF(ISNUMBER(SEARCH("Machine Learn",A248)),"ML Engineer",IF(ISNUMBER(SEARCH("Data Engineer",A248)),"Data Engineer",IF(ISNUMBER(SEARCH("Data Analyst",A248)),"Data Analyst",IF(ISNUMBER(SEARCH("Business Analyst",A248)),"Business Analyst",IF(ISNUMBER(SEARCH("Research",A248)),"Research Scientist",IF(ISNUMBER(SEARCH("Manager",A248)),"DS Manager",IF(ISNUMBER(SEARCH("Director",A248)),"Director/VP","Data Scientist"))))))) -> Data Scientist | D248: 3.6 | E248: West Reading, PA | F248: =IFERROR(LEFT(E248, FIND(",", E248)-1), E248) -> West Reading | G248: 5001 - 10000 | H248: Health Care Services & Hospitals | I248: 35 | J248: 49 | K248: 42 | L248: =IF(K248<50,"<$50K",IF(K248<75,"$50–75K",IF(K248<100,"$75–100K",IF(K248<125,"$100–125K",IF(K248<150,"$125–150K",">$150K"))))) -> <$50K | M248: 4
A249: Junior Data Analyst | B249: =IF(OR(ISNUMBER(SEARCH("Senior",A249)),ISNUMBER(SEARCH("Sr",A249)),ISNUMBER(SEARCH("Lead",A249)),ISNUMBER(SEARCH("Principal",A249))),"Senior",IF(OR(ISNUMBER(SEARCH("Junior",A249)),ISNUMBER(SEARCH("Jr",A249)),ISNUMBER(SEARCH("Entry",A249)),ISNUMBER(SEARCH("Associate",A249))),"Junior",IF(OR(ISNUMBER(SEARCH("Manager",A249)),ISNUMBER(SEARCH("Director",A249)),ISNUMBER(SEARCH("Head",A249)),ISNUMBER(SEARCH("VP",A249))),"Management","Mid-Level"))) -> Junior | C249: =IF(ISNUMBER(SEARCH("Machine Learn",A249)),"ML Engineer",IF(ISNUMBER(SEARCH("Data Engineer",A249)),"Data Engineer",IF(ISNUMBER(SEARCH("Data Analyst",A249)),"Data Analyst",IF(ISNUMBER(SEARCH("Business Analyst",A249)),"Business Analyst",IF(ISNUMBER(SEARCH("Research",A249)),"Research Scientist",IF(ISNUMBER(SEARCH("Manager",A249)),"DS Manager",IF(ISNUMBER(SEARCH("Director",A249)),"Director/VP","Data Scientist"))))))) -> Data Analyst | D249: 3.3 | E249: Washington, DC | F249: =IFERROR(LEFT(E249, FIND(",", E249)-1), E249) -> Washington | G249: 501 - 1000 | H249: Health Care Services & Hospitals | I249: 37 | J249: 63 | K249: 50 | L249: =IF(K249<50,"<$50K",IF(K249<75,"$50–75K",IF(K249<100,"$75–100K",IF(K249<125,"$100–125K",IF(K249<150,"$125–150K",">$150K"))))) -> $50–75K | M249: 138
A250: SQL Data Engineer | B250: =IF(OR(ISNUMBER(SEARCH("Senior",A250)),ISNUMBER(SEARCH("Sr",A250)),ISNUMBER(SEARCH("Lead",A250)),ISNUMBER(SEARCH("Principal",A250))),"Senior",IF(OR(ISNUMBER(SEARCH("Junior",A250)),ISNUMBER(SEARCH("Jr",A250)),ISNUMBER(SEARCH("Entry",A250)),ISNUMBER(SEARCH("Associate",A250))),"Junior",IF(OR(ISNUMBER(SEARCH("Manager",A250)),ISNUMBER(SEARCH("Director",A250)),ISNUMBER(SEARCH("Head",A250)),ISNUMBER(SEARCH("VP",A250))),"Management","Mid-Level"))) -> Mid-Level | C250: =IF(ISNUMBER(SEARCH("Machine Learn",A250)),"ML Engineer",IF(ISNUMBER(SEARCH("Data Engineer",A250)),"Data Engineer",IF(ISNUMBER(SEARCH("Data Analyst",A250)),"Data Analyst",IF(ISNUMBER(SEARCH("Business Analyst",A250)),"Business Analyst",IF(ISNUMBER(SEARCH("Research",A250)),"Research Scientist",IF(ISNUMBER(SEARCH("Manager",A250)),"DS Manager",IF(ISNUMBER(SEARCH("Director",A250)),"Director/VP","Data Scientist"))))))) -> Data Engineer | D250: 3.4 | E250: Austin, TX | F250: =IFERROR(LEFT(E250, FIND(",", E250)-1), E250) -> Austin | G250: 201 - 500 | H250: Consulting | I250: 67 | J250: 119 | K250: 93 | L250: =IF(K250<50,"<$50K",IF(K250<75,"$50–75K",IF(K250<100,"$75–100K",IF(K250<125,"$100–125K",IF(K250<150,"$125–150K",">$150K"))))) -> $75–100K | M250: 15
A251: Data Scientist | B251: =IF(OR(ISNUMBER(SEARCH("Senior",A251)),ISNUMBER(SEARCH("Sr",A251)),ISNUMBER(SEARCH("Lead",A251)),ISNUMBER(SEARCH("Principal",A251))),"Senior",IF(OR(ISNUMBER(SEARCH("Junior",A251)),ISNUMBER(SEARCH("Jr",A251)),ISNUMBER(SEARCH("Entry",A251)),ISNUMBER(SEARCH("Associate",A251))),"Junior",IF(OR(ISNUMBER(SEARCH("Manager",A251)),ISNUMBER(SEARCH("Director",A251)),ISNUMBER(SEARCH("Head",A251)),ISNUMBER(SEARCH("VP",A251))),"Management","Mid-Level"))) -> Mid-Level | C251: =IF(ISNUMBER(SEARCH("Machine Learn",A251)),"ML Engineer",IF(ISNUMBER(SEARCH("Data Engineer",A251)),"Data Engineer",IF(ISNUMBER(SEARCH("Data Analyst",A251)),"Data Analyst",IF(ISNUMBER(SEARCH("Business Analyst",A251)),"Business Analyst",IF(ISNUMBER(SEARCH("Research",A251)),"Research Scientist",IF(ISNUMBER(SEARCH("Manager",A251)),"DS Manager",IF(ISNUMBER(SEARCH("Director",A251)),"Director/VP","Data Scientist"))))))) -> Data Scientist | D251: 3 | E251: Cincinnati, OH | F251: =IFERROR(LEFT(E251, FIND(",", E251)-1), E251) -> Cincinnati | G251: 1001 - 5000 | H251: Insurance Agencies & Brokerages | I251: 72 | J251: 117 | K251: 94.5 | L251: =IF(K251<50,"<$50K",IF(K251<75,"$50–75K",IF(K251<100,"$75–100K",IF(K251<125,"$100–125K",IF(K251<150,"$125–150K",">$150K"))))) -> $75–100K | M251: 134
A252: Senior Data Scientist | B252: =IF(OR(ISNUMBER(SEARCH("Senior",A252)),ISNUMBER(SEARCH("Sr",A252)),ISNUMBER(SEARCH("Lead",A252)),ISNUMBER(SEARCH("Principal",A252))),"Senior",IF(OR(ISNUMBER(SEARCH("Junior",A252)),ISNUMBER(SEARCH("Jr",A252)),ISNUMBER(SEARCH("Entry",A252)),ISNUMBER(SEARCH("Associate",A252))),"Junior",IF(OR(ISNUMBER(SEARCH("Manager",A252)),ISNUMBER(SEARCH("Director",A252)),ISNUMBER(SEARCH("Head",A252)),ISNUMBER(SEARCH("VP",A252))),"Management","Mid-Level"))) -> Senior | C252: =IF(ISNUMBER(SEARCH("Machine Learn",A252)),"ML Engineer",IF(ISNUMBER(SEARCH("Data Engineer",A252)),"Data Engineer",IF(ISNUMBER(SEARCH("Data Analyst",A252)),"Data Analyst",IF(ISNUMBER(SEARCH("Business Analyst",A252)),"Business Analyst",IF(ISNUMBER(SEARCH("Research",A252)),"Research Scientist",IF(ISNUMBER(SEARCH("Manager",A252)),"DS Manager",IF(ISNUMBER(SEARCH("Director",A252)),"Director/VP","Data Scientist"))))))) -> Data Scientist | D252: 4 | E252: San Francisco, CA | F252: =IFERROR(LEFT(E252, FIND(",", E252)-1), E252) -> San Francisco | G252: 5001 - 10000 | H252: Computer Hardware & Software | I252: 116 | J252: 185 | K252: 150.5 | L252: =IF(K252<50,"<$50K",IF(K252<75,"$50–75K",IF(K252<100,"$75–100K",IF(K252<125,"$100–125K",IF(K252<150,"$125–150K",">$150K"))))) -> >$150K | M252: 39
A253: Data Scientist | B253: =IF(OR(ISNUMBER(SEARCH("Senior",A253)),ISNUMBER(SEARCH("Sr",A253)),ISNUMBER(SEARCH("Lead",A253)),ISNUMBER(SEARCH("Principal",A253))),"Senior",IF(OR(ISNUMBER(SEARCH("Junior",A253)),ISNUMBER(SEARCH("Jr",A253)),ISNUMBER(SEARCH("Entry",A253)),ISNUMBER(SEARCH("Associate",A253))),"Junior",IF(OR(ISNUMBER(SEARCH("Manager",A253)),ISNUMBER(SEARCH("Director",A253)),ISNUMBER(SEARCH("Head",A253)),ISNUMBER(SEARCH("VP",A253))),"Management","Mid-Level"))) -> Mid-Level | C253: =IF(ISNUMBER(SEARCH("Machine Learn",A253)),"ML Engineer",IF(ISNUMBER(SEARCH("Data Engineer",A253)),"Data Engineer",IF(ISNUMBER(SEARCH("Data Analyst",A253)),"Data Analyst",IF(ISNUMBER(SEARCH("Business Analyst",A253)),"Business Analyst",IF(ISNUMBER(SEARCH("Research",A253)),"Research Scientist",IF(ISNUMBER(SEARCH("Manager",A253)),"DS Manager",IF(ISNUMBER(SEARCH("Director",A253)),"Director/VP","Data Scientist"))))))) -> Data Scientist | D253: 3.7 | E253: Raleigh, NC | F253: =IFERROR(LEFT(E253, FIND(",", E253)-1), E253) -> Raleigh | G253: 1001 - 5000 | H253: Insurance Carriers | I253: 78 | J253: 126 | K253: 102 | L253: =IF(K253<50,"<$50K",IF(K253<75,"$50–75K",IF(K253<100,"$75–100K",IF(K253<125,"$100–125K",IF(K253<150,"$125–150K",">$150K"))))) -> $100–125K | M253: 17
A254: Scientist, Analytical Development | B254: =IF(OR(ISNUMBER(SEARCH("Senior",A254)),ISNUMBER(SEARCH("Sr",A254)),ISNUMBER(SEARCH("Lead",A254)),ISNUMBER(SEARCH("Principal",A254))),"Senior",IF(OR(ISNUMBER(SEARCH("Junior",A254)),ISNUMBER(SEARCH("Jr",A254)),ISNUMBER(SEARCH("Entry",A254)),ISNUMBER(SEARCH("Associate",A254))),"Junior",IF(OR(ISNUMBER(SEARCH("Manager",A254)),ISNUMBER(SEARCH("Director",A254)),ISNUMBER(SEARCH("Head",A254)),ISNUMBER(SEARCH("VP",A254))),"Management","Mid-Level"))) -> Mid-Level | C254: =IF(ISNUMBER(SEARCH("Machine Learn",A254)),"ML Engineer",IF(ISNUMBER(SEARCH("Data Engineer",A254)),"Data Engineer",IF(ISNUMBER(SEARCH("Data Analyst",A254)),"Data Analyst",IF(ISNUMBER(SEARCH("Business Analyst",A254)),"Business Analyst",IF(ISNUMBER(SEARCH("Research",A254)),"Research Scientist",IF(ISNUMBER(SEARCH("Manager",A254)),"DS Manager",IF(ISNUMBER(SEARCH("Director",A254)),"Director/VP","Data Scientist"))))))) -> Data Scientist | D254: 4.4 | E254: Cambridge, MA | F254: =IFERROR(LEFT(E254, FIND(",", E254)-1), E254) -> Cambridge | G254: 201 - 500 | H254: Biotech & Pharmaceuticals | I254: 42 | J254: 82 | K254: 62 | L254: =IF(K254<50,"<$50K",IF(K254<75,"$50–75K",IF(K254<100,"$75–100K",IF(K254<125,"$100–125K",IF(K254<150,"$125–150K",">$150K"))))) -> $50–75K | M254: 8
A255: Analytics Manager | B255: =IF(OR(ISNUMBER(SEARCH("Senior",A255)),ISNUMBER(SEARCH("Sr",A255)),ISNUMBER(SEARCH("Lead",A255)),ISNUMBER(SEARCH("Principal",A255))),"Senior",IF(OR(ISNUMBER(SEARCH("Junior",A255)),ISNUMBER(SEARCH("Jr",A255)),ISNUMBER(SEARCH("Entry",A255)),ISNUMBER(SEARCH("Associate",A255))),"Junior",IF(OR(ISNUMBER(SEARCH("Manager",A255)),ISNUMBER(SEARCH("Director",A255)),ISNUMBER(SEARCH("Head",A255)),ISNUMBER(SEARCH("VP",A255))),"Management","Mid-Level"))) -> Management | C255: =IF(ISNUMBER(SEARCH("Machine Learn",A255)),"ML Engineer",IF(ISNUMBER(SEARCH("Data Engineer",A255)),"Data Engineer",IF(ISNUMBER(SEARCH("Data Analyst",A255)),"Data Analyst",IF(ISNUMBER(SEARCH("Business Analyst",A255)),"Business Analyst",IF(ISNUMBER(SEARCH("Research",A255)),"Research Scientist",IF(ISNUMBER(SEARCH("Manager",A255)),"DS Manager",IF(ISNUMBER(SEARCH("Director",A255)),"Director/VP","Data Scientist"))))))) -> DS Manager | D255: 4.3 | E255: Dearborn, MI | F255: =IFERROR(LEFT(E255, FIND(",", E255)-1), E255) -> Dearborn | G255: 201 - 500 | H255: Advertising & Marketing | I255: 59 | J255: 116 | K255: 87.5 | L255: =IF(K255<50,"<$50K",IF(K255<75,"$50–75K",IF(K255<100,"$75–100K",IF(K255<125,"$100–125K",IF(K255<150,"$125–150K",">$150K"))))) -> $75–100K | M255: 54
... A257: Data Scientist | B257: =IF(OR(ISNUMBER(SEARCH("Senior",A257)),ISNUMBER(SEARCH("Sr",A257)),ISNUMBER(SEARCH("Lead",A257)),ISNUMBER(SEARCH("Principal",A257))),"Senior",IF(OR(ISNUMBER(SEARCH("Junior",A257)),ISNUMBER(SEARCH("Jr",A257)),ISNUMBER(SEARCH("Entry",A257)),ISNUMBER(SEARCH("Associate",A257))),"Junior",IF(OR(ISNUMBER(SEARCH("Manager",A257)),ISNUMBER(SEARCH("Director",A257)),ISNUMBER(SEARCH("Head",A257)),ISNUMBER(SEARCH("VP",A257))),"Management","Mid-Level"))) -> Mid-Level | C257: =IF(ISNUMBER(SEARCH("Machine Learn",A257)),"ML Engineer",IF(ISNUMBER(SEARCH("Data Engineer",A257)),"Data Engineer",IF(ISNUMBER(SEARCH("Data Analyst",A257)),"Data Analyst",IF(ISNUMBER(SEARCH("Business Analyst",A257)),"Business Analyst",IF(ISNUMBER(SEARCH("Research",A257)),"Research Scientist",IF(ISNUMBER(SEARCH("Manager",A257)),"DS Manager",IF(ISNUMBER(SEARCH("Director",A257)),"Director/VP","Data Scientist"))))))) -> Data Scientist | D257: 4 | E257: Herndon, VA | F257: =IFERROR(LEFT(E257, FIND(",", E257)-1), E257) -> Herndon | G257: 501 - 1000 | H257: Enterprise Software & Network Solutions | I257: 109 | J257: 177 | K257: 143 | L257: =IF(K257<50,"<$50K",IF(K257<75,"$50–75K",IF(K257<100,"$75–100K",IF(K257<125,"$100–125K",IF(K257<150,"$125–150K",">$150K"))))) -> $125–150K | M257: 9
A258: Sr. Data Scientist, Cyber-Security LT Contract | B258: =IF(OR(ISNUMBER(SEARCH("Senior",A258)),ISNUMBER(SEARCH("Sr",A258)),ISNUMBER(SEARCH("Lead",A258)),ISNUMBER(SEARCH("Principal",A258))),"Senior",IF(OR(ISNUMBER(SEARCH("Junior",A258)),ISNUMBER(SEARCH("Jr",A258)),ISNUMBER(SEARCH("Entry",A258)),ISNUMBER(SEARCH("Associate",A258))),"Junior",IF(OR(ISNUMBER(SEARCH("Manager",A258)),ISNUMBER(SEARCH("Director",A258)),ISNUMBER(SEARCH("Head",A258)),ISNUMBER(SEARCH("VP",A258))),"Management","Mid-Level"))) -> Senior | C258: =IF(ISNUMBER(SEARCH("Machine Learn",A258)),"ML Engineer",IF(ISNUMBER(SEARCH("Data Engineer",A258)),"Data Engineer",IF(ISNUMBER(SEARCH("Data Analyst",A258)),"Data Analyst",IF(ISNUMBER(SEARCH("Business Analyst",A258)),"Business Analyst",IF(ISNUMBER(SEARCH("Research",A258)),"Research Scientist",IF(ISNUMBER(SEARCH("Manager",A258)),"DS Manager",IF(ISNUMBER(SEARCH("Director",A258)),"Director/VP","Data Scientist"))))))) -> Data Scientist | D258: 3.2 | E258: Phila, PA | F258: =IFERROR(LEFT(E258, FIND(",", E258)-1), E258) -> Phila | G258: 18264 | H258: Staffing & Outsourcing | I258: 116 | J258: 194 | K258: 155 | L258: =IF(K258<50,"<$50K",IF(K258<75,"$50–75K",IF(K258<100,"$75–100K",IF(K258<125,"$100–125K",IF(K258<150,"$125–150K",">$150K"))))) -> >$150K | M258: -1
A259: Data Engineer | B259: =IF(OR(ISNUMBER(SEARCH("Senior",A259)),ISNUMBER(SEARCH("Sr",A259)),ISNUMBER(SEARCH("Lead",A259)),ISNUMBER(SEARCH("Principal",A259))),"Senior",IF(OR(ISNUMBER(SEARCH("Junior",A259)),ISNUMBER(SEARCH("Jr",A259)),ISNUMBER(SEARCH("Entry",A259)),ISNUMBER(SEARCH("Associate",A259))),"Junior",IF(OR(ISNUMBER(SEARCH("Manager",A259)),ISNUMBER(SEARCH("Director",A259)),ISNUMBER(SEARCH("Head",A259)),ISNUMBER(SEARCH("VP",A259))),"Management","Mid-Level"))) -> Mid-Level | C259: =IF(ISNUMBER(SEARCH("Machine Learn",A259)),"ML Engineer",IF(ISNUMBER(SEARCH("Data Engineer",A259)),"Data Engineer",IF(ISNUMBER(SEARCH("Data Analyst",A259)),"Data Analyst",IF(ISNUMBER(SEARCH("Business Analyst",A259)),"Business Analyst",IF(ISNUMBER(SEARCH("Research",A259)),"Research Scientist",IF(ISNUMBER(SEARCH("Manager",A259)),"DS Manager",IF(ISNUMBER(SEARCH("Director",A259)),"Director/VP","Data Scientist"))))))) -> Data Engineer | D259: 4.2 | E259: Winter Park, FL | F259: =IFERROR(LEFT(E259, FIND(",", E259)-1), E259) -> Winter Park | G259: 51 - 200 | H259: Advertising & Marketing | I259: 48 | J259: 95 | K259: 71.5 | L259: =IF(K259<50,"<$50K",IF(K259<75,"$50–75K",IF(K259<100,"$75–100K",IF(K259<125,"$100–125K",IF(K259<150,"$125–150K",">$150K"))))) -> $50–75K | M259: 15
A260: Data Scientist | B260: =IF(OR(ISNUMBER(SEARCH("Senior",A260)),ISNUMBER(SEARCH("Sr",A260)),ISNUMBER(SEARCH("Lead",A260)),ISNUMBER(SEARCH("Principal",A260))),"Senior",IF(OR(ISNUMBER(SEARCH("Junior",A260)),ISNUMBER(SEARCH("Jr",A260)),ISNUMBER(SEARCH("Entry",A260)),ISNUMBER(SEARCH("Associate",A260))),"Junior",IF(OR(ISNUMBER(SEARCH("Manager",A260)),ISNUMBER(SEARCH("Director",A260)),ISNUMBER(SEARCH("Head",A260)),ISNUMBER(SEARCH("VP",A260))),"Management","Mid-Level"))) -> Mid-Level | C260: =IF(ISNUMBER(SEARCH("Machine Learn",A260)),"ML Engineer",IF(ISNUMBER(SEARCH("Data Engineer",A260)),"Data Engineer",IF(ISNUMBER(SEARCH("Data Analyst",A260)),"Data Analyst",IF(ISNUMBER(SEARCH("Business Analyst",A260)),"Business Analyst",IF(ISNUMBER(SEARCH("Research",A260)),"Research Scientist",IF(ISNUMBER(SEARCH("Manager",A260)),"DS Manager",IF(ISNUMBER(SEARCH("Director",A260)),"Director/VP","Data Scientist"))))))) -> Data Scientist | D260: 3.9 | E260: Oakland, CA | F260: =IFERROR(LEFT(E260, FIND(",", E260)-1), E260) -> Oakland | G260: 51 - 200 | H260: Insurance Carriers | I260: 83 | J260: 133 | K260: 108 | L260: =IF(K260<50,"<$50K",IF(K260<75,"$50–75K",IF(K260<100,"$75–100K",IF(K260<125,"$100–125K",IF(K260<150,"$125–150K",">$150K"))))) -> $100–125K | M260: 21
A261: Sr. Scientist - Digital & Image Analysis/Computational Pathology | B261: =IF(OR(ISNUMBER(SEARCH("Senior",A261)),ISNUMBER(SEARCH("Sr",A261)),ISNUMBER(SEARCH("Lead",A261)),ISNUMBER(SEARCH("Principal",A261))),"Senior",IF(OR(ISNUMBER(SEARCH("Junior",A261)),ISNUMBER(SEARCH("Jr",A261)),ISNUMBER(SEARCH("Entry",A261)),ISNUMBER(SEARCH("Associate",A261))),"Junior",IF(OR(ISNUMBER(SEARCH("Manager",A261)),ISNUMBER(SEARCH("Director",A261)),ISNUMBER(SEARCH("Head",A261)),ISNUMBER(SEARCH("VP",A261))),"Management","Mid-Level"))) -> Senior | C261: =IF(ISNUMBER(SEARCH("Machine Learn",A261)),"ML Engineer",IF(ISNUMBER(SEARCH("Data Engineer",A261)),"Data Engineer",IF(ISNUMBER(SEARCH("Data Analyst",A261)),"Data Analyst",IF(ISNUMBER(SEARCH("Business Analyst",A261)),"Business Analyst",IF(ISNUMBER(SEARCH("Research",A261)),"Research Scientist",IF(ISNUMBER(SEARCH("Manager",A261)),"DS Manager",IF(ISNUMBER(SEARCH("Director",A261)),"Director/VP","Data Scientist"))))))) -> Data Scientist | D261: 3.7 | E261: San Diego, CA | F261: =IFERROR(LEFT(E261, FIND(",", E261)-1), E261) -> San Diego | G261: 10000+ | H261: Biotech & Pharmaceuticals | I261: 105 | J261: 198 | K261: 151.5 | L261: =IF(K261<50,"<$50K",IF(K261<75,"$50–75K",IF(K261<100,"$75–100K",IF(K261<125,"$100–125K",IF(K261<150,"$125–150K",">$150K"))))) -> >$150K | M261: 240
A262: Digital Marketing & ECommerce Data Analyst | B262: =IF(OR(ISNUMBER(SEARCH("Senior",A262)),ISNUMBER(SEARCH("Sr",A262)),ISNUMBER(SEARCH("Lead",A262)),ISNUMBER(SEARCH("Principal",A262))),"Senior",IF(OR(ISNUMBER(SEARCH("Junior",A262)),ISNUMBER(SEARCH("Jr",A262)),ISNUMBER(SEARCH("Entry",A262)),ISNUMBER(SEARCH("Associate",A262))),"Junior",IF(OR(ISNUMBER(SEARCH("Manager",A262)),ISNUMBER(SEARCH("Director",A262)),ISNUMBER(SEARCH("Head",A262)),ISNUMBER(SEARCH("VP",A262))),"Management","Mid-Level"))) -> Mid-Level | C262: =IF(ISNUMBER(SEARCH("Machine Learn",A262)),"ML Engineer",IF(ISNUMBER(SEARCH("Data Engineer",A262)),"Data Engineer",IF(ISNUMBER(SEARCH("Data Analyst",A262)),"Data Analyst",IF(ISNUMBER(SEARCH("Business Analyst",A262)),"Business Analyst",IF(ISNUMBER(SEARCH("Research",A262)),"Research Scientist",IF(ISNUMBER(SEARCH("Manager",A262)),"DS Manager",IF(ISNUMBER(SEARCH("Director",A262)),"Director/VP","Data Scientist"))))))) -> Data Analyst | D262: 3.6 | E262: San Rafael, CA | F262: =IFERROR(LEFT(E262, FIND(",", E262)-1), E262) -> San Rafael | G262: 51 - 200 | H262: Department, Clothing, & Shoe Stores | I262: 31 | J262: 72 | K262: 51.5 | L262: =IF(K262<50,"<$50K",IF(K262<75,"$50–75K",IF(K262<100,"$75–100K",IF(K262<125,"$100–125K",IF(K262<150,"$125–150K",">$150K"))))) -> $50–75K | M262: 15
A263: Principal Scientist - Immunologist | B263: =IF(OR(ISNUMBER(SEARCH("Senior",A263)),ISNUMBER(SEARCH("Sr",A263)),ISNUMBER(SEARCH("Lead",A263)),ISNUMBER(SEARCH("Principal",A263))),"Senior",IF(OR(ISNUMBER(SEARCH("Junior",A263)),ISNUMBER(SEARCH("Jr",A263)),ISNUMBER(SEARCH("Entry",A263)),ISNUMBER(SEARCH("Associate",A263))),"Junior",IF(OR(ISNUMBER(SEARCH("Manager",A263)),ISNUMBER(SEARCH("Director",A263)),ISNUMBER(SEARCH("Head",A263)),ISNUMBER(SEARCH("VP",A263))),"Management","Mid-Level"))) -> Senior | C263: =IF(ISNUMBER(SEARCH("Machine Learn",A263)),"ML Engineer",IF(ISNUMBER(SEARCH("Data Engineer",A263)),"Data Engineer",IF(ISNUMBER(SEARCH("Data Analyst",A263)),"Data Analyst",IF(ISNUMBER(SEARCH("Business Analyst",A263)),"Business Analyst",IF(ISNUMBER(SEARCH("Research",A263)),"Research Scientist",IF(ISNUMBER(SEARCH("Manager",A263)),"DS Manager",IF(ISNUMBER(SEARCH("Director",A263)),"Director/VP","Data Scientist"))))))) -> Data Scientist | D263: 3.7 | E263: Boston, MA | F263: =IFERROR(LEFT(E263, FIND(",", E263)-1), E263) -> Boston | G263: 10000+ | H263: Biotech & Pharmaceuticals | I263: 98 | J263: 182 | K263: 140 | L263: =IF(K263<50,"<$50K",IF(K263<75,"$50–75K",IF(K263<100,"$75–100K",IF(K263<125,"$100–125K",IF(K263<150,"$125–150K",">$150K"))))) -> $125–150K | M263: 240
A264: Senior Data Analyst | B264: =IF(OR(ISNUMBER(SEARCH("Senior",A264)),ISNUMBER(SEARCH("Sr",A264)),ISNUMBER(SEARCH("Lead",A264)),ISNUMBER(SEARCH("Principal",A264))),"Senior",IF(OR(ISNUMBER(SEARCH("Junior",A264)),ISNUMBER(SEARCH("Jr",A264)),ISNUMBER(SEARCH("Entry",A264)),ISNUMBER(SEARCH("Associate",A264))),"Junior",IF(OR(ISNUMBER(SEARCH("Manager",A264)),ISNUMBER(SEARCH("Director",A264)),ISNUMBER(SEARCH("Head",A264)),ISNUMBER(SEARCH("VP",A264))),"Management","Mid-Level"))) -> Senior | C264: =IF(ISNUMBER(SEARCH("Machine Learn",A264)),"ML Engineer",IF(ISNUMBER(SEARCH("Data Engineer",A264)),"Data Engineer",IF(ISNUMBER(SEARCH("Data Analyst",A264)),"Data Analyst",IF(ISNUMBER(SEARCH("Business Analyst",A264)),"Business Analyst",IF(ISNUMBER(SEARCH("Research",A264)),"Research Scientist",IF(ISNUMBER(SEARCH("Manager",A264)),"DS Manager",IF(ISNUMBER(SEARCH("Director",A264)),"Director/VP","Data Scientist"))))))) -> Data Analyst | D264: 2.8 | E264: Hamilton, NJ | F264: =IFERROR(LEFT(E264, FIND(",", E264)-1), E264) -> Hamilton | G264: 201 - 500 | H264: IT Services | I264: 55 | J264: 100 | K264: 77.5 | L264: =IF(K264<50,"<$50K",IF(K264<75,"$50–75K",IF(K264<100,"$75–100K",IF(K264<125,"$100–125K",IF(K264<150,"$125–150K",">$150K"))))) -> $75–100K | M264: 7
A265: Insurance Financial Data Analyst | B265: =IF(OR(ISNUMBER(SEARCH("Senior",A265)),ISNUMBER(SEARCH("Sr",A265)),ISNUMBER(SEARCH("Lead",A265)),ISNUMBER(SEARCH("Principal",A265))),"Senior",IF(OR(ISNUMBER(SEARCH("Junior",A265)),ISNUMBER(SEARCH("Jr",A265)),ISNUMBER(SEARCH("Entry",A265)),ISNUMBER(SEARCH("Associate",A265))),"Junior",IF(OR(ISNUMBER(SEARCH("Manager",A265)),ISNUMBER(SEARCH("Director",A265)),ISNUMBER(SEARCH("Head",A265)),ISNUMBER(SEARCH("VP",A265))),"Management","Mid-Level"))) -> Mid-Level | C265: =IF(ISNUMBER(SEARCH("Machine Learn",A265)),"ML Engineer",IF(ISNUMBER(SEARCH("Data Engineer",A265)),"Data Engineer",IF(ISNUMBER(SEARCH("Data Analyst",A265)),"Data Analyst",IF(ISNUMBER(SEARCH("Business Analyst",A265)),"Business Analyst",IF(ISNUMBER(SEARCH("Research",A265)),"Research Scientist",IF(ISNUMBER(SEARCH("Manager",A265)),"DS Manager",IF(ISNUMBER(SEARCH("Director",A265)),"Director/VP","Data Scientist"))))))) -> Data Analyst | D265: 4.2 | E265: Boise, ID | F265: =IFERROR(LEFT(E265, FIND(",", E265)-1), E265) -> Boise | G265: 501 - 1000 | H265: Investment Banking & Asset Management | I265: 45 | J265: 82 | K265: 63.5 | L265: =IF(K265<50,"<$50K",IF(K265<75,"$50–75K",IF(K265<100,"$75–100K",IF(K265<125,"$100–125K",IF(K265<150,"$125–150K",">$150K"))))) -> $50–75K | M265: 17
A266: Data Scientist | B266: =IF(OR(ISNUMBER(SEARCH("Senior",A266)),ISNUMBER(SEARCH("Sr",A266)),ISNUMBER(SEARCH("Lead",A266)),ISNUMBER(SEARCH("Principal",A266))),"Senior",IF(OR(ISNUMBER(SEARCH("Junior",A266)),ISNUMBER(SEARCH("Jr",A266)),ISNUMBER(SEARCH("Entry",A266)),ISNUMBER(SEARCH("Associate",A266))),"Junior",IF(OR(ISNUMBER(SEARCH("Manager",A266)),ISNUMBER(SEARCH("Director",A266)),ISNUMBER(SEARCH("Head",A266)),ISNUMBER(SEARCH("VP",A266))),"Management","Mid-Level"))) -> Mid-Level | C266: =IF(ISNUMBER(SEARCH("Machine Learn",A266)),"ML Engineer",IF(ISNUMBER(SEARCH("Data Engineer",A266)),"Data Engineer",IF(ISNUMBER(SEARCH("Data Analyst",A266)),"Data Analyst",IF(ISNUMBER(SEARCH("Business Analyst",A266)),"Business Analyst",IF(ISNUMBER(SEARCH("Research",A266)),"Research Scientist",IF(ISNUMBER(SEARCH("Manager",A266)),"DS Manager",IF(ISNUMBER(SEARCH("Director",A266)),"Director/VP","Data Scientist"))))))) -> Data Scientist | D266: 4 | E266: San Francisco, CA | F266: =IFERROR(LEFT(E266, FIND(",", E266)-1), E266) -> San Francisco | G266: 18264 | H266: IT Services | I266: 83 | J266: 135 | K266: 109 | L266: =IF(K266<50,"<$50K",IF(K266<75,"$50–75K",IF(K266<100,"$75–100K",IF(K266<125,"$100–125K",IF(K266<150,"$125–150K",">$150K"))))) -> $100–125K | M266: -1
A267: Data Scientist | B267: =IF(OR(ISNUMBER(SEARCH("Senior",A267)),ISNUMBER(SEARCH("Sr",A267)),ISNUMBER(SEARCH("Lead",A267)),ISNUMBER(SEARCH("Principal",A267))),"Senior",IF(OR(ISNUMBER(SEARCH("Junior",A267)),ISNUMBER(SEARCH("Jr",A267)),ISNUMBER(SEARCH("Entry",A267)),ISNUMBER(SEARCH("Associate",A267))),"Junior",IF(OR(ISNUMBER(SEARCH("Manager",A267)),ISNUMBER(SEARCH("Director",A267)),ISNUMBER(SEARCH("Head",A267)),ISNUMBER(SEARCH("VP",A267))),"Management","Mid-Level"))) -> Mid-Level | C267: =IF(ISNUMBER(SEARCH("Machine Learn",A267)),"ML Engineer",IF(ISNUMBER(SEARCH("Data Engineer",A267)),"Data Engineer",IF(ISNUMBER(SEARCH("Data Analyst",A267)),"Data Analyst",IF(ISNUMBER(SEARCH("Business Analyst",A267)),"Business Analyst",IF(ISNUMBER(SEARCH("Research",A267)),"Research Scientist",IF(ISNUMBER(SEARCH("Manager",A267)),"DS Manager",IF(ISNUMBER(SEARCH("Director",A267)),"Director/VP","Data Scientist"))))))) -> Data Scientist | D267: 3.5 | E267: Oak Ridge, TN | F267: =IFERROR(LEFT(E267, FIND(",", E267)-1), E267) -> Oak Ridge | G267: 5001 - 10000 | H267: Aerospace & Defense | I267: 70 | J267: 122 | K267: 96 | L267: =IF(K267<50,"<$50K",IF(K267<75,"$50–75K",IF(K267<100,"$75–100K",IF(K267<125,"$100–125K",IF(K267<150,"$125–150K",">$150K"))))) -> $75–100K | M267: 171
A268: Principal Data Scientist with over 10 years experience | B268: =IF(OR(ISNUMBER(SEARCH("Senior",A268)),ISNUMBER(SEARCH("Sr",A268)),ISNUMBER(SEARCH("Lead",A268)),ISNUMBER(SEARCH("Principal",A268))),"Senior",IF(OR(ISNUMBER(SEARCH("Junior",A268)),ISNUMBER(SEARCH("Jr",A268)),ISNUMBER(SEARCH("Entry",A268)),ISNUMBER(SEARCH("Associate",A268))),"Junior",IF(OR(ISNUMBER(SEARCH("Manager",A268)),ISNUMBER(SEARCH("Director",A268)),ISNUMBER(SEARCH("Head",A268)),ISNUMBER(SEARCH("VP",A268))),"Management","Mid-Level"))) -> Senior | C268: =IF(ISNUMBER(SEARCH("Machine Learn",A268)),"ML Engineer",IF(ISNUMBER(SEARCH("Data Engineer",A268)),"Data Engineer",IF(ISNUMBER(SEARCH("Data Analyst",A268)),"Data Analyst",IF(ISNUMBER(SEARCH("Business Analyst",A268)),"Business Analyst",IF(ISNUMBER(SEARCH("Research",A268)),"Research Scientist",IF(ISNUMBER(SEARCH("Manager",A268)),"DS Manager",IF(ISNUMBER(SEARCH("Director",A268)),"Director/VP","Data Scientist"))))))) -> Data Scientist | D268: -1 | E268: San Francisco, CA | F268: =IFERROR(LEFT(E268, FIND(",", E268)-1), E268) -> San Francisco | G268: 51 - 200 | H268: IT Services | I268: 200 | J268: 250 | K268: 225 | L268: =IF(K268<50,"<$50K",IF(K268<75,"$50–75K",IF(K268<100,"$75–100K",IF(K268<125,"$100–125K",IF(K268<150,"$125–150K",">$150K"))))) -> >$150K | M268: 4
A269: Data Engineer | B269: =IF(OR(ISNUMBER(SEARCH("Senior",A269)),ISNUMBER(SEARCH("Sr",A269)),ISNUMBER(SEARCH("Lead",A269)),ISNUMBER(SEARCH("Principal",A269))),"Senior",IF(OR(ISNUMBER(SEARCH("Junior",A269)),ISNUMBER(SEARCH("Jr",A269)),ISNUMBER(SEARCH("Entry",A269)),ISNUMBER(SEARCH("Associate",A269))),"Junior",IF(OR(ISNUMBER(SEARCH("Manager",A269)),ISNUMBER(SEARCH("Director",A269)),ISNUMBER(SEARCH("Head",A269)),ISNUMBER(SEARCH("VP",A269))),"Management","Mid-Level"))) -> Mid-Level | C269: =IF(ISNUMBER(SEARCH("Machine Learn",A269)),"ML Engineer",IF(ISNUMBER(SEARCH("Data Engineer",A269)),"Data Engineer",IF(ISNUMBER(SEARCH("Data Analyst",A269)),"Data Analyst",IF(ISNUMBER(SEARCH("Business Analyst",A269)),"Business Analyst",IF(ISNUMBER(SEARCH("Research",A269)),"Research Scientist",IF(ISNUMBER(SEARCH("Manager",A269)),"DS Manager",IF(ISNUMBER(SEARCH("Director",A269)),"Director/VP","Data Scientist"))))))) -> Data Engineer | D269: 3.2 | E269: Agoura Hills, CA | F269: =IFERROR(LEFT(E269, FIND(",", E269)-1), E269) -> Agoura Hills | G269: 1001 - 5000 | H269: Lending | I269: 70 | J269: 132 | K269: 101 | L269: =IF(K269<50,"<$50K",IF(K269<75,"$50–75K",IF(K269<100,"$75–100K",IF(K269<125,"$100–125K",IF(K269<150,"$125–150K",">$150K"))))) -> $100–125K | M269: 13
A270: Senior Data Scientist | B270: =IF(OR(ISNUMBER(SEARCH("Senior",A270)),ISNUMBER(SEARCH("Sr",A270)),ISNUMBER(SEARCH("Lead",A270)),ISNUMBER(SEARCH("Principal",A270))),"Senior",IF(OR(ISNUMBER(SEARCH("Junior",A270)),ISNUMBER(SEARCH("Jr",A270)),ISNUMBER(SEARCH("Entry",A270)),ISNUMBER(SEARCH("Associate",A270))),"Junior",IF(OR(ISNUMBER(SEARCH("Manager",A270)),ISNUMBER(SEARCH("Director",A270)),ISNUMBER(SEARCH("Head",A270)),ISNUMBER(SEARCH("VP",A270))),"Management","Mid-Level"))) -> Senior | C270: =IF(ISNUMBER(SEARCH("Machine Learn",A270)),"ML Engineer",IF(ISNUMBER(SEARCH("Data Engineer",A270)),"Data Engineer",IF(ISNUMBER(SEARCH("Data Analyst",A270)),"Data Analyst",IF(ISNUMBER(SEARCH("Business Analyst",A270)),"Business Analyst",IF(ISNUMBER(SEARCH("Research",A270)),"Research Scientist",IF(ISNUMBER(SEARCH("Manager",A270)),"DS Manager",IF(ISNUMBER(SEARCH("Director",A270)),"Director/VP","Data Scientist"))))))) -> Data Scientist | D270: 3.3 | E270: Woodbridge, NJ | F270: =IFERROR(LEFT(E270, FIND(",", E270)-1), E270) -> Woodbridge | G270: 1001 - 5000 | H270: Insurance Carriers | I270: 73 | J270: 124 | K270: 98.5 | L270: =IF(K270<50,"<$50K",IF(K270<75,"$50–75K",IF(K270<100,"$75–100K",IF(K270<125,"$100–125K",IF(K270<150,"$125–150K",">$150K"))))) -> $75–100K | M270: 39
A271: Data Engineer I - Azure | B271: =IF(OR(ISNUMBER(SEARCH("Senior",A271)),ISNUMBER(SEARCH("Sr",A271)),ISNUMBER(SEARCH("Lead",A271)),ISNUMBER(SEARCH("Principal",A271))),"Senior",IF(OR(ISNUMBER(SEARCH("Junior",A271)),ISNUMBER(SEARCH("Jr",A271)),ISNUMBER(SEARCH("Entry",A271)),ISNUMBER(SEARCH("Associate",A271))),"Junior",IF(OR(ISNUMBER(SEARCH("Manager",A271)),ISNUMBER(SEARCH("Director",A271)),ISNUMBER(SEARCH("Head",A271)),ISNUMBER(SEARCH("VP",A271))),"Management","Mid-Level"))) -> Mid-Level | C271: =IF(ISNUMBER(SEARCH("Machine Learn",A271)),"ML Engineer",IF(ISNUMBER(SEARCH("Data Engineer",A271)),"Data Engineer",IF(ISNUMBER(SEARCH("Data Analyst",A271)),"Data Analyst",IF(ISNUMBER(SEARCH("Business Analyst",A271)),"Business Analyst",IF(ISNUMBER(SEARCH("Research",A271)),"Research Scientist",IF(ISNUMBER(SEARCH("Manager",A271)),"DS Manager",IF(ISNUMBER(SEARCH("Director",A271)),"Director/VP","Data Scientist"))))))) -> Data Engineer | D271: 3.9 | E271: Pella, IA | F271: =IFERROR(LEFT(E271, FIND(",", E271)-1), E271) -> Pella | G271: 1001 - 5000 | H271: Industrial Manufacturing | I271: 54 | J271: 101 | K271: 77.5 | L271: =IF(K271<50,"<$50K",IF(K271<75,"$50–75K",IF(K271<100,"$75–100K",IF(K271<125,"$100–125K",IF(K271<150,"$125–150K",">$150K"))))) -> $75–100K | M271: 73
...

Sheet RatingScatter
A1: Rating | B1: Avg Salary(K) | C1: Rating Band
A2: 3.8 | B2: 72 | C2: =IF(A2<3,"Under 3.0",IF(A2<3.5,"3.0–3.5",IF(A2<4,"3.5–4.0",IF(A2<4.5,"4.0–4.5","4.5+")))) -> 3.5–4.0
A3: 3.4 | B3: 87.5 | C3: =IF(A3<3,"Under 3.0",IF(A3<3.5,"3.0–3.5",IF(A3<4,"3.5–4.0",IF(A3<4.5,"4.0–4.5","4.5+")))) -> 3.0–3.5
A4: 4.8 | B4: 85 | C4: =IF(A4<3,"Under 3.0",IF(A4<3.5,"3.0–3.5",IF(A4<4,"3.5–4.0",IF(A4<4.5,"4.0–4.5","4.5+")))) -> 4.5+
A5: 3.8 | B5: 76.5 | C5: =IF(A5<3,"Under 3.0",IF(A5<3.5,"3.0–3.5",IF(A5<4,"3.5–4.0",IF(A5<4.5,"4.0–4.5","4.5+")))) -> 3.5–4.0
A6: 2.9 | B6: 114.5 | C6: =IF(A6<3,"Under 3.0",IF(A6<3.5,"3.0–3.5",IF(A6<4,"3.5–4.0",IF(A6<4.5,"4.0–4.5","4.5+")))) -> Under 3.0
A7: 3.4 | B7: 95 | C7: =IF(A7<3,"Under 3.0",IF(A7<3.5,"3.0–3.5",IF(A7<4,"3.5–4.0",IF(A7<4.5,"4.0–4.5","4.5+")))) -> 3.0–3.5
A8: 4.1 | B8: 73.5 | C8: =IF(A8<3,"Under 3.0",IF(A8<3.5,"3.0–3.5",IF(A8<4,"3.5–4.0",IF(A8<4.5,"4.0–4.5","4.5+")))) -> 4.0–4.5
A9: 3.8 | B9: 114 | C9: =IF(A9<3,"Under 3.0",IF(A9<3.5,"3.0–3.5",IF(A9<4,"3.5–4.0",IF(A9<4.5,"4.0–4.5","4.5+")))) -> 3.5–4.0
A10: 3.3 | B10: 61 | C10: =IF(A10<3,"Under 3.0",IF(A10<3.5,"3.0–3.5",IF(A10<4,"3.5–4.0",IF(A10<4.5,"4.0–4.5","4.5+")))) -> 3.0–3.5
A11: 4.6 | B11: 140 | C11: =IF(A11<3,"Under 3.0",IF(A11<3.5,"3.0–3.5",IF(A11<4,"3.5–4.0",IF(A11<4.5,"4.0–4.5","4.5+")))) -> 4.5+
A12: 3.5 | B12: 163.5 | C12: =IF(A12<3,"Under 3.0",IF(A12<3.5,"3.0–3.5",IF(A12<4,"3.5–4.0",IF(A12<4.5,"4.0–4.5","4.5+")))) -> 3.5–4.0
A13: 4.1 | B13: 85 | C13: =IF(A13<3,"Under 3.0",IF(A13<3.5,"3.0–3.5",IF(A13<4,"3.5–4.0",IF(A13<4.5,"4.0–4.5","4.5+")))) -> 4.0–4.5
... A177: 3.3 | B177: 98.5 | C177: =IF(A177<3,"Under 3.0",IF(A177<3.5,"3.0–3.5",IF(A177<4,"3.5–4.0",IF(A177<4.5,"4.0–4.5","4.5+")))) -> 3.0–3.5
A178: -1 | B178: 225
A179: 3.6 | B179: 56.5 | C179: =IF(A179<3,"Under 3.0",IF(A179<3.5,"3.0–3.5",IF(A179<4,"3.5–4.0",IF(A179<4.5,"4.0–4.5","4.5+")))) -> 3.5–4.0
A180: 3.7 | B180: 161.5 | C180: =IF(A180<3,"Under 3.0",IF(A180<3.5,"3.0–3.5",IF(A180<4,"3.5–4.0",IF(A180<4.5,"4.0–4.5","4.5+")))) -> 3.5–4.0
A181: 3.4 | B181: 147 | C181: =IF(A181<3,"Under 3.0",IF(A181<3.5,"3.0–3.5",IF(A181<4,"3.5–4.0",IF(A181<4.5,"4.0–4.5","4.5+")))) -> 3.0–3.5
A182: 4.1 | B182: 61 | C182: =IF(A182<3,"Under 3.0",IF(A182<3.5,"3.0–3.5",IF(A182<4,"3.5–4.0",IF(A182<4.5,"4.0–4.5","4.5+")))) -> 4.0–4.5
A183: 2.6 | B183: 120 | C183: =IF(A183<3,"Under 3.0",IF(A183<3.5,"3.0–3.5",IF(A183<4,"3.5–4.0",IF(A183<4.5,"4.0–4.5","4.5+")))) -> Under 3.0
A184: 3.2 | B184: 124.5 | C184: =IF(A184<3,"Under 3.0",IF(A184<3.5,"3.0–3.5",IF(A184<4,"3.5–4.0",IF(A184<4.5,"4.0–4.5","4.5+")))) -> 3.0–3.5
A185: 3.9 | B185: 148 | C185: =IF(A185<3,"Under 3.0",IF(A185<3.5,"3.0–3.5",IF(A185<4,"3.5–4.0",IF(A185<4.5,"4.0–4.5","4.5+")))) -> 3.5–4.0
A186: 4.7 | B186: 59 | C186: =IF(A186<3,"Under 3.0",IF(A186<3.5,"3.0–3.5",IF(A186<4,"3.5–4.0",IF(A186<4.5,"4.0–4.5","4.5+")))) -> 4.5+
A187: 3.7 | B187: 146.5 | C187: =IF(A187<3,"Under 3.0",IF(A187<3.5,"3.0–3.5",IF(A187<4,"3.5–4.0",IF(A187<4.5,"4.0–4.5","4.5+")))) -> 3.5–4.0
A188: 2.9 | B188: 91.5 | C188: =IF(A188<3,"Under 3.0",IF(A188<3.5,"3.0–3.5",IF(A188<4,"3.5–4.0",IF(A188<4.5,"4.0–4.5","4.5+")))) -> Under 3.0
A189: 3 | B189: 133 | C189: =IF(A189<3,"Under 3.0",IF(A189<3.5,"3.0–3.5",IF(A189<4,"3.5–4.0",IF(A189<4.5,"4.0–4.5","4.5+")))) -> 3.0–3.5
A190: 4.7 | B190: 140.5 | C190: =IF(A190<3,"Under 3.0",IF(A190<3.5,"3.0–3.5",IF(A190<4,"3.5–4.0",IF(A190<4.5,"4.0–4.5","4.5+")))) -> 4.5+
... A267: 3.5 | B267: 96 | C267: =IF(A267<3,"Under 3.0",IF(A267<3.5,"3.0–3.5",IF(A267<4,"3.5–4.0",IF(A267<4.5,"4.0–4.5","4.5+")))) -> 3.5–4.0
A268: -1 | B268: 225
A269: 3.2 | B269: 101 | C269: =IF(A269<3,"Under 3.0",IF(A269<3.5,"3.0–3.5",IF(A269<4,"3.5–4.0",IF(A269<4.5,"4.0–4.5","4.5+")))) -> 3.0–3.5
A270: 3.3 | B270: 98.5 | C270: =IF(A270<3,"Under 3.0",IF(A270<3.5,"3.0–3.5",IF(A270<4,"3.5–4.0",IF(A270<4.5,"4.0–4.5","4.5+")))) -> 3.0–3.5
A271: 3.9 | B271: 77.5 | C271: =IF(A271<3,"Under 3.0",IF(A271<3.5,"3.0–3.5",IF(A271<4,"3.5–4.0",IF(A271<4.5,"4.0–4.5","4.5+")))) -> 3.5–4.0
A272: 3.7 | B272: 161.5 | C272: =IF(A272<3,"Under 3.0",IF(A272<3.5,"3.0–3.5",IF(A272<4,"3.5–4.0",IF(A272<4.5,"4.0–4.5","4.5+")))) -> 3.5–4.0
A273: 3.6 | B273: 56.5 | C273: =IF(A273<3,"Under 3.0",IF(A273<3.5,"3.0–3.5",IF(A273<4,"3.5–4.0",IF(A273<4.5,"4.0–4.5","4.5+")))) -> 3.5–4.0
A274: 3.4 | B274: 147 | C274: =IF(A274<3,"Under 3.0",IF(A274<3.5,"3.0–3.5",IF(A274<4,"3.5–4.0",IF(A274<4.5,"4.0–4.5","4.5+")))) -> 3.0–3.5
A275: 3.5 | B275: 90 | C275: =IF(A275<3,"Under 3.0",IF(A275<3.5,"3.0–3.5",IF(A275<4,"3.5–4.0",IF(A275<4.5,"4.0–4.5","4.5+")))) -> 3.5–4.0
A276: 4.3 | B276: 58 | C276: =IF(A276<3,"Under 3.0",IF(A276<3.5,"3.0–3.5",IF(A276<4,"3.5–4.0",IF(A276<4.5,"4.0–4.5","4.5+")))) -> 4.0–4.5
A277: 4.1 | B277: 61 | C277: =IF(A277<3,"Under 3.0",IF(A277<3.5,"3.0–3.5",IF(A277<4,"3.5–4.0",IF(A277<4.5,"4.0–4.5","4.5+")))) -> 4.0–4.5
A278: 2.6 | B278: 120 | C278: =IF(A278<3,"Under 3.0",IF(A278<3.5,"3.0–3.5",IF(A278<4,"3.5–4.0",IF(A278<4.5,"4.0–4.5","4.5+")))) -> Under 3.0
A279: 3.6 | B279: 128 | C279: =IF(A279<3,"Under 3.0",IF(A279<3.5,"3.0–3.5",IF(A279<4,"3.5–4.0",IF(A279<4.5,"4.0–4.5","4.5+")))) -> 3.5–4.0
A280: 3.5 | B280: 99.5 | C280: =IF(A280<3,"Under 3.0",IF(A280<3.5,"3.0–3.5",IF(A280<4,"3.5–4.0",IF(A280<4.5,"4.0–4.5","4.5+")))) -> 3.5–4.0
... A301: 3.9 | B301: 60 | C301: =IF(A301<3,"Under 3.0",IF(A301<3.5,"3.0–3.5",IF(A301<4,"3.5–4.0",IF(A301<4.5,"4.0–4.5","4.5+")))) -> 3.5–4.0
A302: -1 | B302: 87.5
A303: 4.4 | B303: 90.5 | C303: =IF(A303<3,"Under 3.0",IF(A303<3.5,"3.0–3.5",IF(A303<4,"3.5–4.0",IF(A303<4.5,"4.0–4.5","4.5+")))) -> 4.0–4.5
A304: 3.8 | B304: 114.5 | C304: =IF(A304<3,"Under 3.0",IF(A304<3.5,"3.0–3.5",IF(A304<4,"3.5–4.0",IF(A304<4.5,"4.0–4.5","4.5+")))) -> 3.5–4.0
A305: 3.8 | B305: 121 | C305: =IF(A305<3,"Under 3.0",IF(A305<3.5,"3.0–3.5",IF(A305<4,"3.5–4.0",IF(A305<4.5,"4.0–4.5","4.5+")))) -> 3.5–4.0
A306: 2.2 | B306: 110 | C306: =IF(A306<3,"Under 3.0",IF(A306<3.5,"3.0–3.5",IF(A306<4,"3.5–4.0",IF(A306<4.5,"4.0–4.5","4.5+")))) -> Under 3.0
A307: 2.9 | B307: 91.5 | C307: =IF(A307<3,"Under 3.0",IF(A307<3.5,"3.0–3.5",IF(A307<4,"3.5–4.0",IF(A307<4.5,"4.0–4.5","4.5+")))) -> Under 3.0
A308: 4.1 | B308: 70.5 | C308: =IF(A308<3,"Under 3.0",IF(A308<3.5,"3.0–3.5",IF(A308<4,"3.5–4.0",IF(A308<4.5,"4.0–4.5","4.5+")))) -> 4.0–4.5
A309: 3.7 | B309: 70.5 | C309: =IF(A309<3,"Under 3.0",IF(A309<3.5,"3.0–3.5",IF(A309<4,"3.5–4.0",IF(A309<4.5,"4.0–4.5","4.5+")))) -> 3.5–4.0
A310: 3.8 | B310: 76.5 | C310: =IF(A310<3,"Under 3.0",IF(A310<3.5,"3.0–3.5",IF(A310<4,"3.5–4.0",IF(A310<4.5,"4.0–4.5","4.5+")))) -> 3.5–4.0
A311: 3.6 | B311: 92 | C311: =IF(A311<3,"Under 3.0",IF(A311<3.5,"3.0–3.5",IF(A311<4,"3.5–4.0",IF(A311<4.5,"4.0–4.5","4.5+")))) -> 3.5–4.0
A312: 4.7 | B312: 140.5 | C312: =IF(A312<3,"Under 3.0",IF(A312<3.5,"3.0–3.5",IF(A312<4,"3.5–4.0",IF(A312<4.5,"4.0–4.5","4.5+")))) -> 4.5+
A313: 3.5 | B313: 82 | C313: =IF(A313<3,"Under 3.0",IF(A313<3.5,"3.0–3.5",IF(A313<4,"3.5–4.0",IF(A313<4.5,"4.0–4.5","4.5+")))) -> 3.5–4.0
A314: 3.3 | B314: 84.5 | C314: =IF(A314<3,"Under 3.0",IF(A314<3.5,"3.0–3.5",IF(A314<4,"3.5–4.0",IF(A314<4.5,"4.0–4.5","4.5+")))) -> 3.0–3.5
... A371: 3.4 | B371: 90 | C371: =IF(A371<3,"Under 3.0",IF(A371<3.5,"3.0–3.5",IF(A371<4,"3.5–4.0",IF(A371<4.5,"4.0–4.5","4.5+")))) -> 3.0–3.5
A372: -1 | B372: 120
A373: 2.6 | B373: 73.5 | C373: =IF(A373<3,"Under 3.0",IF(A373<3.5,"3.0–3.5",IF(A373<4,"3.5–4.0",IF(A373<4.5,"4.0–4.5","4.5+")))) -> Under 3.0
A374: 3.8 | B374: 91 | C374: =IF(A374<3,"Under 3.0",IF(A374<3.5,"3.0–3.5",IF(A374<4,"3.5–4.0",IF(A374<4.5,"4.0–4.5","4.5+")))) -> 3.5–4.0
A375: 5 | B375: 155 | C375: =IF(A375<3,"Under 3.0",IF(A375<3.5,"3.0–3.5",IF(A375<4,"3.5–4.0",IF(A375<4.5,"4.0–4.5","4.5+")))) -> 4.5+
A376: 3.6 | B376: 129.5 | C376: =IF(A376<3,"Under 3.0",IF(A376<3.5,"3.0–3.5",IF(A376<4,"3.5–4.0",IF(A376<4.5,"4.0–4.5","4.5+")))) -> 3.5–4.0
A377: 4 | B377: 167.5 | C377: =IF(A377<3,"Under 3.0",IF(A377<3.5,"3.0–3.5",IF(A377<4,"3.5–4.0",IF(A377<4.5,"4.0–4.5","4.5+")))) -> 4.0–4.5
A378: 3.8 | B378: 60 | C378: =IF(A378<3,"Under 3.0",IF(A378<3.5,"3.0–3.5",IF(A378<4,"3.5–4.0",IF(A378<4.5,"4.0–4.5","4.5+")))) -> 3.5–4.0
A379: 3.9 | B379: 180 | C379: =IF(A379<3,"Under 3.0",IF(A379<3.5,"3.0–3.5",IF(A379<4,"3.5–4.0",IF(A379<4.5,"4.0–4.5","4.5+")))) -> 3.5–4.0
A380: 3.8 | B380: 65 | C380: =IF(A380<3,"Under 3.0",IF(A380<3.5,"3.0–3.5",IF(A380<4,"3.5–4.0",IF(A380<4.5,"4.0–4.5","4.5+")))) -> 3.5–4.0
A381: 4.3 | B381: 112.5 | C381: =IF(A381<3,"Under 3.0",IF(A381<3.5,"3.0–3.5",IF(A381<4,"3.5–4.0",IF(A381<4.5,"4.0–4.5","4.5+")))) -> 4.0–4.5
A382: 1.9 | B382: 87.5 | C382: =IF(A382<3,"Under 3.0",IF(A382<3.5,"3.0–3.5",IF(A382<4,"3.5–4.0",IF(A382<4.5,"4.0–4.5","4.5+")))) -> Under 3.0
A383: 3.3 | B383: 51.5 | C383: =IF(A383<3,"Under 3.0",IF(A383<3.5,"3.0–3.5",IF(A383<4,"3.5–4.0",IF(A383<4.5,"4.0–4.5","4.5+")))) -> 3.0–3.5
A384: 4.7 | B384: 51 | C384: =IF(A384<3,"Under 3.0",IF(A384<3.5,"3.0–3.5",IF(A384<4,"3.5–4.0",IF(A384<4.5,"4.0–4.5","4.5+")))) -> 4.5+
... A405: 4.4 | B405: 140 | C405: =IF(A405<3,"Under 3.0",IF(A405<3.5,"3.0–3.5",IF(A405<4,"3.5–4.0",IF(A405<4.5,"4.0–4.5","4.5+")))) -> 4.0–4.5
A406: -1 | B406: 120
A407: 3 | B407: 66.5 | C407: =IF(A407<3,"Under 3.0",IF(A407<3.5,"3.0–3.5",IF(A407<4,"3.5–4.0",IF(A407<4.5,"4.0–4.5","4.5+")))) -> 3.0–3.5
A408: 4.7 | B408: 94.5 | C408: =IF(A408<3,"Under 3.0",IF(A408<3.5,"3.0–3.5",IF(A408<4,"3.5–4.0",IF(A408<4.5,"4.0–4.5","4.5+")))) -> 4.5+
A409: 3.8 | B409: 119 | C409: =IF(A409<3,"Under 3.0",IF(A409<3.5,"3.0–3.5",IF(A409<4,"3.5–4.0",IF(A409<4.5,"4.0–4.5","4.5+")))) -> 3.5–4.0
A410: 3.2 | B410: 51.5 | C410: =IF(A410<3,"Under 3.0",IF(A410<3.5,"3.0–3.5",IF(A410<4,"3.5–4.0",IF(A410<4.5,"4.0–4.5","4.5+")))) -> 3.0–3.5
A411: 2.7 | B411: 27.5 | C411: =IF(A411<3,"Under 3.0",IF(A411<3.5,"3.0–3.5",IF(A411<4,"3.5–4.0",IF(A411<4.5,"4.0–4.5","4.5+")))) -> Under 3.0
A412: 3.3 | B412: 194.5 | C412: =IF(A412<3,"Under 3.0",IF(A412<3.5,"3.0–3.5",IF(A412<4,"3.5–4.0",IF(A412<4.5,"4.0–4.5","4.5+")))) -> 3.0–3.5
A413: 3.9 | B413: 71.5 | C413: =IF(A413<3,"Under 3.0",IF(A413<3.5,"3.0–3.5",IF(A413<4,"3.5–4.0",IF(A413<4.5,"4.0–4.5","4.5+")))) -> 3.5–4.0
A414: 3.7 | B414: 105.5 | C414: =IF(A414<3,"Under 3.0",IF(A414<3.5,"3.0–3.5",IF(A414<4,"3.5–4.0",IF(A414<4.5,"4.0–4.5","4.5+")))) -> 3.5–4.0
A415: 3.1 | B415: 74 | C415: =IF(A415<3,"Under 3.0",IF(A415<3.5,"3.0–3.5",IF(A415<4,"3.5–4.0",IF(A415<4.5,"4.0–4.5","4.5+")))) -> 3.0–3.5
A416: 3.7 | B416: 62.5 | C416: =IF(A416<3,"Under 3.0",IF(A416<3.5,"3.0–3.5",IF(A416<4,"3.5–4.0",IF(A416<4.5,"4.0–4.5","4.5+")))) -> 3.5–4.0
A417: 4.3 | B417: 65.5 | C417: =IF(A417<3,"Under 3.0",IF(A417<3.5,"3.0–3.5",IF(A417<4,"3.5–4.0",IF(A417<4.5,"4.0–4.5","4.5+")))) -> 4.0–4.5
A418: 3.6 | B418: 161.5 | C418: =IF(A418<3,"Under 3.0",IF(A418<3.5,"3.0–3.5",IF(A418<4,"3.5–4.0",IF(A418<4.5,"4.0–4.5","4.5+")))) -> 3.5–4.0
... A457: 3.5 | B457: 80.5 | C457: =IF(A457<3,"Under 3.0",IF(A457<3.5,"3.0–3.5",IF(A457<4,"3.5–4.0",IF(A457<4.5,"4.0–4.5","4.5+")))) -> 3.5–4.0
A458: -1 | B458: 110.5
A459: 2.9 | B459: 114 | C459: =IF(A459<3,"Under 3.0",IF(A459<3.5,"3.0–3.5",IF(A459<4,"3.5–4.0",IF(A459<4.5,"4.0–4.5","4.5+")))) -> Under 3.0
A460: 3.5 | B460: 139.5 | C460: =IF(A460<3,"Under 3.0",IF(A460<3.5,"3.0–3.5",IF(A460<4,"3.5–4.0",IF(A460<4.5,"4.0–4.5","4.5+")))) -> 3.5–4.0
A461: 4.8 | B461: 145.5 | C461: =IF(A461<3,"Under 3.0",IF(A461<3.5,"3.0–3.5",IF(A461<4,"3.5–4.0",IF(A461<4.5,"4.0–4.5","4.5+")))) -> 4.5+
A462: 4 | B462: 87 | C462: =IF(A462<3,"Under 3.0",IF(A462<3.5,"3.0–3.5",IF(A462<4,"3.5–4.0",IF(A462<4.5,"4.0–4.5","4.5+")))) -> 4.0–4.5
A463: 4.2 | B463: 100.5 | C463: =IF(A463<3,"Under 3.0",IF(A463<3.5,"3.0–3.5",IF(A463<4,"3.5–4.0",IF(A463<4.5,"4.0–4.5","4.5+")))) -> 4.0–4.5
A464: 3.8 | B464: 147 | C464: =IF(A464<3,"Under 3.0",IF(A464<3.5,"3.0–3.5",IF(A464<4,"3.5–4.0",IF(A464<4.5,"4.0–4.5","4.5+")))) -> 3.5–4.0
A465: 3.7 | B465: 110.5 | C465: =IF(A465<3,"Under 3.0",IF(A465<3.5,"3.0–3.5",IF(A465<4,"3.5–4.0",IF(A465<4.5,"4.0–4.5","4.5+")))) -> 3.5–4.0
A466: 3.9 | B466: 49 | C466: =IF(A466<3,"Under 3.0",IF(A466<3.5,"3.0–3.5",IF(A466<4,"3.5–4.0",IF(A466<4.5,"4.0–4.5","4.5+")))) -> 3.5–4.0
A467: 4.6 | B467: 94 | C467: =IF(A467<3,"Under 3.0",IF(A467<3.5,"3.0–3.5",IF(A467<4,"3.5–4.0",IF(A467<4.5,"4.0–4.5","4.5+")))) -> 4.5+
A468: 4.3 | B468: 123.5 | C468: =IF(A468<3,"Under 3.0",IF(A468<3.5,"3.0–3.5",IF(A468<4,"3.5–4.0",IF(A468<4.5,"4.0–4.5","4.5+")))) -> 4.0–4.5
A469: 3.3 | B469: 84.5 | C469: =IF(A469<3,"Under 3.0",IF(A469<3.5,"3.0–3.5",IF(A469<4,"3.5–4.0",IF(A469<4.5,"4.0–4.5","4.5+")))) -> 3.0–3.5
A470: 3.7 | B470: 71 | C470: =IF(A470<3,"Under 3.0",IF(A470<3.5,"3.0–3.5",IF(A470<4,"3.5–4.0",IF(A470<4.5,"4.0–4.5","4.5+")))) -> 3.5–4.0
... A552: 3.4 | B552: 90 | C552: =IF(A552<3,"Under 3.0",IF(A552<3.5,"3.0–3.5",IF(A552<4,"3.5–4.0",IF(A552<4.5,"4.0–4.5","4.5+")))) -> 3.0–3.5
A553: -1 | B553: 120
A554: 3.9 | B554: 138.5 | C554: =IF(A554<3,"Under 3.0",IF(A554<3.5,"3.0–3.5",IF(A554<4,"3.5–4.0",IF(A554<4.5,"4.0–4.5","4.5+")))) -> 3.5–4.0
...

Sheet SizeRating
A3: Row Labels | B3: Average of Rating
A4: 51 - 200 | B4: 4.0212766
A5: 18264 | B5: 3.7354839
A6: 201 - 500 | B6: 3.6700855
A7: 10000+ | B7: 3.63
A8: 1001 - 5000 | B8: 3.5986667
A9: 501 - 1000 | B9: 3.5813433
A10: 5001 - 10000 | B10: 3.5315789
A11: unknown | B11: 0.2
A12: Grand Total | B12: 3.6188679

Sheet Size
B3: Values
A4: Row Labels | B4: Average of Avg Salary(K) | C4: Average of Lower Salary(in K) | D4: Average of Upper Salary(in K ) | E4: Count of Job Title
A5: 1001 - 5000 | B5: 94.69 | C5: 68.953333 | D5: 120.42667 | E5: 150
A6: 501 - 1000 | B6: 91.503731 | C6: 66.865672 | D6: 116.14179 | E6: 134
A7: 10000+ | B7: 112.80385 | C7: 83.661538 | D7: 141.94615 | E7: 130
A8: 201 - 500 | B8: 100.24786 | C8: 72.136752 | D8: 128.35897 | E8: 117
A9: 51 - 200 | B9: 111.77128 | C9: 84.468085 | D9: 139.07447 | E9: 94
A10: 5001 - 10000 | B10: 97.486842 | C10: 70.421053 | D10: 124.55263 | E10: 76
A11: 18264 | B11: 105.06452 | C11: 78.580645 | D11: 131.54839 | E11: 31
A12: unknown | B12: 127.05 | C12: 112.1 | D12: 142 | E12: 10
A13: Grand Total | B13: 101.4845 | C13: 74.754717 | D13: 128.21429 | E13: 742

Sheet Industry
A1: Size | B1: (All)
A2: Exp Level | B2: (All)
B4: Values
A5: Row Labels | B5: Average of Avg Salary(K) | C5: Count of Job Title
A6: Other Retail Stores | B6: 163.5 | C6: 1
A7: Motion Picture Production & Distribution | B7: 146 | C7: 1
A8: Financial Analytics & Research | B8: 145.125 | C8: 8
A9: Health, Beauty, & Fitness | B9: 139.5 | C9: 1
A10: Telecommunications Services | B10: 131.5 | C10: 4
A11: Brokerage Services | B11: 129 | C11: 2
A12: Auctions & Galleries | B12: 128 | C12: 1
A13: Internet | B13: 123.81034 | C13: 29
A14: Investment Banking & Asset Management | B14: 118.4 | C14: 5
A15: TV Broadcast & Cable Networks | B15: 117.75 | C15: 2
A16: Enterprise Software & Network Solutions | B16: 115.36905 | C16: 42
A17: Computer Hardware & Software | B17: 115.19492 | C17: 59
A18: -1 | B18: 114.65 | C18: 10
A19: Accounting | B19: 113.5 | C19: 1
A20: Biotech & Pharmaceuticals | B20: 112.12054 | C20: 112
A21: Grand Total | B21: 116.54496 | C21: 278

Sheet City Salary
A1: Size | B1: (Multiple Items)
A2: Exp Level | B2: (All)
A4: Row Labels | B4: Average of Avg Salary(K)
A5: San Francisco | B5: 175.75
A6: Jersey City | B6: 173
A7: Mountain View | B7: 172.5
A8: Novato | B8: 168
A9: San Jose | B9: 163.5
A10: Santa Clara | B10: 154.5
A11: Marlborough | B11: 150.7
A12: Newark | B12: 146
A13: Fort Lee | B13: 145.66667
A14: Natick | B14: 139.5
A15: Palo Alto | B15: 135.33333
A16: Herndon | B16: 131.75
... A20: Grand Total | B20: 146.3

Sheet CityCount
A1: Industry | B1: (All)
A3: Row Labels | B3: Count of Job Title
A4: New York | B4: 55
A5: San Francisco | B5: 49
A6: Cambridge | B6: 48
A7: Chicago | B7: 32
A8: Boston | B8: 23
A9: San Jose | B9: 13
A10: Pittsburgh | B10: 12 | K10: Row Labels | L10: Count of Count of Job Title2
A11: Rockville | B11: 11 | K11: Boston | L11: 1
A12: Washington | B12: 11 | K12: Cambridge | L12: 1
A13: Springfield | B13: 10 | K13: Chicago | L13: 1
A14: Winston-Salem | B14: 10 | K14: Grand Total | L14: 1
A15: Herndon | B15: 10 | K15: Herndon | L15: 1
A16: Richland | B16: 10 | K16: Indianapolis | L16: 1
A17: Indianapolis | B17: 9 | K17: New York | L17: 1
A18: San Diego | B18: 9 | K18: Pittsburgh | L18: 1
A19: Grand Total | B19: 312 | K19: Richland | L19: 1
K20: Rockville | L20: 1
K21: San Diego | L21: 1
K22: San Francisco | L22: 1
K23: San Jose | L23: 1
K24: Springfield | L24: 1
K25: Washington | L25: 1
K26: Winston-Salem | L26: 1
K27: Grand Total | L27: 16

Sheet Title Count
A1: Exp Level | B1: (All)
A3: Row Labels | B3: Count of Job Title
A4: Data Scientist | B4: 435
A5: Data Engineer | B5: 119
A6: Data Analyst | B6: 99
A7: ML Engineer | B7: 29
A8: DS Manager | B8: 25
A9: Research Scientist | B9: 21
A10: Director/VP | B10: 14
A11: Grand Total | B11: 742

Sheet Title Salary
A1: Exp Level | B1: (Multiple Items)
B3: Values
A4: Row Labels | B4: Average of Upper Salary(in K ) | C4: Average of Lower Salary(in K) | D4: Average of Avg Salary(K)
A5: Data Analyst | B5: 85.688889 | C5: 47.588889 | D5: 66.638889
A6: Data Engineer | B6: 133.89474 | C6: 75.72807 | D6: 104.8114
A7: Data Scientist | B7: 134.12322 | C7: 80.035545 | D7: 107.07938
A8: DS Manager | B8: 210 | C8: 125 | D8: 167.5
A9: ML Engineer | B9: 156.18519 | C9: 87.666667 | D9: 121.92593
A10: Research Scientist | B10: 118.05 | C10: 66.5 | D10: 92.275
A11: Grand Total | B11: 128.25778 | C11: 75.019259 | D11: 101.63852

Sheet Rating Band
A1: Rating Band | B1: Avg Salary(K) | C1: Job Title | E1: Values
A2: 3.5–4.0 | B2: 72 | C2: Data Scientist | D2: Row Labels | E2: Average of Avg Salary(K) | F2: Count of Job Title
A3: 3.0–3.5 | B3: 87.5 | C3: Healthcare Data Scientist | D3: Under 3.0 | E3: 87.673611 | F3: 72
A4: 4.5+ | B4: 85 | C4: Data Scientist | D4: 3.0–3.5 | E4: 97.10625 | F4: 160
A5: 3.5–4.0 | B5: 76.5 | C5: Data Scientist | D5: 3.5–4.0 | E5: 102.89107 | F5: 280
A6: Under 3.0 | B6: 114.5 | C6: Data Scientist | D6: 4.0–4.5 | E6: 106.55096 | F6: 157
A7: 3.0–3.5 | B7: 95 | C7: Data Scientist | D7: 4.5+ | E7: 103.48387 | F7: 62
A8: 4.0–4.5 | B8: 73.5 | C8: Data Scientist | D8: Grand Total | E8: 100.96238 | F8: 731
A9: 3.5–4.0 | B9: 114 | C9: Data Scientist
A10: 3.0–3.5 | B10: 61 | C10: Research Scientist
A11: 4.5+ | B11: 140 | C11: Data Scientist
A12: 3.5–4.0 | B12: 163.5 | C12: Data Scientist
A13: 4.0–4.5 | B13: 85 | C13: Data Scientist
A14: 3.0–3.5 | B14: 139 | C14: Staff Data Scientist - Technology
A15: 4.0–4.5 | B15: 65.5 | C15: Data Analyst
A16: 3.5–4.0 | B16: 113.5 | C16: Data Scientist
A17: 3.5–4.0 | B17: 146 | C17: Data Engineer I
A18: 3.5–4.0 | B18: 102 | C18: Scientist I/II, Biology
A19: 4.0–4.5 | B19: 153.5 | C19: Customer Data Scientist
A20: 4.0–4.5 | B20: 142.5 | C20: Data Scientist - Health Data Analytics
... A732: 3.5–4.0 | B732: 93.5 | C732: Research Scientist, Immunology - Cancer Biology
C733: IT - Data Engineer II
C734: Machine Learning Engineer (NLP)
C735: Senior Data Analyst
C736: Data Science Project Manager
C737: Data Engineer
C738: Principal, Data Science - Advanced Analytics
C739: Sr Scientist, Immuno-Oncology - Oncology
C740: Senior Data Engineer
C741: Project Scientist - Auton Lab, Robotics Institute
C742: Data Science Manager
C743: Research Scientist â€“ Security and Privacy

Sheet Stats
B1: Avg salary statistics
B2: Count | C2: =COUNTA(data_cleaned_2021!K:K ) -> 743
B3: Mean | C3: =AVERAGE(data_cleaned_2021!K:K) -> 101.4845
B4: Median | C4: =MEDIAN(data_cleaned_2021!K:K) -> 97.5
B5: Std Dev | C5: =STDEV(data_cleaned_2021!K:K) -> 37.482449
B6: Min | C6: =MIN(data_cleaned_2021!K:K) -> 15.5
B7: 25th Pct | C7: =PERCENTILE(data_cleaned_2021!K:K,0.25) -> 73.5
B8: 75th Pct | C8: =PERCENTILE(data_cleaned_2021!K:K,0.75) -> 122.5
B9: Max | C9: =MAX(data_cleaned_2021!K:K) -> 254
